Workbook

Sheet Batch Coverage v16
A1: CU Batch | B1: P Batch | C1: Strain | D1: Status | E1: Missing (n) | F1: 2 Identification B — Microscopy | G1: 3 Identification C — HPLC | H1: 4 Assay — Total Δ⁹-THC | I1: 5 Assay — Total CBD | J1: 6 Total CBN | K1: 7 Foreign Matter | L1: 8 Loss on Drying | M1: 9 Microbiological Purity | N1: 10 Mycotoxins | O1: 11 Heavy Metals | P1: 12 Pesticide Residues | Q1: Missing parameters | R1: Certificates (n) | S1: Labs present
A2: GG1024_02 | B2: P050012 | C2: Gorilla Glue | D2: ✓ COMPLETE | E2: 0 | F2: ✓ | G2: ✓ | H2: ✓ | I2: ✓ | J2: ✓ | K2: ✓ | L2: ✓ | M2: ✓ | N2: ✓ | O2: ✓ | P2: ✓ | Q2: — | R2: 5.0 | S2: [CNP] 1; [IJZ] 1; [IJZ-MB] 2; [PP] 1
A3: GP0824_02 | B3: P050022 | C3: Grape Pie | D3: ✓ COMPLETE | E3: 0 | F3: ✓ | G3: ✓ | H3: ✓ | I3: ✓ | J3: ✓ | K3: ✓ | L3: ✓ | M3: ✓ | N3: ✓ | O3: ✓ | P3: ✓ | Q3: — | R3: 12.0 | S3: [CNP] 5; [FHM-K] 1; [FHM-M] 1; [IJZ] 2; [IJZ-MB] 2; [PP] 1
A4: MB0824_04 | B4: P050032 | C4: Motor Breath | D4: ✓ COMPLETE | E4: 0 | F4: ✓ | G4: ✓ | H4: ✓ | I4: ✓ | J4: ✓ | K4: ✓ | L4: ✓ | M4: ✓ | N4: ✓ | O4: ✓ | P4: ✓ | Q4: — | R4: 5.0 | S4: [CNP] 1; [IJZ] 1; [IJZ-MB] 2; [PP] 1
A5: OMP1024_01 | B5: P050042 | C5: Orange Punch Mimosa | D5: ✓ COMPLETE | E5: 0 | F5: ✓ | G5: ✓ | H5: ✓ | I5: ✓ | J5: ✓ | K5: ✓ | L5: ✓ | M5: ✓ | N5: ✓ | O5: ✓ | P5: ✓ | Q5: — | R5: 4.0 | S5: [CNP] 1; [IJZ] 1; [IJZ-MB] 1; [PP] 1
A6: HPA1024_01 | B6: P050052 | C6: High Pro Amnesia | D6: ✓ COMPLETE | E6: 0 | F6: ✓ | G6: ✓ | H6: ✓ | I6: ✓ | J6: ✓ | K6: ✓ | L6: ✓ | M6: ✓ | N6: ✓ | O6: ✓ | P6: ✓ | Q6: — | R6: 6.0 | S6: [CNP] 1; [FHM-K] 1; [FHM-M] 1; [IJZ] 1; [IJZ-MB] 1; [PP] 1
A7: OPM1024_02 | B7: P050062 | C7: Orange Punch Mimosa | D7: ✓ COMPLETE | E7: 0 | F7: ✓ | G7: ✓ | H7: ✓ | I7: ✓ | J7: ✓ | K7: ✓ | L7: ✓ | M7: ✓ | N7: ✓ | O7: ✓ | P7: ✓ | Q7: — | R7: 6.0 | S7: [CNP] 1; [FHM-K] 1; [FHM-M] 1; [IJZ] 1; [IJZ-MB] 1; [PP] 1
A8: GP0824_03 | B8: P050072 | C8: Grape Pie | D8: ✓ COMPLETE | E8: 0 | F8: ✓ | G8: ✓ | H8: ✓ | I8: ✓ | J8: ✓ | K8: ✓ | L8: ✓ | M8: ✓ | N8: ✓ | O8: ✓ | P8: ✓ | Q8: — | R8: 7.0 | S8: [CNP] 4; [IJZ] 1; [IJZ-MB] 1; [PP] 1
A9: OPM1024_03 | B9: P050082 | C9: Orange Punch Mimosa | D9: ✓ COMPLETE | E9: 0 | F9: ✓ | G9: ✓ | H9: ✓ | I9: ✓ | J9: ✓ | K9: ✓ | L9: ✓ | M9: ✓ | N9: ✓ | O9: ✓ | P9: ✓ | Q9: — | R9: 4.0 | S9: [CNP] 1; [IJZ] 1; [IJZ-MB] 1; [PP] 1
A10: GG1024_01 | B10: P050092 | C10: Gorilla Glue | D10: ✓ COMPLETE | E10: 0 | F10: ✓ | G10: ✓ | H10: ✓ | I10: ✓ | J10: ✓ | K10: ✓ | L10: ✓ | M10: ✓ | N10: ✓ | O10: ✓ | P10: ✓ | Q10: — | R10: 6.0 | S10: [CNP] 1; [FHM-K] 1; [FHM-M] 1; [IJZ] 1; [IJZ-MB] 1; [PP] 1
A11: GP0824_01 | B11: P050102 | C11: Grape Pie | D11: ✓ COMPLETE | E11: 0 | F11: ✓ | G11: ✓ | H11: ✓ | I11: ✓ | J11: ✓ | K11: ✓ | L11: ✓ | M11: ✓ | N11: ✓ | O11: ✓ | P11: ✓ | Q11: — | R11: 6.0 | S11: [CNP] 1; [IJZ] 1; [IJZ-MB] 3; [PP] 1
A12: MB0824_05 | B12: P050112 | C12: Motor Breath | D12: ✓ COMPLETE | E12: 0 | F12: ✓ | G12: ✓ | H12: ✓ | I12: ✓ | J12: ✓ | K12: ✓ | L12: ✓ | M12: ✓ | N12: ✓ | O12: ✓ | P12: ✓ | Q12: — | R12: 4.0 | S12: [CNP] 1; [IJZ] 1; [IJZ-MB] 1; [PP] 1
... A41: WED102501 | B41: P060102 | C41: Wedding Cake | D41: ✓ COMPLETE | E41: 0 | F41: ✓ | G41: ✓ | H41: ✓ | I41: ✓ | J41: ✓ | K41: ✓ | L41: ✓ | M41: ✓ | N41: ✓ | O41: ✓ | P41: ✓ | Q41: — | R41: 2.0 | S41: [IJZ-MB] 2
A42: PUM102501 | B42: P060112 | C42: Pure Michigan | D42: ⚠ 3 MISSING | E42: 3 | F42: ✗ | G42: ✓ | H42: ✓ | I42: ✓ | J42: ✓ | K42: ✗ | L42: ✓ | M42: ✓ | N42: ✓ | O42: ✓ | P42: ✓ | Q42: #1 Ident. A; #2 Ident. B; #7 Foreign matter | R42: 0
A43: ACC102501 | B43: P060122 | C43: Amnesia Core Cut | D43: ⚠ 3 MISSING | E43: 3 | F43: ✗ | G43: ✓ | H43: ✓ | I43: ✓ | J43: ✓ | K43: ✗ | L43: ✓ | M43: ✓ | N43: ✓ | O43: ✓ | P43: ✓ | Q43: #1 Ident. A; #2 Ident. B; #7 Foreign matter | R43: 0
A44: CF102501 | B44: P060132 | C44: Chem Flyer | D44: ⚠ 3 MISSING | E44: 3 | F44: ✗ | G44: ✓ | H44: ✓ | I44: ✓ | J44: ✓ | K44: ✗ | L44: ✓ | M44: ✓ | N44: ✓ | O44: ✓ | P44: ✓ | Q44: #1 Ident. A; #2 Ident. B; #7 Foreign matter | R44: 0
A45: GRC102501 | B45: P060142 / P060182 | D45: ⚠ 1 MISSING | E45: 1 | F45: ✓ | G45: ✓ | H45: ✓ | I45: ✓ | J45: ✓ | K45: ✓ | L45: ✓ | M45: ✓ | N45: ✗ | O45: ✓ | P45: ✓ | Q45: #10 Mycotoxins | R45: 5.0 | S45: [FHM-K] 2; [IJZ-MB] 1; [PP] 2
A46: J31102501 | B46: P060152 | C46: Jokerz 31 | D46: ✓ COMPLETE | E46: 0 | F46: ✓ | G46: ✓ | H46: ✓ | I46: ✓ | J46: ✓ | K46: ✓ | L46: ✓ | M46: ✓ | N46: ✓ | O46: ✓ | P46: ✓ | Q46: — | R46: 5.0 | S46: [FHM-K] 3; [FHM-M] 1; [PP] 1
A47: SJ102501 | B47: P060162 | C47: Sleepy Joy | D47: ⚠ 2 MISSING | E47: 2 | F47: ✓ | G47: ✓ | H47: ✓ | I47: ✓ | J47: ✓ | K47: ✓ | L47: ✓ | M47: ✓ | N47: ✗ | O47: ✗ | P47: ✓ | Q47: #10 Mycotoxins; #11 Heavy metals | R47: 4.0 | S47: [FHM-K] 2; [IJZ-MB] 1; [PP] 1
A48: KC102501 | B48: P060172 | C48: Kush Crasher | D48: ✓ COMPLETE | E48: 0 | F48: ✓ | G48: ✓ | H48: ✓ | I48: ✓ | J48: ✓ | K48: ✓ | L48: ✓ | M48: ✓ | N48: ✓ | O48: ✓ | P48: ✓ | Q48: — | R48: 3.0 | S48: [FHM-K] 2; [PP] 1
A49: SJ112501 | B49: P060192 | C49: Sleepy Joy | D49: ✓ COMPLETE | E49: 0 | F49: ✓ | G49: ✓ | H49: ✓ | I49: ✓ | J49: ✓ | K49: ✓ | L49: ✓ | M49: ✓ | N49: ✓ | O49: ✓ | P49: ✓ | Q49: — | R49: 3.0 | S49: [FHM-K] 2; [PP] 1
A50: J31112501 | B50: P060202 | C50: Jokerz 31 | D50: ✓ COMPLETE | E50: 0 | F50: ✓ | G50: ✓ | H50: ✓ | I50: ✓ | J50: ✓ | K50: ✓ | L50: ✓ | M50: ✓ | N50: ✓ | O50: ✓ | P50: ✓ | Q50: — | R50: 8.0 | S50: [FHM-K] 6; [IJZ-MB] 1; [PP] 1
A51: JD112501 | B51: P060212 | C51: Jelly Donutz | D51: ✓ COMPLETE | E51: 0 | F51: ✓ | G51: ✓ | H51: ✓ | I51: ✓ | J51: ✓ | K51: ✓ | L51: ✓ | M51: ✓ | N51: ✓ | O51: ✓ | P51: ✓ | Q51: — | R51: 6.0 | S51: [CNP] 1; [FHM-K] 1; [FHM-M] 1; [IJZ] 1; [IJZ-MB] 1; [PP] 1
A52: OPM112501 | B52: P060222 | C52: Orange Punch Mimosa | D52: ⚠ 2 MISSING | E52: 2 | F52: ✓ | G52: ✓ | H52: ✓ | I52: ✓ | J52: ✗ | K52: ✓ | L52: ✓ | M52: ✓ | N52: ✗ | O52: ✓ | P52: ✓ | Q52: #6 CBN; #10 Mycotoxins | R52: 3.0 | S52: [CNP] 1; [IJZ-MB] 1; [PP] 1
A53: PM112501 | B53: P060232 | C53: Permanent Market | D53: ⚠ 1 MISSING | E53: 1 | F53: ✓ | G53: ✓ | H53: ✓ | I53: ✓ | J53: ✓ | K53: ✓ | L53: ✓ | M53: ✓ | N53: ✗ | O53: ✓ | P53: ✓ | Q53: #10 Mycotoxins | R53: 2.0 | S53: [CNP] 1; [PP] 1
A54: OPM122501 | B54: P060242 | C54: Orange Punch Mimosa | D54: ✓ COMPLETE | E54: 0 | F54: ✓ | G54: ✓ | H54: ✓ | I54: ✓ | J54: ✓ | K54: ✓ | L54: ✓ | M54: ✓ | N54: ✓ | O54: ✓ | P54: ✓ | Q54: — | R54: 7.0 | S54: [FHM-K] 3; [FHM-M] 1; [IJZ] 1; [IJZ-MB] 1; [PP] 1
A55: GG112501 | B55: P060252 | C55: Gorilla Glue | D55: ✓ COMPLETE | E55: 0 | F55: ✓ | G55: ✓ | H55: ✓ | I55: ✓ | J55: ✓ | K55: ✓ | L55: ✓ | M55: ✓ | N55: ✓ | O55: ✓ | P55: ✓ | Q55: — | R55: 5.0 | S55: [CNP] 1; [IJZ] 1; [IJZ-MB] 2; [PP] 1
A56: J31122501 | B56: P060262 | C56: Jokerz 31 | D56: ⚠ 1 MISSING | E56: 1 | F56: ✓ | G56: ✓ | H56: ✓ | I56: ✓ | J56: ✓ | K56: ✓ | L56: ✗ | M56: ✓ | N56: ✓ | O56: ✓ | P56: ✓ | Q56: #8 LoD | R56: 8.0 | S56: [FHM-K] 2; [IJZ] 2; [IJZ-MB] 3; [PP] 1
A57: CC112501 | B57: P060272 | C57: CashCow | D57: ✓ COMPLETE | E57: 0 | F57: ✓ | G57: ✓ | H57: ✓ | I57: ✓ | J57: ✓ | K57: ✓ | L57: ✓ | M57: ✓ | N57: ✓ | O57: ✓ | P57: ✓ | Q57: — | R57: 5.0 | S57: [CNP] 1; [IJZ] 1; [IJZ-MB] 2; [PP] 1
... A62: FB012601_1 | B62: P060322 | C62: Fat Bastard | D62: ✓ COMPLETE | E62: 0 | F62: ✓ | G62: ✓ | H62: ✓ | I62: ✓ | J62: ✓ | K62: ✓ | L62: ✓ | M62: ✓ | N62: ✓ | O62: ✓ | P62: ✓ | Q62: — | R62: 4.0 | S62: [CNP] 1; [IJZ] 1; [IJZ-MB] 1; [PP] 1
A63: CC012601/1 | B63: P060332 | D63: ⚠ 3 MISSING | E63: 3 | F63: ✓ | G63: ✓ | H63: ✓ | I63: ✓ | J63: ✓ | K63: ✓ | L63: ✗ | M63: ✓ | N63: ✓ | O63: ✗ | P63: ✗ | Q63: #8 LoD; #11 Heavy metals; #12 Pesticides | R63: 3.0 | S63: [FHM-K] 1; [FHM-M] 1; [PP] 1
A64: SCR012601* | B64: P060342 | C64: Scrambler | D64: ❌ 8 MISSING | E64: 8 | F64: ✓ | G64: ✗ | H64: ✗ | I64: ✗ | J64: ✗ | K64: ✓ | L64: ✗ | M64: ✓ | N64: ✗ | O64: ✗ | P64: ✗ | Q64: #3 Ident. C; #4 Δ⁹-THC; #5 CBD; #6 CBN; #8 LoD; #10 Mycotoxins; #11 Heavy metals; #12 Pesticides | R64: 2.0 | S64: [IJZ-MB] 2
A65: FB012602* | B65: P060352 | C65: Fat Bastard | D65: ⚠ 3 MISSING | E65: 3 | F65: ✓ | G65: ✓ | H65: ✓ | I65: ✓ | J65: ✓ | K65: ✓ | L65: ✗ | M65: ✓ | N65: ✓ | O65: ✗ | P65: ✗ | Q65: #8 LoD; #11 Heavy metals; #12 Pesticides | R65: 3.0 | S65: [FHM-K] 1; [FHM-M] 1; [PP] 1
A66: JD012603 | B66: P060362 / P060412 / P060422 | D66: ✓ COMPLETE | E66: 0 | F66: ✓ | G66: ✓ | H66: ✓ | I66: ✓ | J66: ✓ | K66: ✓ | L66: ✓ | M66: ✓ | N66: ✓ | O66: ✓ | P66: ✓ | Q66: — | R66: 2.0 | S66: [CNP] 2
A67: CC012603 | B67: P060372 | C67: Cash Cow | D67: ❌ 7 MISSING | E67: 7 | F67: ✗ | G67: ✓ | H67: ✓ | I67: ✓ | J67: ✓ | K67: ✗ | L67: ✗ | M67: ✓ | N67: ✗ | O67: ✗ | P67: ✗ | Q67: #1 Ident. A; #2 Ident. B; #7 Foreign matter; #8 LoD; #10 Mycotoxins; #11 Heavy metals; #12 Pesticides | R67: 0
A68: SCR012603 | B68: P060382 | C68: Scrambler | D68: ⚠ 3 MISSING | E68: 3 | F68: ✓ | G68: ✓ | H68: ✓ | I68: ✓ | J68: ✓ | K68: ✓ | L68: ✗ | M68: ✓ | N68: ✓ | O68: ✗ | P68: ✗ | Q68: #8 LoD; #11 Heavy metals; #12 Pesticides | R68: 3.0 | S68: [FHM-K] 1; [FHM-M] 1; [PP] 1
A69: FB012603V | B69: P060392 | C69: Fat Bastard | D69: ✓ COMPLETE | E69: 0 | F69: ✓ | G69: ✓ | H69: ✓ | I69: ✓ | J69: ✓ | K69: ✓ | L69: ✓ | M69: ✓ | N69: ✓ | O69: ✓ | P69: ✓ | Q69: — | R69: 2.0 | S69: [CNP] 1; [IJZ-MB] 1
A70: GG012603 | B70: P060402 | C70: Gorilla Glue | D70: ✓ COMPLETE | E70: 0 | F70: ✓ | G70: ✓ | H70: ✓ | I70: ✓ | J70: ✓ | K70: ✓ | L70: ✓ | M70: ✓ | N70: ✓ | O70: ✓ | P70: ✓ | Q70: — | R70: 3.0 | S70: [CNP] 1; [FHM-K] 1; [FHM-M] 1
A71: FB012603 | B71: P060432 | C71: Fat Bastard | D71: ✓ COMPLETE | E71: 0 | F71: ✓ | G71: ✓ | H71: ✓ | I71: ✓ | J71: ✓ | K71: ✓ | L71: ✓ | M71: ✓ | N71: ✓ | O71: ✓ | P71: ✓ | Q71: — | R71: 2.0 | S71: [CNP] 1; [IJZ-MB] 1
A72: SCR022601 | B72: P060442 | C72: Scrambler | D72: ✓ COMPLETE | E72: 0 | F72: ✓ | G72: ✓ | H72: ✓ | I72: ✓ | J72: ✓ | K72: ✓ | L72: ✓ | M72: ✓ | N72: ✓ | O72: ✓ | P72: ✓ | Q72: — | R72: 2.0 | S72: [CNP] 1; [IJZ-MB] 1
A73: FB032601 | B73: P060452 | C73: Fat Bastard | D73: ✓ COMPLETE | E73: 0 | F73: ✓ | G73: ✓ | H73: ✓ | I73: ✓ | J73: ✓ | K73: ✓ | L73: ✓ | M73: ✓ | N73: ✓ | O73: ✓ | P73: ✓ | Q73: — | R73: 1.0 | S73: [CNP] 1
A74: GG032601 | B74: P060462 | C74: Gorilla Glue | D74: ⚠ 2 MISSING | E74: 2 | F74: ✓ | G74: ✓ | H74: ✓ | I74: ✓ | J74: ✓ | K74: ✓ | L74: ✓ | M74: ✗ | N74: ✓ | O74: ✗ | P74: ✓ | Q74: #9 Microbiology; #11 Heavy metals | R74: 1.0 | S74: [CNP] 1
A75: JD022601 | B75: P060482 | C75: JellyDonutz | D75: ✓ COMPLETE | E75: 0 | F75: ✓ | G75: ✓ | H75: ✓ | I75: ✓ | J75: ✓ | K75: ✓ | L75: ✓ | M75: ✓ | N75: ✓ | O75: ✓ | P75: ✓ | Q75: — | R75: 1.0 | S75: [CNP] 1
A76: — not recorded — | B76: P160012 | D76: ✓ COMPLETE | E76: 0 | F76: ✓ | G76: ✓ | H76: ✓ | I76: ✓ | J76: ✓ | K76: ✓ | L76: ✓ | M76: ✓ | N76: ✓ | O76: ✓ | P76: ✓ | Q76: — | R76: 1.0 | S76: [CNP] 1
A77: — not recorded — | B77: P160022 | D77: ✓ COMPLETE | E77: 0 | F77: ✓ | G77: ✓ | H77: ✓ | I77: ✓ | J77: ✓ | K77: ✓ | L77: ✓ | M77: ✓ | N77: ✓ | O77: ✓ | P77: ✓ | Q77: — | R77: 1.0 | S77: [CNP] 1
A78: — not recorded — | B78: P160032 | D78: ✓ COMPLETE | E78: 0 | F78: ✓ | G78: ✓ | H78: ✓ | I78: ✓ | J78: ✓ | K78: ✓ | L78: ✓ | M78: ✓ | N78: ✓ | O78: ✓ | P78: ✓ | Q78: — | R78: 1.0 | S78: [CNP] 1
A79: BG1024 | B79: — not assigned — | C79: Blue Gelato | D79: ✓ COMPLETE | E79: 0 | F79: ✓ | G79: ✓ | H79: ✓ | I79: ✓ | J79: ✓ | K79: ✓ | L79: ✓ | M79: ✓ | N79: ✓ | O79: ✓ | P79: ✓ | Q79: — | R79: 6.0 | S79: [CNP] 1; [FHM-K] 1; [FHM-M] 1; [IJZ] 1; [IJZ-MB] 1; [PP] 1
A80: BSS1024 | B80: — not assigned — | C80: Blue Sunset Sherbet | D80: ✓ COMPLETE | E80: 0 | F80: ✓ | G80: ✓ | H80: ✓ | I80: ✓ | J80: ✓ | K80: ✓ | L80: ✓ | M80: ✓ | N80: ✓ | O80: ✓ | P80: ✓ | Q80: — | R80: 6.0 | S80: [CNP] 1; [FHM-K] 1; [FHM-M] 1; [IJZ] 1; [IJZ-MB] 1; [PP] 1
A81: CC042601 | B81: — not assigned — | C81: Cash Cow | D81: ❌ 8 MISSING | E81: 8 | F81: ✗ | G81: ✓ | H81: ✓ | I81: ✓ | J81: ✓ | K81: ✗ | L81: ✗ | M81: ✗ | N81: ✗ | O81: ✗ | P81: ✗ | Q81: #1 Ident. A; #2 Ident. B; #7 Foreign matter; #8 LoD; #9 Microbiology; #10 Mycotoxins; #11 Heavy metals; #12 Pesticides | R81: 0
A82: CJ1024 | B82: — not assigned — | C82: Cap Junky | D82: ✓ COMPLETE | E82: 0 | F82: ✓ | G82: ✓ | H82: ✓ | I82: ✓ | J82: ✓ | K82: ✓ | L82: ✓ | M82: ✓ | N82: ✓ | O82: ✓ | P82: ✓ | Q82: — | R82: 5.0 | S82: [CNP] 1; [IJZ] 1; [IJZ-MB] 2; [PP] 1
A83: FB042601 | B83: — not assigned — | C83: Fat Bastard | D83: ❌ 8 MISSING | E83: 8 | F83: ✗ | G83: ✓ | H83: ✓ | I83: ✓ | J83: ✓ | K83: ✗ | L83: ✗ | M83: ✗ | N83: ✗ | O83: ✗ | P83: ✗ | Q83: #1 Ident. A; #2 Ident. B; #7 Foreign matter; #8 LoD; #9 Microbiology; #10 Mycotoxins; #11 Heavy metals; #12 Pesticides | R83: 0
A84: GG1024 | B84: — not assigned — | C84: Gorilla Glue | D84: ✓ COMPLETE | E84: 0 | F84: ✓ | G84: ✓ | H84: ✓ | I84: ✓ | J84: ✓ | K84: ✓ | L84: ✓ | M84: ✓ | N84: ✓ | O84: ✓ | P84: ✓ | Q84: — | R84: 2.0 | S84: [PP] 2
A85: HPA1024 | B85: — not assigned — | C85: High Pro Amnesia | D85: ❌ 4 MISSING | E85: 4 | F85: ✓ | G85: ✓ | H85: ✓ | I85: ✓ | J85: ✓ | K85: ✓ | L85: ✗ | M85: ✗ | N85: ✓ | O85: ✗ | P85: ✗ | Q85: #8 LoD; #9 Microbiology; #11 Heavy metals; #12 Pesticides | R85: 4.0 | S85: [FHM-K] 1; [FHM-M] 1; [PP] 2
A86: JD032601 | B86: — not assigned — | C86: Jelly Donutz | D86: ❌ 8 MISSING | E86: 8 | F86: ✗ | G86: ✗ | H86: ✗ | I86: ✗ | J86: ✗ | K86: ✗ | L86: ✗ | M86: ✓ | N86: ✓ | O86: ✓ | P86: ✓ | Q86: #1 Ident. A; #2 Ident. B; #3 Ident. C; #4 Δ⁹-THC; #5 CBD; #6 CBN; #7 Foreign matter; #8 LoD | R86: 0
A87: JD042601 | B87: — not assigned — | C87: Jelly Donutz | D87: ❌ 8 MISSING | E87: 8 | F87: ✗ | G87: ✓ | H87: ✓ | I87: ✓ | J87: ✓ | K87: ✗ | L87: ✗ | M87: ✗ | N87: ✗ | O87: ✗ | P87: ✗ | Q87: #1 Ident. A; #2 Ident. B; #7 Foreign matter; #8 LoD; #9 Microbiology; #10 Mycotoxins; #11 Heavy metals; #12 Pesticides | R87: 0
A88: JD112501＊ | B88: — not assigned — | C88: Jelly Donutz | D88: ✓ COMPLETE | E88: 0 | F88: ✓ | G88: ✓ | H88: ✓ | I88: ✓ | J88: ✓ | K88: ✓ | L88: ✓ | M88: ✓ | N88: ✓ | O88: ✓ | P88: ✓ | Q88: — | R88: 4.0 | S88: [CNP] 1; [IJZ] 1; [IJZ-MB] 1; [PP] 1
A89: OPM1024 | B89: — not assigned — | C89: Orange Punch Mimosa | D89: ❌ 4 MISSING | E89: 4 | F89: ✓ | G89: ✓ | H89: ✓ | I89: ✓ | J89: ✓ | K89: ✓ | L89: ✗ | M89: ✗ | N89: ✓ | O89: ✗ | P89: ✗ | Q89: #8 LoD; #9 Microbiology; #11 Heavy metals; #12 Pesticides | R89: 4.0 | S89: [FHM-K] 1; [FHM-M] 1; [PP] 2
A90: OPM1024-01 | B90: — not assigned — | C90: Orange Punch Mimosa | D90: ❌ 4 MISSING | E90: 4 | F90: ✗ | G90: ✓ | H90: ✓ | I90: ✓ | J90: ✗ | K90: ✗ | L90: ✓ | M90: ✓ | N90: ✓ | O90: ✓ | P90: ✓ | Q90: #1 Ident. A; #2 Ident. B; #6 CBN; #7 Foreign matter | R90: 0

Sheet CoQ Parameter Tracker v13
A1: BATCH IDENTIFICATION | D1: IDENTIFICATION 1–3 | M1: CANNABINOID ASSAY 4–6 | V1: PHYSICAL 7–8 | AB1: MICROBIOLOGY 9 | AH1: CONTAMINANTS 10–12
A2: CU Batch | B2: P Batch | C2: STATUS | D2: #1 Identification A Appearance · Ph. Eur. mon. 3028 | G2: #2 Identification B Microscopy · Ph. Eur. 2.8.23 | J2: #3 Identification C HPLC · Ph. Eur. 2.2.29 | M2: #4 Assay — Total Δ⁹-THC* Ph. Eur. 2.2.29 (HPLC) | P2: #5 Assay — Total CBD Ph. Eur. 2.2.29 · CBD + CBDA×0.877 | S2: #6 Total CBN Ph. Eur. 2.2.29 · CBN + CBNA×0.876 | V2: #7 Foreign Matter Ph. Eur. 2.8.2 / in-house | Y2: #8 Loss on Drying Ph. Eur. 2.2.32 · 40 °C, 24 h, 15–25 mbar | AB2: #9 Microbiological Purity Ph. Eur. 2.6.12 / 2.6.13 / 2.6.31 · cat. C | AH2: #10 Mycotoxins Ph. Eur. 2.8.18 / 2.8.22 (HPLC-FLD) | AL2: #11 Heavy Metals Ph. Eur. 2.4.27 (ICP-MS) | AQ2: #12 Pesticide Residues Ph. Eur. 2.8.13 (LC-MS/MS) · CUMCS equivalency
D3: A.C.: Conforms to Ph. Eur. monograph 3028 (Cannabis flos) | G3: A.C.: Conforms to Ph. Eur. monograph 3028 (Cannabis flos) | J3: A.C.: Conforms to Ph. Eur. monograph 3028 (Cannabis flos) | M3: A.C.: Per target grade (CoQ §01) | P3: A.C.: ≤ 1.0 % w/w | S3: A.C.: ≤ 1.0 % w/w | V3: A.C.: ≤ 2.0 % (25–50 g); leaves < 1 cm; no seeds | Y3: A.C.: ≤ 12.0 % | AB3: A.C.: ≤ 10⁵ CFU/g | AC3: A.C.: ≤ 10⁴ CFU/g | AD3: A.C.: ≤ 10⁴ CFU/g | AE3: A.C.: Absence / 25 g | AF3: A.C.: Absence / 1 g | AH3: A.C.: ≤ 2 µg/kg | AI3: A.C.: ≤ 4 µg/kg | AJ3: A.C.: ≤ 20 µg/kg | AL3: A.C.: ≤ 0.5 mg/kg | AM3: A.C.: ≤ 0.3 mg/kg | AN3: A.C.: ≤ 0.2 mg/kg | AO3: A.C.: ≤ 0.1 mg/kg | AQ3: A.C.: ≤ LOQ (Ph. Eur. 2.8.13 / CUMCS equivalency)
D4: Result | E4: [eCOA code],[date],[Lab] | F4: ✓ ✗ | G4: Result | H4: [eCOA code],[date],[Lab] | I4: ✓ ✗ | J4: Result | K4: [eCOA code],[date],[Lab] | L4: ✓ ✗ | M4: Result | N4: [eCOA code],[date],[Lab] | O4: ✓ ✗ | P4: Result | Q4: [eCOA code],[date],[Lab] | R4: ✓ ✗ | S4: Result | T4: [eCOA code],[date],[Lab] | U4: ✓ ✗ | V4: Result | W4: [eCOA code],[date],[Lab] | X4: ✓ ✗ | Y4: Result | Z4: [eCOA code],[date],[Lab] | AA4: ✓ ✗ | AB4: TAMC | AC4: TYMC | AD4: GNB | AE4: Salm. | AF4: E. coli | AG4: ✓ ✗ | AH4: AfB₁ | AI4: ΣAf | AJ4: OTA | AK4: ✓ ✗ | AL4: Pb | AM4: Cd | AN4: As | AO4: Hg | AP4: ✓ ✗ | AQ4: Result | AR4: [eCOA code],[date],[Lab] | AS4: ✓ ✗
A5: BG1024 | B5: N/A — no P batch assigned | C5: ✓ COMPLETE 2 testing instances • 2 document(s) on file, not credited | D5: Conforms | E5: {=IFERROR(INDEX('iCoA Register'!$B:$B,MATCH("BG1024|I",'iCoA Register'!$P:$P,0)),"iCoA — at issue")&", (07.03.2025) [PP]"} -> iCoA-PP_26-003, (07.03.2025) [PP] | F5: ✓ | G5: not on this certificate | H5: ППК25050, (26.02.2025) [CNP] · on file, not credited | I5: • | J5: Conforms (ImB spec.) | K5: ППК25050, (26.02.2025) [CNP] | L5: ✓ | M5: 21.80 | N5: ППК25050, (26.02.2025) [CNP] | O5: ✓ | P5: 0.04 | Q5: ППК25050, (26.02.2025) [CNP] | R5: ✓ | S5: 0.02 ᴰ | T5: ППК25050, (26.02.2025) [CNP] | U5: ✓ | V5: Conforms | W5: {=IFERROR(INDEX('iCoA Register'!$B:$B,MATCH("BG1024|I",'iCoA Register'!$P:$P,0)),"iCoA — at issue")&", (07.03.2025) [PP]"} -> iCoA-PP_26-003, (07.03.2025) [PP] | X5: ✓ | Y5: 5.73 | Z5: ППК25050, (26.02.2025) [CNP] | AA5: ✓ | AB5: 1.6 x 10⁴ | AC5: 1 x 10⁴ | AD5: <10² и >10 | AE5: Одговара | AF5: Одговара | AG5: ✓ | AH5: n.r. | AI5: <2 | AJ5: n.r. | AK5: ✓ | AL5: 0.01 | AM5: 0.016 | AN5: 0.014 | AO5: 0.005 | AP5: ✓ | AQ5: ≤ LOQ (all 29 compounds) | AR5: 752-2025, (27.02.2025) [IJZ] | AS5: ✓
AB6: 163-0271-25, (24.02.2025) [IJZ-MB] | AH6: 752-2025, (27.02.2025) [IJZ] | AL6: 752-2025, (27.02.2025) [IJZ]
G7: Conforms | H7: {=IFERROR(INDEX('iCoA Register'!$B:$B,MATCH("BG1024|I",'iCoA Register'!$P:$P,0)),"iCoA — at issue")&", (07.03.2025) [PP]"} -> iCoA-PP_26-003, (07.03.2025) [PP] | I7: ✓ | J7: Conforms (ImB spec.) ᴿ | K7: 197-1-K-26, (07.08.2026) [FHM-K] | L7: ✓ | M7: 26.14 | N7: 197-1-K-26, (07.08.2026) [FHM-K] | O7: ✓ | P7: < LOQ | Q7: 197-1-K-26, (07.08.2026) [FHM-K] | R7: ✓ | S7: 0.28 | T7: 197-1-K-26, (07.08.2026) [FHM-K] | U7: ✓ | Y7: not on this certificate | Z7: 197-1-K-26, (07.08.2026) [FHM-K] · on file, not credited | AA7: • | AH7: ND | AI7: ND ᴿ | AJ7: ND | AK7: ✓
AH8: 197-1-M-26, (10.08.2026) [FHM-M]
A9: BSS1024 | B9: N/A — no P batch assigned | C9: ✓ COMPLETE 2 testing instances • 2 document(s) on file, not credited | D9: Conforms | E9: {=IFERROR(INDEX('iCoA Register'!$B:$B,MATCH("BSS1024|I",'iCoA Register'!$P:$P,0)),"iCoA — at issue")&", (04.03.2025) [PP]"} -> iCoA-PP_26-002, (04.03.2025) [PP] | F9: ✓ | G9: not on this certificate | H9: ППК25051, (26.02.2025) [CNP] · on file, not credited | I9: • | J9: Conforms (ImB spec.) | K9: ППК25051, (26.02.2025) [CNP] | L9: ✓ | M9: 21.03 | N9: ППК25051, (26.02.2025) [CNP] | O9: ✓ | P9: 0.04 | Q9: ППК25051, (26.02.2025) [CNP] | R9: ✓ | S9: 0.02 ᴰ | T9: ППК25051, (26.02.2025) [CNP] | U9: ✓ | V9: Conforms | W9: {=IFERROR(INDEX('iCoA Register'!$B:$B,MATCH("BSS1024|I",'iCoA Register'!$P:$P,0)),"iCoA — at issue")&", (04.03.2025) [PP]"} -> iCoA-PP_26-002, (04.03.2025) [PP] | X9: ✓ | Y9: 5.99 | Z9: ППК25051, (26.02.2025) [CNP] | AA9: ✓ | AB9: 1.5×10⁴ | AC9: 2.2×10³ | AD9: <10^2 и >10 | AE9: Одговара | AF9: Одговара | AG9: ✓ | AH9: n.r. | AI9: <2 | AJ9: n.r. | AK9: ✓ | AL9: 0.071 | AM9: 0.014 | AN9: 0.081 | AO9: 0.014 | AP9: ✓ | AQ9: ≤ LOQ (all 29 compounds) | AR9: 751-2025, (27.02.2025) [IJZ] | AS9: ✓
AB10: 161-0269-25, (24.02.2025) [IJZ-MB] | AH10: 751-2025, (27.02.2025) [IJZ] | AL10: 751-2025, (27.02.2025) [IJZ]
G11: Conforms | H11: {=IFERROR(INDEX('iCoA Register'!$B:$B,MATCH("BSS1024|I",'iCoA Register'!$P:$P,0)),"iCoA — at issue")&", (04.03.2025) [PP]"} -> iCoA-PP_26-002, (04.03.2025) [PP] | I11: ✓ | J11: Conforms (ImB spec.) | K11: 197-2-K-26, (07.08.2026) [FHM-K] | L11: ✓ | M11: 25.01 | N11: 197-2-K-26, (07.08.2026) [FHM-K] | O11: ✓ | P11: < LOQ | Q11: 197-2-K-26, (07.08.2026) [FHM-K] | R11: ✓ | S11: < LOQ | T11: 197-2-K-26, (07.08.2026) [FHM-K] | U11: ✓ | Y11: not on this certificate | Z11: 197-2-K-26, (07.08.2026) [FHM-K] · on file, not credited | AA11: • | AH11: ND | AI11: ND ᴿ | AJ11: ND | AK11: ✓
AH12: 197-2-M-26, (10.08.2026) [FHM-M]
A13: CC112501 | B13: P060272 | C13: ✓ COMPLETE 2 testing instances • 1 document(s) on file, not credited | D13: Conforms | E13: {=IFERROR(INDEX('iCoA Register'!$B:$B,MATCH("P060272|I",'iCoA Register'!$P:$P,0)),"iCoA — at issue")&", (18.05.2026) [PP]"} -> iCoA-PP_26-060, (18.05.2026) [PP] | F13: ✓ | G13: not on this certificate | H13: ППК26068, (11.05.2026) [CNP] · on file, not credited | I13: • | J13: Conforms (ImB spec.) | K13: ППК26068, (11.05.2026) [CNP] | L13: ✓ | M13: 13.35 | N13: ППК26068, (11.05.2026) [CNP] | O13: ✓ | P13: 0.04 | Q13: ППК26068, (11.05.2026) [CNP] | R13: ✓ | S13: BLQ ᴰ | T13: ППК26068, (11.05.2026) [CNP] | U13: ✓ | V13: Conforms | W13: {=IFERROR(INDEX('iCoA Register'!$B:$B,MATCH("P060272|I",'iCoA Register'!$P:$P,0)),"iCoA — at issue")&", (18.05.2026) [PP]"} -> iCoA-PP_26-060, (18.05.2026) [PP] | X13: ✓ | Y13: 7.39 | Z13: ППК26068, (11.05.2026) [CNP] | AA13: ✓ | AB13: 3.8 x 10³ | AC13: 2.7 x 10³ | AD13: <10³ и >10² | AE13: отсуства/25 | AF13: отсуства/g | AG13: ✓ | AH13: n.r. | AI13: <2 | AJ13: n.r. | AK13: ✓ | AL13: 0.0289 | AM13: 0.0119 | AN13: 0.016 | AO13: 0.0102 | AP13: ✓ | AQ13: ≤ LOQ (all 29 compounds) | AR13: 2359-2026, (29.04.2026) [IJZ] | AS13: ✓
AB14: 311-0555-26, (28.04.2026) [IJZ-MB] | AH14: 2359-2026, (29.04.2026) [IJZ] | AL14: 2359-2026, (29.04.2026) [IJZ]
G15: Conforms | H15: {=IFERROR(INDEX('iCoA Register'!$B:$B,MATCH("P060272|I",'iCoA Register'!$P:$P,0)),"iCoA — at issue")&", (18.05.2026) [PP]"} -> iCoA-PP_26-060, (18.05.2026) [PP] | I15: ✓ | AB15: 1.6×10³ | AC15: 1×10³ | AD15: <10³ и >10² | AE15: absent | AF15: absent | AG15: ✓
AB16: 543-1074-26, (31.08.2026) [IJZ-MB]
A17: CJ1024 | B17: N/A — no P batch assigned | C17: ✓ COMPLETE 2 testing instances • 1 document(s) on file, not credited | D17: Conforms | E17: {=IFERROR(INDEX('iCoA Register'!$B:$B,MATCH("CJ1024|I",'iCoA Register'!$P:$P,0)),"iCoA — at issue")&", (03.03.2025) [PP]"} -> iCoA-PP_26-001, (03.03.2025) [PP] | F17: ✓ | G17: not on this certificate | H17: ППК25052, (26.02.2025) [CNP] · on file, not credited | I17: • | J17: Conforms (ImB spec.) | K17: ППК25052, (26.02.2025) [CNP] | L17: ✓ | M17: 23.00 | N17: ППК25052, (26.02.2025) [CNP] | O17: ✓ | P17: 0.05 | Q17: ППК25052, (26.02.2025) [CNP] | R17: ✓ | S17: 0.02 ᴰ | T17: ППК25052, (26.02.2025) [CNP] | U17: ✓ | V17: Conforms | W17: {=IFERROR(INDEX('iCoA Register'!$B:$B,MATCH("CJ1024|I",'iCoA Register'!$P:$P,0)),"iCoA — at issue")&", (03.03.2025) [PP]"} -> iCoA-PP_26-001, (03.03.2025) [PP] | X17: ✓ | Y17: 5.91 | Z17: ППК25052, (26.02.2025) [CNP] | AA17: ✓ | AB17: 8.4 x 10³ | AC17: <10 | AD17: <10 | AE17: Одговара | AF17: Одговара | AG17: ✓ | AH17: n.r. | AI17: <2 | AJ17: n.r. | AK17: ✓ | AL17: 0.036 | AM17: 0.013 | AN17: 0.063 | AO17: 0.006 | AP17: ✓ | AQ17: ≤ LOQ (all 29 compounds) | AR17: 750-2025, (27.02.2025) [IJZ] | AS17: ✓
AB18: 164-0272-25, (24.02.2025) [IJZ-MB] | AH18: 750-2025, (27.02.2025) [IJZ] | AL18: 750-2025, (27.02.2025) [IJZ]
G19: Conforms | H19: {=IFERROR(INDEX('iCoA Register'!$B:$B,MATCH("CJ1024|I",'iCoA Register'!$P:$P,0)),"iCoA — at issue")&", (03.03.2025) [PP]"} -> iCoA-PP_26-001, (03.03.2025) [PP] | I19: ✓ | AB19: <10 | AC19: 10 | AD19: <10 | AE19: absent | AF19: absent | AG19: ✓
AB20: 565-1096-26, (01.09.2026) [IJZ-MB]
A21: FB012601_1 | B21: P060322 | C21: ✓ COMPLETE 2 testing instances • 1 document(s) on file, not credited | D21: Conforms | E21: {=IFERROR(INDEX('iCoA Register'!$B:$B,MATCH("P060322|I",'iCoA Register'!$P:$P,0)),"iCoA — at issue")&", (22.05.2026) [PP]"} -> iCoA-PP_26-066, (22.05.2026) [PP] | F21: ✓ | G21: not on this certificate | H21: ППК26067, (11.05.2026) [CNP] · on file, not credited | I21: • | J21: Conforms (ImB spec.) | K21: ППК26067, (11.05.2026) [CNP] | L21: ✓ | M21: 14.68 | N21: ППК26067, (11.05.2026) [CNP] | O21: ✓ | P21: 0.04 | Q21: ППК26067, (11.05.2026) [CNP] | R21: ✓ | S21: BLQ ᴰ | T21: ППК26067, (11.05.2026) [CNP] | U21: ✓ | V21: Conforms | W21: {=IFERROR(INDEX('iCoA Register'!$B:$B,MATCH("P060322|I",'iCoA Register'!$P:$P,0)),"iCoA — at issue")&", (22.05.2026) [PP]"} -> iCoA-PP_26-066, (22.05.2026) [PP] | X21: ✓ | Y21: 7.67 | Z21: ППК26067, (11.05.2026) [CNP] | AA21: ✓ | AB21: 2 x 10³ | AC21: 2.1 x 10³ | AD21: <10 | AE21: отсутна/25 g | AF21: отсутна/g | AG21: ✓ | AH21: n.r. | AI21: <2 | AJ21: n.r. | AK21: ✓ | AL21: 0.0114 | AM21: 0.017 | AN21: 0.0144 | AO21: 0.0155 | AP21: ✓ | AQ21: ≤ LOQ (all 26 compounds) | AR21: 2362-2026, (30.04.2026) [IJZ] | AS21: ✓
AB22: 308-0552-26, (28.04.2026) [IJZ-MB] | AH22: 2362-2026, (30.04.2026) [IJZ] | AL22: 2362-2026, (30.04.2026) [IJZ]
G23: Conforms | H23: {=IFERROR(INDEX('iCoA Register'!$B:$B,MATCH("P060322|I",'iCoA Register'!$P:$P,0)),"iCoA — at issue")&", (22.05.2026) [PP]"} -> iCoA-PP_26-066, (22.05.2026) [PP] | I23: ✓
A25: FB012603 | B25: P060432 | C25: ⚠ 3 NO RESULT (3 no cert / 0 cert w/o result) | D25: Одговара | E25: ППК26112, (30.06.2026) [CNP] | F25: ✓ | G25: Одговара | H25: ППК26112, (30.06.2026) [CNP] | I25: ✓ | J25: Conforms (ImB spec.) | K25: ППК26112, (30.06.2026) [CNP] | L25: ✓ | M25: 20.83 | N25: ППК26112, (30.06.2026) [CNP] | O25: ✓ | P25: 0.21 | Q25: ППК26112, (30.06.2026) [CNP] | R25: ✓ | S25: 0.06 | T25: ППК26112, (30.06.2026) [CNP] | U25: ✓ | V25: / (Одговара) | W25: ППК26112, (30.06.2026) [CNP] | X25: ✓ | Y25: 7.04 | Z25: ППК26112, (30.06.2026) [CNP] | AA25: ✓ | AB25: 9.8×10³ | AC25: 2.5×10³ | AD25: <10² и >10 | AE25: absent | AF25: absent | AG25: ✓ | AH25: — MISSING — | AI25: — MISSING — | AJ25: — MISSING — | AK25: ✗ | AL25: — MISSING — | AM25: — MISSING — | AN25: — MISSING — | AO25: — MISSING — | AP25: ✗ | AQ25: — MISSING — | AR25: — no certificate — | AS25: ✗
AB26: 537-1068-26, (31.08.2026) [IJZ-MB] | AH26: — no certificate — | AL26: — no certificate —
A27: FB012603V | B27: P060392 | C27: ⚠ 3 NO RESULT (3 no cert / 0 cert w/o result) | D27: Одговара | E27: ППК26110, (30.06.2026) [CNP] | F27: ✓ | G27: Одговара | H27: ППК26110, (30.06.2026) [CNP] | I27: ✓ | J27: Conforms (ImB spec.) | K27: ППК26110, (30.06.2026) [CNP] | L27: ✓ | M27: 18.29 | N27: ППК26110, (30.06.2026) [CNP] | O27: ✓ | P27: 0.16 | Q27: ППК26110, (30.06.2026) [CNP] | R27: ✓ | S27: 0.06 | T27: ППК26110, (30.06.2026) [CNP] | U27: ✓ | V27: / (Одговара) | W27: ППК26110, (30.06.2026) [CNP] | X27: ✓ | Y27: 6.36 | Z27: ППК26110, (30.06.2026) [CNP] | AA27: ✓ | AB27: 2.9×10³ | AC27: 2.5×10³ | AD27: <10 | AE27: absent | AF27: absent | AG27: ✓ | AH27: — MISSING — | AI27: — MISSING — | AJ27: — MISSING — | AK27: ✗ | AL27: — MISSING — | AM27: — MISSING — | AN27: — MISSING — | AO27: — MISSING — | AP27: ✗ | AQ27: — MISSING — | AR27: — no certificate — | AS27: ✗
AB28: 538-1069-26, (31.08.2026) [IJZ-MB] | AH28: — no certificate — | AL28: — no certificate —
A29: FB032601 | B29: P060452 | C29: ✗ 4 NO RESULT (4 no cert / 0 cert w/o result) | D29: Одговара | E29: ППК26127, (21.07.2026) [CNP] | F29: ✓ | G29: Одговара | H29: ППК26127, (21.07.2026) [CNP] | I29: ✓ | J29: Conforms (ImB spec.) | K29: ППК26127, (21.07.2026) [CNP] | L29: ✓ | M29: 12.39 | N29: ППК26127, (21.07.2026) [CNP] | O29: ✓ | P29: 0.06 | Q29: ППК26127, (21.07.2026) [CNP] | R29: ✓ | S29: 0.04 | T29: ППК26127, (21.07.2026) [CNP] | U29: ✓ | V29: 0.08% (Не одговара) | W29: ППК26127, (21.07.2026) [CNP] | X29: ✓ | Y29: 7.77 | Z29: ППК26127, (21.07.2026) [CNP] | AA29: ✓ | AB29: — MISSING — | AC29: — MISSING — | AD29: — MISSING — | AE29: — MISSING — | AF29: — MISSING — | AG29: ✗ | AH29: — MISSING — | AI29: — MISSING — | AJ29: — MISSING — | AK29: ✗ | AL29: — MISSING — | AM29: — MISSING — | AN29: — MISSING — | AO29: — MISSING — | AP29: ✗ | AQ29: — MISSING — | AR29: — no certificate — | AS29: ✗
AB30: — no certificate — | AH30: — no certificate — | AL30: — no certificate —
A31: FB112501 | B31: P060292 | C31: ✓ COMPLETE 2 testing instances • 1 document(s) on file, not credited | D31: Conforms | E31: {=IFERROR(INDEX('iCoA Register'!$B:$B,MATCH("P060292|I",'iCoA Register'!$P:$P,0)),"iCoA — at issue")&", (19.05.2026) [PP]"} -> iCoA-PP_26-062, (19.05.2026) [PP] | F31: ✓ | G31: not on this certificate | H31: ППК26066, (11.05.2026) [CNP] · on file, not credited | I31: • | J31: Conforms (ImB spec.) | K31: ППК26066, (11.05.2026) [CNP] | L31: ✓ | M31: 16.69 | N31: ППК26066, (11.05.2026) [CNP] | O31: ✓ | P31: 0.05 | Q31: ППК26066, (11.05.2026) [CNP] | R31: ✓ | S31: BLQ ᴰ | T31: ППК26066, (11.05.2026) [CNP] | U31: ✓ | V31: Conforms | W31: {=IFERROR(INDEX('iCoA Register'!$B:$B,MATCH("P060292|I",'iCoA Register'!$P:$P,0)),"iCoA — at issue")&", (19.05.2026) [PP]"} -> iCoA-PP_26-062, (19.05.2026) [PP] | X31: ✓ | Y31: 6.09 | Z31: ППК26066, (11.05.2026) [CNP] | AA31: ✓ | AB31: 3.9 x 10³ | AC31: 2.4 x 10³ | AD31: <10 | AE31: отсутна/25 | AF31: отсутна/g | AG31: ✓ | AH31: n.r. | AI31: <2 | AJ31: n.r. | AK31: ✓ | AL31: 0.0215 | AM31: 0.0108 | AN31: 0.0199 | AO31: 0.0078 | AP31: ✓ | AQ31: ≤ LOQ (all 29 compounds) | AR31: 2357-2026, (29.04.2026) [IJZ] | AS31: ✓
AB32: 312-0556-26, (28.04.2026) [IJZ-MB] | AH32: 2357-2026, (29.04.2026) [IJZ] | AL32: 2357-2026, (29.04.2026) [IJZ]
G33: Conforms | H33: {=IFERROR(INDEX('iCoA Register'!$B:$B,MATCH("P060292|I",'iCoA Register'!$P:$P,0)),"iCoA — at issue")&", (19.05.2026) [PP]"} -> iCoA-PP_26-062, (19.05.2026) [PP] | I33: ✓ | AB33: 3×10³ | AC33: 5.2×10² | AD33: <10² и >10 | AE33: absent | AF33: absent | AG33: ✓
AB34: 542-1073-26, (31.08.2026) [IJZ-MB]
A35: GG012601＊ | B35: P060302 | C35: ✓ COMPLETE 2 testing instances • 1 document(s) on file, not credited | D35: Conforms | E35: {=IFERROR(INDEX('iCoA Register'!$B:$B,MATCH("P060302|I",'iCoA Register'!$P:$P,0)),"iCoA — at issue")&", (20.05.2026) [PP]"} -> iCoA-PP_26-063, (20.05.2026) [PP] | F35: ✓ | G35: not on this certificate | H35: ППК26062, (11.05.2026) [CNP] · on file, not credited | I35: • | J35: Conforms (ImB spec.) | K35: ППК26062, (11.05.2026) [CNP] | L35: ✓ | M35: 15.35 | N35: ППК26062, (11.05.2026) [CNP] | O35: ✓ | P35: 0.06 | Q35: ППК26062, (11.05.2026) [CNP] | R35: ✓ | S35: BLQ ᴰ | T35: ППК26062, (11.05.2026) [CNP] | U35: ✓ | V35: Conforms | W35: {=IFERROR(INDEX('iCoA Register'!$B:$B,MATCH("P060302|I",'iCoA Register'!$P:$P,0)),"iCoA — at issue")&", (20.05.2026) [PP]"} -> iCoA-PP_26-063, (20.05.2026) [PP] | X35: ✓ | Y35: 6.13 | Z35: ППК26062, (11.05.2026) [CNP] | AA35: ✓ | AB35: 1 x 10⁴ | AC35: 1 x 10⁴ | AD35: <10 | AE35: отсутна/25 | AF35: отсутна/g | AG35: ✓ | AH35: n.r. | AI35: <2 | AJ35: n.r. | AK35: ✓ | AL35: 0.0227 | AM35: 0.0179 | AN35: 0.0163 | AO35: 0.031 | AP35: ✓ | AQ35: ≤ LOQ (all 29 compounds) | AR35: 2364-2026, (30.04.2026) [IJZ] | AS35: ✓
AB36: 310-0554-26, (28.04.2026) [IJZ-MB] | AH36: 2364-2026, (30.04.2026) [IJZ] | AL36: 2364-2026, (30.04.2026) [IJZ]
G37: Conforms | H37: {=IFERROR(INDEX('iCoA Register'!$B:$B,MATCH("P060302|I",'iCoA Register'!$P:$P,0)),"iCoA — at issue")&", (20.05.2026) [PP]"} -> iCoA-PP_26-063, (20.05.2026) [PP] | I37: ✓ | AB37: 2.2×10³ | AC37: 2.1×10³ | AD37: <10 | AE37: absent | AF37: absent | AG37: ✓
AB38: 541-1072-26, (31.08.2026) [IJZ-MB]
A39: GG012603 | B39: P060402 | C39: ⚠ 3 NO RESULT (3 no cert / 0 cert w/o result) 2 testing instances • 1 document(s) on file, not credited | D39: Одговара | E39: ППК26114, (30.06.2026) [CNP] | F39: ✓ | G39: Одговара | H39: ППК26114, (30.06.2026) [CNP] | I39: ✓ | J39: Conforms (ImB spec.) | K39: ППК26114, (30.06.2026) [CNP] | L39: ✓ | M39: 17.59 | N39: ППК26114, (30.06.2026) [CNP] | O39: ✓ | P39: 0.05 | Q39: ППК26114, (30.06.2026) [CNP] | R39: ✓ | S39: 0.15 | T39: ППК26114, (30.06.2026) [CNP] | U39: ✓ | V39: 0.09 % (Одговара) | W39: ППК26114, (30.06.2026) [CNP] | X39: ✓ | Y39: 6.48 | Z39: ППК26114, (30.06.2026) [CNP] | AA39: ✓ | AB39: — MISSING — | AC39: — MISSING — | AD39: — MISSING — | AE39: — MISSING — | AF39: — MISSING — | AG39: ✗ | AH39: ND | AI39: ND ᴿ | AJ39: ND | AK39: ✓ | AL39: — MISSING — | AM39: — MISSING — | AN39: — MISSING — | AO39: — MISSING — | AP39: ✗ | AQ39: — MISSING — | AR39: — no certificate — | AS39: ✗
AB40: — no certificate — | AH40: 197-8-M-26, (10.08.2026) [FHM-M] | AL40: — no certificate —
J41: Conforms (ImB spec.) ᴿ | K41: 197-8-K-26, (07.08.2026) [FHM-K] | L41: ✓ | M41: 16.70 | N41: 197-8-K-26, (07.08.2026) [FHM-K] | O41: ✓ | P41: < LOQ | Q41: 197-8-K-26, (07.08.2026) [FHM-K] | R41: ✓ | S41: < LOQ | T41: 197-8-K-26, (07.08.2026) [FHM-K] | U41: ✓ | Y41: not on this certificate | Z41: 197-8-K-26, (07.08.2026) [FHM-K] · on file, not credited | AA41: •
A43: GG032601 | B43: P060462 | C43: ✗ 4 NO RESULT (4 no cert / 0 cert w/o result) | D43: Одговара | E43: ППК26128, (21.07.2026) [CNP] | F43: ✓ | G43: Одговара | H43: ППК26128, (21.07.2026) [CNP] | I43: ✓ | J43: Conforms (ImB spec.) | K43: ППК26128, (21.07.2026) [CNP] | L43: ✓ | M43: 18.98 | N43: ППК26128, (21.07.2026) [CNP] | O43: ✓ | P43: 0.25 | Q43: ППК26128, (21.07.2026) [CNP] | R43: ✓ | S43: 0.04 | T43: ППК26128, (21.07.2026) [CNP] | U43: ✓ | V43: / (Одговара) | W43: ППК26128, (21.07.2026) [CNP] | X43: ✓ | Y43: 7.88 | Z43: ППК26128, (21.07.2026) [CNP] | AA43: ✓ | AB43: — MISSING — | AC43: — MISSING — | AD43: — MISSING — | AE43: — MISSING — | AF43: — MISSING — | AG43: ✗ | AH43: — MISSING — | AI43: — MISSING — | AJ43: — MISSING — | AK43: ✗ | AL43: — MISSING — | AM43: — MISSING — | AN43: — MISSING — | AO43: — MISSING — | AP43: ✗ | AQ43: — MISSING — | AR43: — no certificate — | AS43: ✗
AB44: — no certificate — | AH44: — no certificate — | AL44: — no certificate —
A45: GG1024 | B45: N/A — no P batch assigned | C45: ✗ 9 NO RESULT (9 no cert / 0 cert w/o result) 2 testing instances | D45: Conforms | E45: {=IFERROR(INDEX('iCoA Register'!$B:$B,MATCH("GG1024|I",'iCoA Register'!$P:$P,0)),"iCoA — at issue")&", (11.03.2025) [PP]"} -> iCoA-PP_26-004, (11.03.2025) [PP] | F45: ✓ | G45: Conforms | H45: {=IFERROR(INDEX('iCoA Register'!$B:$B,MATCH("GG1024|I",'iCoA Register'!$P:$P,0)),"iCoA — at issue")&", (11.03.2025) [PP]"} -> iCoA-PP_26-004, (11.03.2025) [PP] | I45: ✓ | J45: — MISSING — | K45: — no certificate — | L45: ✗ | M45: — MISSING — | N45: — no certificate — | O45: ✗ | P45: — MISSING — | Q45: — no certificate — | R45: ✗ | S45: — MISSING — | T45: — no certificate — | U45: ✗ | V45: Confirms | W45: {=IFERROR(INDEX('iCoA Register'!$B:$B,MATCH("GG1024|I",'iCoA Register'!$P:$P,0)),"iCoA — at issue")&", (11.03.2025) [PP]"} -> iCoA-PP_26-004, (11.03.2025) [PP] | X45: ✓ | Y45: — MISSING — | Z45: — no certificate — | AA45: ✗ | AB45: — MISSING — | AC45: — MISSING — | AD45: — MISSING — | AE45: — MISSING — | AF45: — MISSING — | AG45: ✗ | AH45: — MISSING — | AI45: — MISSING — | AJ45: — MISSING — | AK45: ✗ | AL45: — MISSING — | AM45: — MISSING — | AN45: — MISSING — | AO45: — MISSING — | AP45: ✗ | AQ45: — MISSING — | AR45: — no certificate — | AS45: ✗
AB46: — no certificate — | AH46: — no certificate — | AL46: — no certificate —
D47: Confirms | E47: NO-DOC-CODE (Report of Analysis), (23.04.2025) [PP] | F47: ✓ | V47: Confirms | W47: NO-DOC-CODE (Report of Analysis), (23.04.2025) [PP] | X47: ✓
A49: GG112501 | B49: P060252 | C49: ✓ COMPLETE 2 testing instances • 1 document(s) on file, not credited | D49: Conforms | E49: {=IFERROR(INDEX('iCoA Register'!$B:$B,MATCH("P060252|I",'iCoA Register'!$P:$P,0)),"iCoA — at issue")&", (05.05.2026) [PP]"} -> iCoA-PP_26-058, (05.05.2026) [PP] | F49: ✓ | G49: Conforms | H49: {=IFERROR(INDEX('iCoA Register'!$B:$B,MATCH("P060252|I",'iCoA Register'!$P:$P,0)),"iCoA — at issue")&", (05.05.2026) [PP]"} -> iCoA-PP_26-058, (05.05.2026) [PP] | I49: ✓ | J49: Conforms (ImB spec.) | K49: ППК26061, (11.05.2026) [CNP] | L49: ✓ | M49: 17.94 | N49: ППК26061, (11.05.2026) [CNP] | O49: ✓ | P49: 0.08 | Q49: ППК26061, (11.05.2026) [CNP] | R49: ✓ | S49: BLQ ᴰ | T49: ППК26061, (11.05.2026) [CNP] | U49: ✓ | V49: Conforms | W49: {=IFERROR(INDEX('iCoA Register'!$B:$B,MATCH("P060252|I",'iCoA Register'!$P:$P,0)),"iCoA — at issue")&", (05.05.2026) [PP]"} -> iCoA-PP_26-058, (05.05.2026) [PP] | X49: ✓ | Y49: 6.31 | Z49: ППК26061, (11.05.2026) [CNP] | AA49: ✓ | AB49: 5.1×10³ | AC49: 4.5×10³ | AD49: <10^2 | AE49: отсутна/25 | AF49: отсутна/г | AG49: ✓ | AH49: n.r. | AI49: <2 | AJ49: n.r. | AK49: ✓ | AL49: 0.033 | AM49: 0.0154 | AN49: 0.0272 | AO49: 0.0146 | AP49: ✓ | AQ49: ≤ LOQ (all 26 compounds) | AR49: 2358-2026, (29.04.2026) [IJZ] | AS49: ✓
AB50: 304-0548-26, (28.04.2026) [IJZ-MB] | AH50: 2358-2026, (29.04.2026) [IJZ] | AL50: 2358-2026, (29.04.2026) [IJZ]
G51: not on this certificate | H51: ППК26061, (11.05.2026) [CNP] · on file, not credited | I51: • | AB51: 5×10³ | AC51: 1.1×10³ | AD51: <10³ и >10² | AE51: absent | AF51: absent | AG51: ✓
AB52: 545-1076-26, (31.08.2026) [IJZ-MB]
A53: GRC102501 | B53: P060142 / P060182 | C53: ⚠ 3 NO RESULT (3 no cert / 0 cert w/o result) 2 testing instances • 2 document(s) on file, not credited | D53: Conforms | E53: {=IFERROR(INDEX('iCoA Register'!$B:$B,MATCH("P060142|I",'iCoA Register'!$P:$P,0)),"iCoA — at issue")&", (23.02.2026) [PP]"} -> iCoA-PP_26-047, (23.02.2026) [PP] | F53: ✓ | G53: Conforms | H53: {=IFERROR(INDEX('iCoA Register'!$B:$B,MATCH("P060142|I",'iCoA Register'!$P:$P,0)),"iCoA — at issue")&", (23.02.2026) [PP]"} -> iCoA-PP_26-047, (23.02.2026) [PP] | I53: ✓ | J53: not on this certificate | K53: 051-6-LoD-26, (02.03.2026) [FHM-K] · on file, not credited | L53: • | M53: not on this certificate | N53: 051-6-LoD-26, (02.03.2026) [FHM-K] · on file, not credited | O53: • | P53: not on this certificate | Q53: 051-6-LoD-26, (02.03.2026) [FHM-K] · on file, not credited | R53: • | S53: not on this certificate | T53: 051-6-LoD-26, (02.03.2026) [FHM-K] · on file, not credited | U53: • | V53: Conforms | W53: {=IFERROR(INDEX('iCoA Register'!$B:$B,MATCH("P060142|I",'iCoA Register'!$P:$P,0)),"iCoA — at issue")&", (23.02.2026) [PP]"} -> iCoA-PP_26-047, (23.02.2026) [PP] | X53: ✓ | Y53: 7.7 | Z53: 051-6-LoD-26, (02.03.2026) [FHM-K] | AA53: ✓ | AB53: 10 | AC53: <10 | AD53: <10 | AE53: absent | AF53: absent | AG53: ✓ | AH53: — MISSING — | AI53: — MISSING — | AJ53: — MISSING — | AK53: ✗ | AL53: — MISSING — | AM53: — MISSING — | AN53: — MISSING — | AO53: — MISSING — | AP53: ✗ | AQ53: — MISSING — | AR53: — no certificate — | AS53: ✗
AB54: 550-1081-26, (01.09.2026) [IJZ-MB] | AH54: — no certificate — | AL54: — no certificate —
D55: Conforms | E55: {=IFERROR(INDEX('iCoA Register'!$B:$B,MATCH("P060182|I",'iCoA Register'!$P:$P,0)),"iCoA — at issue")&", (14.03.2026) [PP]"} -> iCoA-PP_26-051, (14.03.2026) [PP] | F55: ✓ | G55: Conforms | H55: {=IFERROR(INDEX('iCoA Register'!$B:$B,MATCH("P060182|I",'iCoA Register'!$P:$P,0)),"iCoA — at issue")&", (14.03.2026) [PP]"} -> iCoA-PP_26-051, (14.03.2026) [PP] | I55: ✓ | J55: Conforms (ImB spec.) ᴿ | K55: 051-6-K-26, (04.03.2026) [FHM-K] | L55: ✓ | M55: 11.53 | N55: 051-6-K-26, (04.03.2026) [FHM-K] | O55: ✓ | P55: <LOQ** | Q55: 051-6-K-26, (04.03.2026) [FHM-K] | R55: ✓ | S55: <LOQ** | T55: 051-6-K-26, (04.03.2026) [FHM-K] | U55: ✓ | V55: Conforms | W55: {=IFERROR(INDEX('iCoA Register'!$B:$B,MATCH("P060182|I",'iCoA Register'!$P:$P,0)),"iCoA — at issue")&", (14.03.2026) [PP]"} -> iCoA-PP_26-051, (14.03.2026) [PP] | X55: ✓ | Y55: not on this certificate | Z55: 051-6-K-26, (04.03.2026) [FHM-K] · on file, not credited | AA55: •
A57: HPA1024 | B57: N/A — no P batch assigned | C57: ✗ 4 NO RESULT (4 no cert / 0 cert w/o result) 2 testing instances • 1 document(s) on file, not credited | D57: Conforms | E57: {=IFERROR(INDEX('iCoA Register'!$B:$B,MATCH("HPA1024|I",'iCoA Register'!$P:$P,0)),"iCoA — at issue")&", (11.04.2025) [PP]"} -> iCoA-PP_26-005, (11.04.2025) [PP] | F57: ✓ | G57: Conforms | H57: {=IFERROR(INDEX('iCoA Register'!$B:$B,MATCH("HPA1024|I",'iCoA Register'!$P:$P,0)),"iCoA — at issue")&", (11.04.2025) [PP]"} -> iCoA-PP_26-005, (11.04.2025) [PP] | I57: ✓ | J57: Conforms (ImB spec.) ᴿ | K57: 197-13-K-26, (07.08.2026) [FHM-K] | L57: ✓ | M57: 17.31 | N57: 197-13-K-26, (07.08.2026) [FHM-K] | O57: ✓ | P57: <LOQ | Q57: 197-13-K-26, (07.08.2026) [FHM-K] | R57: ✓ | S57: 0.36 | T57: 197-13-K-26, (07.08.2026) [FHM-K] | U57: ✓ | V57: Conforms | W57: {=IFERROR(INDEX('iCoA Register'!$B:$B,MATCH("HPA1024|I",'iCoA Register'!$P:$P,0)),"iCoA — at issue")&", (11.04.2025) [PP]"} -> iCoA-PP_26-005, (11.04.2025) [PP] | X57: ✓ | Y57: not on this certificate | Z57: 197-13-K-26, (07.08.2026) [FHM-K] · on file, not credited | AA57: • | AB57: — MISSING — | AC57: — MISSING — | AD57: — MISSING — | AE57: — MISSING — | AF57: — MISSING — | AG57: ✗ | AH57: ND | AI57: ND ᴿ | AJ57: <LOQ | AK57: ✓ | AL57: — MISSING — | AM57: — MISSING — | AN57: — MISSING — | AO57: — MISSING — | AP57: ✗ | AQ57: — MISSING — | AR57: — no certificate — | AS57: ✗
AB58: — no certificate — | AH58: 197-13-M-26, (10.08.2026) [FHM-M] | AL58: — no certificate —
D59: Confirms | E59: NO-DOC-CODE (Report of Analysis), (23.04.2025) [PP] | F59: ✓ | V59: Confirms | W59: NO-DOC-CODE (Report of Analysis), (23.04.2025) [PP] | X59: ✓
A61: J31102501 | B61: P060152 | C61: ⚠ 3 NO RESULT (3 no cert / 0 cert w/o result) 3 testing instances • 3 document(s) on file, not credited | D61: Conforms | E61: {=IFERROR(INDEX('iCoA Register'!$B:$B,MATCH("P060152|I",'iCoA Register'!$P:$P,0)),"iCoA — at issue")&", (05.03.2026) [PP]"} -> iCoA-PP_26-048, (05.03.2026) [PP] | F61: ✓ | G61: Conforms | H61: {=IFERROR(INDEX('iCoA Register'!$B:$B,MATCH("P060152|I",'iCoA Register'!$P:$P,0)),"iCoA — at issue")&", (05.03.2026) [PP]"} -> iCoA-PP_26-048, (05.03.2026) [PP] | I61: ✓ | J61: not on this certificate | K61: 051-1-LoD-26, (02.03.2026) [FHM-K] · on file, not credited | L61: • | M61: not on this certificate | N61: 051-1-LoD-26, (02.03.2026) [FHM-K] · on file, not credited | O61: • | P61: not on this certificate | Q61: 051-1-LoD-26, (02.03.2026) [FHM-K] · on file, not credited | R61: • | S61: not on this certificate | T61: 051-1-LoD-26, (02.03.2026) [FHM-K] · on file, not credited | U61: • | V61: Conforms | W61: {=IFERROR(INDEX('iCoA Register'!$B:$B,MATCH("P060152|I",'iCoA Register'!$P:$P,0)),"iCoA — at issue")&", (05.03.2026) [PP]"} -> iCoA-PP_26-048, (05.03.2026) [PP] | X61: ✓ | Y61: 6.3 | Z61: 051-1-LoD-26, (02.03.2026) [FHM-K] | AA61: ✓ | AB61: — MISSING — | AC61: — MISSING — | AD61: — MISSING — | AE61: — MISSING — | AF61: — MISSING — | AG61: ✗ | AH61: ND | AI61: ND ᴿ | AJ61: ND | AK61: ✓ | AL61: — MISSING — | AM61: — MISSING — | AN61: — MISSING — | AO61: — MISSING — | AP61: ✗ | AQ61: — MISSING — | AR61: — no certificate — | AS61: ✗
AB62: — no certificate — | AH62: 197-16-M-26, (10.08.2026) [FHM-M] | AL62: — no certificate —
J63: Conforms (ImB spec.) ᴿ | K63: 051-1-K-26, (04.03.2026) [FHM-K] | L63: ✓ | M63: 19.14 | N63: 051-1-K-26, (04.03.2026) [FHM-K] | O63: ✓ | P63: <LOQ** | Q63: 051-1-K-26, (04.03.2026) [FHM-K] | R63: ✓ | S63: <LOQ** | T63: 051-1-K-26, (04.03.2026) [FHM-K] | U63: ✓ | Y63: not on this certificate | Z63: 051-1-K-26, (04.03.2026) [FHM-K] · on file, not credited | AA63: •
J65: Conforms (ImB spec.) | K65: 197-16-K-26, (07.08.2026) [FHM-K] | L65: ✓ | M65: 17.32 | N65: 197-16-K-26, (07.08.2026) [FHM-K] | O65: ✓ | P65: <LOQ | Q65: 197-16-K-26, (07.08.2026) [FHM-K] | R65: ✓ | S65: <LOQ | T65: 197-16-K-26, (07.08.2026) [FHM-K] | U65: ✓ | Y65: not on this certificate | Z65: 197-16-K-26, (07.08.2026) [FHM-K] · on file, not credited | AA65: •
A67: J31112501 | B67: P060202 | C67: ⚠ 3 NO RESULT (3 no cert / 0 cert w/o result) 6 testing instances • 6 document(s) on file, not credited | D67: Conforms | E67: {=IFERROR(INDEX('iCoA Register'!$B:$B,MATCH("P060202|I",'iCoA Register'!$P:$P,0)),"iCoA — at issue")&", (17.04.2026) [PP]"} -> iCoA-PP_26-053, (17.04.2026) [PP] | F67: ✓ | G67: Conforms | H67: {=IFERROR(INDEX('iCoA Register'!$B:$B,MATCH("P060202|I",'iCoA Register'!$P:$P,0)),"iCoA — at issue")&", (17.04.2026) [PP]"} -> iCoA-PP_26-053, (17.04.2026) [PP] | I67: ✓ | J67: not on this certificate | K67: 051-5-LoD-26, (02.03.2026) [FHM-K] · on file, not credited | L67: • | M67: not on this certificate | N67: 051-5-LoD-26, (02.03.2026) [FHM-K] · on file, not credited | O67: • | P67: not on this certificate | Q67: 051-5-LoD-26, (02.03.2026) [FHM-K] · on file, not credited | R67: • | S67: not on this certificate | T67: 051-5-LoD-26, (02.03.2026) [FHM-K] · on file, not credited | U67: • | V67: Conforms | W67: {=IFERROR(INDEX('iCoA Register'!$B:$B,MATCH("P060202|I",'iCoA Register'!$P:$P,0)),"iCoA — at issue")&", (17.04.2026) [PP]"} -> iCoA-PP_26-053, (17.04.2026) [PP] | X67: ✓ | Y67: 8.4 | Z67: 051-5-LoD-26, (02.03.2026) [FHM-K] | AA67: ✓ | AB67: 4.4×10² | AC67: 8.6×10² | AD67: <10² и >10 | AE67: absent | AF67: absent | AG67: ✓ | AH67: — MISSING — | AI67: — MISSING — | AJ67: — MISSING — | AK67: ✗ | AL67: — MISSING — | AM67: — MISSING — | AN67: — MISSING — | AO67: — MISSING — | AP67: ✗ | AQ67: — MISSING — | AR67: — no certificate — | AS67: ✗
AB68: 547-1078-26, (31.08.2026) [IJZ-MB] | AH68: — no certificate — | AL68: — no certificate —
J69: Conforms (ImB spec.) ᴿ | K69: 051-5-K-26, (04.03.2026) [FHM-K] | L69: ✓ | M69: 25.27 | N69: 051-5-K-26, (04.03.2026) [FHM-K] | O69: ✓ | P69: <LOQ** | Q69: 051-5-K-26, (04.03.2026) [FHM-K] | R69: ✓ | S69: <LOQ** | T69: 051-5-K-26, (04.03.2026) [FHM-K] | U69: ✓ | Y69: not on this certificate | Z69: 051-5-K-26, (04.03.2026) [FHM-K] · on file, not credited | AA69: •
J71: held for review | K71: 100-1-K-26, (09.04.2026) [FHM-K] | L71: ✗ | M71: 20.21 | N71: 100-1-K-26, (09.04.2026) [FHM-K] | O71: ✓ | P71: <LOQ | Q71: 100-1-K-26, (09.04.2026) [FHM-K] | R71: ✓ | S71: <LOQ | T71: 100-1-K-26, (09.04.2026) [FHM-K] | U71: ✓ | Y71: not on this certificate | Z71: 100-1-K-26, (09.04.2026) [FHM-K] · on file, not credited | AA71: •
J73: not on this certificate | K73: 100-1-LoD-26, (09.04.2026) [FHM-K] · on file, not credited | L73: • | M73: not on this certificate | N73: 100-1-LoD-26, (09.04.2026) [FHM-K] · on file, not credited | O73: • | P73: not on this certificate | Q73: 100-1-LoD-26, (09.04.2026) [FHM-K] · on file, not credited | R73: • | S73: not on this certificate | T73: 100-1-LoD-26, (09.04.2026) [FHM-K] · on file, not credited | U73: • | Y73: 7.6 | Z73: 100-1-LoD-26, (09.04.2026) [FHM-K] | AA73: ✓
J75: not on this certificate | K75: 100-2-LoD-26, (09.04.2026) [FHM-K] · on file, not credited | L75: • | M75: not on this certificate | N75: 100-2-LoD-26, (09.04.2026) [FHM-K] · on file, not credited | O75: • | P75: not on this certificate | Q75: 100-2-LoD-26, (09.04.2026) [FHM-K] · on file, not credited | R75: • | S75: not on this certificate | T75: 100-2-LoD-26, (09.04.2026) [FHM-K] · on file, not credited | U75: • | Y75: 10.3 ± 0.2 | Z75: 100-2-LoD-26, (09.04.2026) [FHM-K] | AA75: ✓
J77: not on this certificate | K77: 100-3-LoD-26, (09.04.2026) [FHM-K] · on file, not credited | L77: • | M77: not on this certificate | N77: 100-3-LoD-26, (09.04.2026) [FHM-K] · on file, not credited | O77: • | P77: not on this certificate | Q77: 100-3-LoD-26, (09.04.2026) [FHM-K] · on file, not credited | R77: • | S77: not on this certificate | T77: 100-3-LoD-26, (09.04.2026) [FHM-K] · on file, not credited | U77: • | Y77: 10.3 | Z77: 100-3-LoD-26, (09.04.2026) [FHM-K] | AA77: ✓
A79: J31122501 | B79: P060262 | C79: ⚠ 1 NO RESULT (1 no cert / 0 cert w/o result) 3 testing instances • 2 document(s) on file, not credited | D79: Conforms | E79: {=IFERROR(INDEX('iCoA Register'!$B:$B,MATCH("P060262|I",'iCoA Register'!$P:$P,0)),"iCoA — at issue")&", (14.05.2026) [PP]"} -> iCoA-PP_26-059, (14.05.2026) [PP] | F79: ✓ | G79: Conforms | H79: {=IFERROR(INDEX('iCoA Register'!$B:$B,MATCH("P060262|I",'iCoA Register'!$P:$P,0)),"iCoA — at issue")&", (14.05.2026) [PP]"} -> iCoA-PP_26-059, (14.05.2026) [PP] | I79: ✓ | J79: Conforms (ImB spec.) ᴿ | K79: 100-2-K-26, (09.04.2026) [FHM-K] | L79: ✓ | M79: 19.84 ᴿ | N79: 100-2-K-26, (09.04.2026) [FHM-K] | O79: ✓ | P79: <LOQ (<0.20) ᴿ | Q79: 100-2-K-26, (09.04.2026) [FHM-K] | R79: ✓ | S79: <LOQ ᴿ | T79: 100-2-K-26, (09.04.2026) [FHM-K] | U79: ✓ | V79: Conforms | W79: {=IFERROR(INDEX('iCoA Register'!$B:$B,MATCH("P060262|I",'iCoA Register'!$P:$P,0)),"iCoA — at issue")&", (14.05.2026) [PP]"} -> iCoA-PP_26-059, (14.05.2026) [PP] | X79: ✓ | Y79: not ingested | Z79: 100-2-K-26, (09.04.2026) [FHM-K] · on file, not credited | AA79: • | AB79: 1900 ᴿ | AC79: 840 ᴿ | AD79: <10³ and >10² ᴿ | AE79: absent ᴿ | AF79: absent ᴿ | AG79: ✓ | AH79: n.r. | AI79: Complies ᴿ | AJ79: n.r. | AK79: ✓ | AL79: not ingested | AP79: ✗ | AQ79: N.D. ᴿ | AR79: 1625-2026, (23.04.2026) [IJZ] | AS79: ✓
AB80: 230-0393-26, (07.04.2026) [IJZ-MB] | AH80: 1625-2026, (23.04.2026) [IJZ] | AL80: 1625-2026, (23.04.2026) [IJZ]
J81: not ingested | K81: 100-3-K-26, (09.04.2026) [FHM-K] | L81: ✗ | M81: 21.84 ᴿ | N81: 100-3-K-26, (09.04.2026) [FHM-K] | O81: ✓ | P81: <LOQ (<0.20) ᴿ | Q81: 100-3-K-26, (09.04.2026) [FHM-K] | R81: ✓ | S81: <LOQ ᴿ | T81: 100-3-K-26, (09.04.2026) [FHM-K] | U81: ✓ | Y81: not ingested | Z81: 100-3-K-26, (09.04.2026) [FHM-K] · on file, not credited | AA81: • | AB81: 850 ᴿ | AC81: 370 ᴿ | AD81: <10² and >10 ᴿ | AE81: absent ᴿ | AF81: absent ᴿ | AG81: ✓ | AH81: n.r. | AI81: 2.5 ᴿ | AJ81: n.r. | AK81: ✓ | AL81: N.D. ᴿ | AM81: N.D. ᴿ | AN81: N.D. ᴿ | AO81: N.D. ᴿ | AP81: ✓ | AQ81: N.D. ᴿ | AR81: 1628-2026, (23.04.2026) [IJZ] | AS81: ✓
AB82: 231-0394-26, (07.04.2026) [IJZ-MB] | AH82: 1628-2026, (23.04.2026) [IJZ] | AL82: 1628-2026, (23.04.2026) [IJZ]
AB83: 1×10³ | AC83: 1.7×10² | AD83: <10³ и >10² | AE83: absent | AF83: absent | AG83: ✓
AB84: 544-1075-26, (31.08.2026) [IJZ-MB]
A85: JD012601＊ | B85: P060312 | C85: ✓ COMPLETE 2 testing instances • 1 document(s) on file, not credited | D85: Conforms | E85: {=IFERROR(INDEX('iCoA Register'!$B:$B,MATCH("P060312|I",'iCoA Register'!$P:$P,0)),"iCoA — at issue")&", (21.05.2026) [PP]"} -> iCoA-PP_26-064, (21.05.2026) [PP] | F85: ✓ | G85: not on this certificate | H85: ППК26064, (11.05.2026) [CNP] · on file, not credited | I85: • | J85: Conforms (ImB spec.) | K85: ППК26064, (11.05.2026) [CNP] | L85: ✓ | M85: 18.16 | N85: ППК26064, (11.05.2026) [CNP] | O85: ✓ | P85: 0.06 | Q85: ППК26064, (11.05.2026) [CNP] | R85: ✓ | S85: BLQ ᴰ | T85: ППК26064, (11.05.2026) [CNP] | U85: ✓ | V85: Conforms | W85: {=IFERROR(INDEX('iCoA Register'!$B:$B,MATCH("P060312|I",'iCoA Register'!$P:$P,0)),"iCoA — at issue")&", (21.05.2026) [PP]"} -> iCoA-PP_26-064, (21.05.2026) [PP] | X85: ✓ | Y85: 6.68 | Z85: ППК26064, (11.05.2026) [CNP] | AA85: ✓ | AB85: 1.9 x 10³ | AC85: 2.4 x 10³ | AD85: <10 | AE85: отсутна/25 | AF85: отсутна/g | AG85: ✓ | AH85: n.r. | AI85: <2 | AJ85: n.r. | AK85: ✓ | AL85: 0.0739 | AM85: 0.0166 | AN85: 0.0136 | AO85: 0.0322 | AP85: ✓ | AQ85: ≤ LOQ (all 28 compounds) | AR85: 2363-2026, (30.04.2026) [IJZ] | AS85: ✓
AB86: 309-0553-26, (28.04.2026) [IJZ-MB] | AH86: 2363-2026, (30.04.2026) [IJZ] | AL86: 2363-2026, (30.04.2026) [IJZ]
G87: Conforms | H87: {=IFERROR(INDEX('iCoA Register'!$B:$B,MATCH("P060312|I",'iCoA Register'!$P:$P,0)),"iCoA — at issue")&", (21.05.2026) [PP]"} -> iCoA-PP_26-064, (21.05.2026) [PP] | I87: ✓ | AB87: 2.2×10³ | AC87: 1.7×10³ | AD87: <10 | AE87: absent | AF87: absent | AG87: ✓
AB88: 540-1071-26, (31.08.2026) [IJZ-MB]
A89: JD012603 | B89: P060362 / P060412 / P060422 | C89: ✗ 4 NO RESULT (4 no cert / 0 cert w/o result) 2 testing instances • 1 document(s) on file, not credited | D89: Одговара | E89: ППК26111, (30.06.2026) [CNP] | F89: ✓ | G89: Одговара | H89: ППК26111, (30.06.2026) [CNP] | I89: ✓ | J89: Conforms (ImB spec.) | K89: ППК26111, (30.06.2026) [CNP] | L89: ✓ | M89: 15.16 | N89: ППК26111, (30.06.2026) [CNP] | O89: ✓ | P89: BLQ | Q89: ППК26111, (30.06.2026) [CNP] | R89: ✓ | S89: 0.04 | T89: ППК26111, (30.06.2026) [CNP] | U89: ✓ | V89: / (Одговара) | W89: ППК26111, (30.06.2026) [CNP] | X89: ✓ | Y89: 7.04 | Z89: ППК26111, (30.06.2026) [CNP] | AA89: ✓ | AB89: — MISSING — | AC89: — MISSING — | AD89: — MISSING — | AE89: — MISSING — | AF89: — MISSING — | AG89: ✗ | AH89: — MISSING — | AI89: — MISSING — | AJ89: — MISSING — | AK89: ✗ | AL89: — MISSING — | AM89: — MISSING — | AN89: — MISSING — | AO89: — MISSING — | AP89: ✗ | AQ89: — MISSING — | AR89: — no certificate — | AS89: ✗
AB90: — no certificate — | AH90: — no certificate — | AL90: — no certificate —
D91: Одговара | E91: ППК26113, (30.06.2026) [CNP] · on file, not credited | F91: • | G91: Одговара | H91: ППК26113, (30.06.2026) [CNP] | I91: ✓ | J91: Conforms (ImB spec.) | K91: ППК26113, (30.06.2026) [CNP] | L91: ✓ | M91: 20.54 | N91: ППК26113, (30.06.2026) [CNP] | O91: ✓ | P91: 0.05 | Q91: ППК26113, (30.06.2026) [CNP] | R91: ✓ | S91: 0.05 | T91: ППК26113, (30.06.2026) [CNP] | U91: ✓ | V91: / (Одговара) | W91: ППК26113, (30.06.2026) [CNP] · on file, not credited | X91: • | Y91: 7.52 | Z91: ППК26113, (30.06.2026) [CNP] | AA91: ✓
A93: JD022601 | B93: P060482 | C93: ✗ 4 NO RESULT (4 no cert / 0 cert w/o result) | D93: Одговара | E93: ППК26115, (30.06.2026) [CNP] | F93: ✓ | G93: Одговара | H93: ППК26115, (30.06.2026) [CNP] | I93: ✓ | J93: Conforms (ImB spec.) | K93: ППК26115, (30.06.2026) [CNP] | L93: ✓ | M93: 18.58 | N93: ППК26115, (30.06.2026) [CNP] | O93: ✓ | P93: BLQ | Q93: ППК26115, (30.06.2026) [CNP] | R93: ✓ | S93: 0.05 | T93: ППК26115, (30.06.2026) [CNP] | U93: ✓ | V93: / (Одговара) | W93: ППК26115, (30.06.2026) [CNP] | X93: ✓ | Y93: 7.73 | Z93: ППК26115, (30.06.2026) [CNP] | AA93: ✓ | AB93: — MISSING — | AC93: — MISSING — | AD93: — MISSING — | AE93: — MISSING — | AF93: — MISSING — | AG93: ✗ | AH93: — MISSING — | AI93: — MISSING — | AJ93: — MISSING — | AK93: ✗ | AL93: — MISSING — | AM93: — MISSING — | AN93: — MISSING — | AO93: — MISSING — | AP93: ✗ | AQ93: — MISSING — | AR93: — no certificate — | AS93: ✗
AB94: — no certificate — | AH94: — no certificate — | AL94: — no certificate —
A95: JD112501 | B95: P060212 | C95: ✓ COMPLETE 3 testing instances • 5 document(s) on file, not credited | D95: Conforms | E95: {=IFERROR(INDEX('iCoA Register'!$B:$B,MATCH("P060212|I",'iCoA Register'!$P:$P,0)),"iCoA — at issue")&", (21.04.2026) [PP]"} -> iCoA-PP_26-054, (21.04.2026) [PP] | F95: ✓ | G95: Conforms | H95: {=IFERROR(INDEX('iCoA Register'!$B:$B,MATCH("P060212|I",'iCoA Register'!$P:$P,0)),"iCoA — at issue")&", (21.04.2026) [PP]"} -> iCoA-PP_26-054, (21.04.2026) [PP] | I95: ✓ | J95: Conforms (ImB spec.) | K95: ППК26063, (11.05.2026) [CNP] | L95: ✓ | M95: 19.64 | N95: ППК26063, (11.05.2026) [CNP] | O95: ✓ | P95: 0.06 | Q95: ППК26063, (11.05.2026) [CNP] | R95: ✓ | S95: BLQ ᴰ | T95: ППК26063, (11.05.2026) [CNP] | U95: ✓ | V95: Conforms | W95: {=IFERROR(INDEX('iCoA Register'!$B:$B,MATCH("P060212|I",'iCoA Register'!$P:$P,0)),"iCoA — at issue")&", (21.04.2026) [PP]"} -> iCoA-PP_26-054, (21.04.2026) [PP] | X95: ✓ | Y95: 6.69 | Z95: ППК26063, (11.05.2026) [CNP] | AA95: ✓ | AB95: 1 x 10⁴ | AC95: 6.7 x 10³ | AD95: <10³ и >10² | AE95: отсутна/25 | AF95: отсутна/g | AG95: • | AH95: n.r. | AI95: <2 | AJ95: n.r. | AK95: ✓ | AL95: 0.022 | AM95: 0.0149 | AN95: 0.02 | AO95: 0.0166 | AP95: ✓ | AQ95: ≤ LOQ (all 26 compounds) | AR95: 2361-2026, (30.04.2026) [IJZ] | AS95: ✓
AB96: 306-0550-26, (28.04.2026) [IJZ-MB] · on file, not credited | AH96: 2361-2026, (30.04.2026) [IJZ] | AL96: 2361-2026, (30.04.2026) [IJZ]
G97: not on this certificate | H97: ППК26063, (11.05.2026) [CNP] · on file, not credited | I97: • | J97: Conforms (ImB spec.) | K97: ППК26065, (11.05.2026) [CNP] · on file, not credited | L97: • | M97: 13.93 | N97: ППК26065, (11.05.2026) [CNP] · on file, not credited | O97: • | P97: 0.04 | Q97: ППК26065, (11.05.2026) [CNP] · on file, not credited | R97: • | S97: BLQ ᴰ | T97: ППК26065, (11.05.2026) [CNP] · on file, not credited | U97: • | Y97: 6.38 | Z97: ППК26065, (11.05.2026) [CNP] · on file, not credited | AA97: • | AB97: 2.6 x 10³ | AC97: 3.3 x 10³ | AD97: n.r. | AE97: отсуство/25 | AF97: отсуство/g | AG97: ✓ | AH97: n.r. | AI97: <2 | AJ97: n.r. | AK97: • | AL97: 0.0109 | AM97: 0.01287 | AN97: 0.0175 | AO97: 0.0165 | AP97: • | AQ97: ≤ LOQ (all 27 compounds) | AR97: 2365-2026, (30.04.2026) [IJZ] · on file, not credited | AS97: •
AB98: 307-0551-26, (28.04.2026) [IJZ-MB] | AH98: 2365-2026, (30.04.2026) [IJZ] · on file, not credited | AL98: 2365-2026, (30.04.2026) [IJZ] · on file, not credited
G99: not on this certificate | H99: ППК26065, (11.05.2026) [CNP] · on file, not credited | I99: • | J99: Conforms (ImB spec.) ᴿ | K99: 197-15-K-26, (07.08.2026) [FHM-K] | L99: ✓ | M99: 20.32 | N99: 197-15-K-26, (07.08.2026) [FHM-K] | O99: ✓ | P99: < LOQ | Q99: 197-15-K-26, (07.08.2026) [FHM-K] | R99: ✓ | S99: < LOQ | T99: 197-15-K-26, (07.08.2026) [FHM-K] | U99: ✓ | Y99: not on this certificate | Z99: 197-15-K-26, (07.08.2026) [FHM-K] · on file, not credited | AA99: • | AH99: ND | AI99: ND ᴿ | AJ99: ND | AK99: ✓
AH100: 197-15-M-26, (10.08.2026) [FHM-M]
A101: JD112501＊ | B101: N/A — no P batch assigned | C101: ✓ COMPLETE | D101: Conforms | E101: {=IFERROR(INDEX('iCoA Register'!$B:$B,MATCH("JD112501|I",'iCoA Register'!$P:$P,0)),"iCoA — at issue")&", (packaging date — to record) [PP]"} -> — at issue —, (packaging date — to record) [PP] | F101: ✓ | G101: Conforms | H101: {=IFERROR(INDEX('iCoA Register'!$B:$B,MATCH("JD112501|I",'iCoA Register'!$P:$P,0)),"iCoA — at issue")&", (packaging date — to record) [PP]"} -> — at issue —, (packaging date — to record) [PP] | I101: ✓ | J101: Conforms (ImB spec.) | K101: ППК26065, (11.05.2026) [CNP] | L101: ✓ | M101: 13.93 | N101: ППК26065, (11.05.2026) [CNP] | O101: ✓ | P101: 0.04 | Q101: ППК26065, (11.05.2026) [CNP] | R101: ✓ | S101: BLQ ᴰ | T101: ППК26065, (11.05.2026) [CNP] | U101: ✓ | V101: Conforms | W101: {=IFERROR(INDEX('iCoA Register'!$B:$B,MATCH("JD112501|I",'iCoA Register'!$P:$P,0)),"iCoA — at issue")&", (packaging date — to record) [PP]"} -> — at issue —, (packaging date — to record) [PP] | X101: ✓ | Y101: 6.38 | Z101: ППК26065, (11.05.2026) [CNP] | AA101: ✓ | AB101: 1 x 10⁴ | AC101: 6.7 x 10³ | AD101: <10³ и >10² | AE101: отсутна/25 | AF101: отсутна/g | AG101: ✓ | AH101: n.r. | AI101: <2 | AJ101: n.r. | AK101: ✓ | AL101: 0.0109 | AM101: 0.01287 | AN101: 0.0175 | AO101: 0.0165 | AP101: ✓ | AQ101: ≤ LOQ (all 27 compounds) | AR101: 2365-2026, (30.04.2026) [IJZ] | AS101: ✓
AB102: 306-0550-26, (28.04.2026) [IJZ-MB] | AH102: 2365-2026, (30.04.2026) [IJZ] | AL102: 2365-2026, (30.04.2026) [IJZ]
A103: KC102501 | B103: P060172 | C103: ✗ 4 NO RESULT (4 no cert / 0 cert w/o result) 2 testing instances • 2 document(s) on file, not credited | D103: Conforms | E103: {=IFERROR(INDEX('iCoA Register'!$B:$B,MATCH("P060172|I",'iCoA Register'!$P:$P,0)),"iCoA — at issue")&", (12.03.2026) [PP]"} -> iCoA-PP_26-050, (12.03.2026) [PP] | F103: ✓ | G103: Conforms | H103: {=IFERROR(INDEX('iCoA Register'!$B:$B,MATCH("P060172|I",'iCoA Register'!$P:$P,0)),"iCoA — at issue")&", (12.03.2026) [PP]"} -> iCoA-PP_26-050, (12.03.2026) [PP] | I103: ✓ | J103: not on this certificate | K103: 051-4-LoD-26, (02.03.2026) [FHM-K] · on file, not credited | L103: • | M103: not on this certificate | N103: 051-4-LoD-26, (02.03.2026) [FHM-K] · on file, not credited | O103: • | P103: not on this certificate | Q103: 051-4-LoD-26, (02.03.2026) [FHM-K] · on file, not credited | R103: • | S103: not on this certificate | T103: 051-4-LoD-26, (02.03.2026) [FHM-K] · on file, not credited | U103: • | V103: Conforms | W103: {=IFERROR(INDEX('iCoA Register'!$B:$B,MATCH("P060172|I",'iCoA Register'!$P:$P,0)),"iCoA — at issue")&", (12.03.2026) [PP]"} -> iCoA-PP_26-050, (12.03.2026) [PP] | X103: ✓ | Y103: 8.6 | Z103: 051-4-LoD-26, (02.03.2026) [FHM-K] | AA103: ✓ | AB103: — MISSING — | AC103: — MISSING — | AD103: — MISSING — | AE103: — MISSING — | AF103: — MISSING — | AG103: ✗ | AH103: — MISSING — | AI103: — MISSING — | AJ103: — MISSING — | AK103: ✗ | AL103: — MISSING — | AM103: — MISSING — | AN103: — MISSING — | AO103: — MISSING — | AP103: ✗ | AQ103: — MISSING — | AR103: — no certificate — | AS103: ✗
AB104: — no certificate — | AH104: — no certificate — | AL104: — no certificate —
J105: Conforms (ImB spec.) ᴿ | K105: 051-4-K-26, (04.03.2026) [FHM-K] | L105: ✓ | M105: 17.04 | N105: 051-4-K-26, (04.03.2026) [FHM-K] | O105: ✓ | P105: <LOQ** | Q105: 051-4-K-26, (04.03.2026) [FHM-K] | R105: ✓ | S105: <LOQ** | T105: 051-4-K-26, (04.03.2026) [FHM-K] | U105: ✓ | Y105: not on this certificate | Z105: 051-4-K-26, (04.03.2026) [FHM-K] · on file, not credited | AA105: •
A107: OPM1024 | B107: N/A — no P batch assigned | C107: ✗ 4 NO RESULT (4 no cert / 0 cert w/o result) 2 testing instances • 1 document(s) on file, not credited | D107: Confirms | E107: NO-DOC-CODE (Report of Analysis), (23.04.2025) [PP] | F107: ✓ | G107: Conforms | H107: {=IFERROR(INDEX('iCoA Register'!$B:$B,MATCH("OPM1024|I",'iCoA Register'!$P:$P,0)),"iCoA — at issue")&", (24.04.2025) [PP]"} -> iCoA-PP_26-006, (24.04.2025) [PP] | I107: ✓ | J107: Conforms (ImB spec.) ᴿ | K107: 197-17-K-26, (07.08.2026) [FHM-K] | L107: ✓ | M107: 20.03 | N107: 197-17-K-26, (07.08.2026) [FHM-K] | O107: ✓ | P107: <LOQ | Q107: 197-17-K-26, (07.08.2026) [FHM-K] | R107: ✓ | S107: <LOQ | T107: 197-17-K-26, (07.08.2026) [FHM-K] | U107: ✓ | V107: Confirms | W107: NO-DOC-CODE (Report of Analysis), (23.04.2025) [PP] | X107: ✓ | Y107: not on this certificate | Z107: 197-17-K-26, (07.08.2026) [FHM-K] · on file, not credited | AA107: • | AB107: — MISSING — | AC107: — MISSING — | AD107: — MISSING — | AE107: — MISSING — | AF107: — MISSING — | AG107: ✗ | AH107: ND | AI107: ND ᴿ | AJ107: ND | AK107: ✓ | AL107: — MISSING — | AM107: — MISSING — | AN107: — MISSING — | AO107: — MISSING — | AP107: ✗ | AQ107: — MISSING — | AR107: — no certificate — | AS107: ✗
AB108: — no certificate — | AH108: 197-17-M-26, (10.08.2026) [FHM-M] | AL108: — no certificate —
D109: Conforms | E109: {=IFERROR(INDEX('iCoA Register'!$B:$B,MATCH("OPM1024|I",'iCoA Register'!$P:$P,0)),"iCoA — at issue")&", (24.04.2025) [PP]"} -> iCoA-PP_26-006, (24.04.2025) [PP] | F109: ✓ | V109: Conforms | W109: {=IFERROR(INDEX('iCoA Register'!$B:$B,MATCH("OPM1024|I",'iCoA Register'!$P:$P,0)),"iCoA — at issue")&", (24.04.2025) [PP]"} -> iCoA-PP_26-006, (24.04.2025) [PP] | X109: ✓
A111: OPM112501 | B111: P060222 | C111: ✗ 4 NO RESULT (3 no cert / 1 cert w/o result) 2 testing instances • 1 document(s) on file, not credited | D111: Conforms | E111: {=IFERROR(INDEX('iCoA Register'!$B:$B,MATCH("P060222|I",'iCoA Register'!$P:$P,0)),"iCoA — at issue")&", (24.04.2026) [PP]"} -> iCoA-PP_26-055, (24.04.2026) [PP] | F111: ✓ | G111: not ingested | H111: ППК26031, (05.03.2026) [CNP] · on file, not credited | I111: • | J111: Conforms (ImB spec.) ᴿ | K111: ППК26031, (05.03.2026) [CNP] | L111: ✓ | M111: 8.00 ᴿ | N111: ППК26031, (05.03.2026) [CNP] | O111: ✓ | P111: 0.02 ᴿ | Q111: ППК26031, (05.03.2026) [CNP] | R111: ✓ | S111: not ingested | T111: ППК26031, (05.03.2026) [CNP] | U111: ✗ | V111: Conforms | W111: {=IFERROR(INDEX('iCoA Register'!$B:$B,MATCH("P060222|I",'iCoA Register'!$P:$P,0)),"iCoA — at issue")&", (24.04.2026) [PP]"} -> iCoA-PP_26-055, (24.04.2026) [PP] | X111: ✓ | Y111: 8.06 ᴿ | Z111: ППК26031, (05.03.2026) [CNP] | AA111: ✓ | AB111: <10 | AC111: 10 | AD111: <10 | AE111: absent | AF111: absent | AG111: ✓ | AH111: — MISSING — | AI111: — MISSING — | AJ111: — MISSING — | AK111: ✗ | AL111: — MISSING — | AM111: — MISSING — | AN111: — MISSING — | AO111: — MISSING — | AP111: ✗ | AQ111: — MISSING — | AR111: — no certificate — | AS111: ✗
AB112: 546-1077-26, (31.08.2026) [IJZ-MB] | AH112: — no certificate — | AL112: — no certificate —
G113: Conforms | H113: {=IFERROR(INDEX('iCoA Register'!$B:$B,MATCH("P060222|I",'iCoA Register'!$P:$P,0)),"iCoA — at issue")&", (24.04.2026) [PP]"} -> iCoA-PP_26-055, (24.04.2026) [PP] | I113: ✓
A115: OPM122501 | B115: P060242 | C115: ✓ COMPLETE 3 testing instances • 3 document(s) on file, not credited | D115: Conforms | E115: {=IFERROR(INDEX('iCoA Register'!$B:$B,MATCH("P060242|I",'iCoA Register'!$P:$P,0)),"iCoA — at issue")&", (28.04.2026) [PP]"} -> iCoA-PP_26-057, (28.04.2026) [PP] | F115: ✓ | G115: Conforms | H115: {=IFERROR(INDEX('iCoA Register'!$B:$B,MATCH("P060242|I",'iCoA Register'!$P:$P,0)),"iCoA — at issue")&", (28.04.2026) [PP]"} -> iCoA-PP_26-057, (28.04.2026) [PP] | I115: ✓ | J115: Conforms (ImB spec.) ᴿ | K115: 100-4-K-26, (09.04.2026) [FHM-K] | L115: ✓ | M115: 8.09 | N115: 100-4-K-26, (09.04.2026) [FHM-K] | O115: ✓ | P115: <LOQ | Q115: 100-4-K-26, (09.04.2026) [FHM-K] | R115: ✓ | S115: <LOQ | T115: 100-4-K-26, (09.04.2026) [FHM-K] | U115: ✓ | V115: Conforms | W115: {=IFERROR(INDEX('iCoA Register'!$B:$B,MATCH("P060242|I",'iCoA Register'!$P:$P,0)),"iCoA — at issue")&", (28.04.2026) [PP]"} -> iCoA-PP_26-057, (28.04.2026) [PP] | X115: ✓ | Y115: not on this certificate | Z115: 100-4-K-26, (09.04.2026) [FHM-K] · on file, not credited | AA115: • | AB115: 120 | AC115: 100 | AD115: <10 | AE115: Одговара | AF115: Одговара | AG115: ✓ | AH115: n.r. | AI115: 2.2 | AJ115: n.r. | AK115: ✓ | AL115: 0.049 | AM115: 0.165 | AN115: н.д. | AO115: н.д. | AP115: ✓ | AQ115: ≤ LOQ (all 25 compounds) | AR115: 1627-2026, (23.04.2026) [IJZ] | AS115: ✓
AB116: 229-0392-26, (07.04.2026) [IJZ-MB] | AH116: 1627-2026, (23.04.2026) [IJZ] | AL116: 1627-2026, (23.04.2026) [IJZ]
...

Sheet iCoA Register
A1: No. | B1: iCoA code | C1: Issuable | D1: Issue date (planned) | E1: Test date (packaging) | F1: Packaging complete | G1: Group | H1: Series | I1: CU Batch | J1: P Batch | K1: Strain | L1: iCoA scope | M1: CNP reference | N1: CoQ (register) | O1: Plan reference (31.08.2026) | P1: Key | Q1: Status
A2: =IF(C2="yes",COUNT(A$1:A1)+1,"") -> 1 | B2: =IF(A2<>"","iCoA-PP_26-"&TEXT(A2,"000"),IF(C2="n/a","not needed","— at issue —")) -> iCoA-PP_26-001 | C2: yes | D2: =IF(A2="","",IF(G2="legacy",DATE(2026,5,15),IF(ISNUMBER(F2),(F2+5)+CHOOSE(WEEKDAY(F2+5,2),0,0,0,0,0,2,1),""))) -> 46157 | E2: {=IFERROR(INDEX('Batch Dates'!$F:$F,MATCH(J2,'Batch Dates'!$C:$C,0)),IFERROR(INDEX('Batch Dates'!$F:$F,MATCH(I2,'Batch Dates'!$B:$B,0)),""))} -> 45719 | F2: {=IFERROR(INDEX('Batch Dates'!$G:$G,MATCH(J2,'Batch Dates'!$C:$C,0)),IFERROR(INDEX('Batch Dates'!$G:$G,MATCH(I2,'Batch Dates'!$B:$B,0)),""))} -> 45719 | G2: legacy | H2: initial release | I2: CJ1024 | J2: N/A — no P batch assigned | K2: Cap Junky | L2: Ident A + Ident B + Foreign matter | M2: — | N2: {=IFERROR(INDEX('CoQ Register'!$B:$B,MATCH("CJ1024|I",'CoQ Register'!$S:$S,0)),"—")} -> CoQ-PP_26-001 | O2: — | P2: CJ1024|I | Q2: registered — issued with the legacy series on 15.05.2026
A3: =IF(C3="yes",COUNT(A$1:A2)+1,"") -> 2 | B3: =IF(A3<>"","iCoA-PP_26-"&TEXT(A3,"000"),IF(C3="n/a","not needed","— at issue —")) -> iCoA-PP_26-002 | C3: yes | D3: =IF(A3="","",IF(G3="legacy",DATE(2026,5,15),IF(ISNUMBER(F3),(F3+5)+CHOOSE(WEEKDAY(F3+5,2),0,0,0,0,0,2,1),""))) -> 46157 | E3: {=IFERROR(INDEX('Batch Dates'!$F:$F,MATCH(J3,'Batch Dates'!$C:$C,0)),IFERROR(INDEX('Batch Dates'!$F:$F,MATCH(I3,'Batch Dates'!$B:$B,0)),""))} -> 45720 | F3: {=IFERROR(INDEX('Batch Dates'!$G:$G,MATCH(J3,'Batch Dates'!$C:$C,0)),IFERROR(INDEX('Batch Dates'!$G:$G,MATCH(I3,'Batch Dates'!$B:$B,0)),""))} -> 45720 | G3: legacy | H3: initial release | I3: BSS1024 | J3: N/A — no P batch assigned | K3: Blue Sunset Sherbet | L3: Ident A + Ident B + Foreign matter | M3: — | N3: {=IFERROR(INDEX('CoQ Register'!$B:$B,MATCH("BSS1024|I",'CoQ Register'!$S:$S,0)),"—")} -> CoQ-PP_26-002 | O3: iCoA-PP-2025-0001 | P3: BSS1024|I | Q3: registered — issued with the legacy series on 15.05.2026
A4: =IF(C4="yes",COUNT(A$1:A3)+1,"") -> 3 | B4: =IF(A4<>"","iCoA-PP_26-"&TEXT(A4,"000"),IF(C4="n/a","not needed","— at issue —")) -> iCoA-PP_26-003 | C4: yes | D4: =IF(A4="","",IF(G4="legacy",DATE(2026,5,15),IF(ISNUMBER(F4),(F4+5)+CHOOSE(WEEKDAY(F4+5,2),0,0,0,0,0,2,1),""))) -> 46157 | E4: {=IFERROR(INDEX('Batch Dates'!$F:$F,MATCH(J4,'Batch Dates'!$C:$C,0)),IFERROR(INDEX('Batch Dates'!$F:$F,MATCH(I4,'Batch Dates'!$B:$B,0)),""))} -> 45723 | F4: {=IFERROR(INDEX('Batch Dates'!$G:$G,MATCH(J4,'Batch Dates'!$C:$C,0)),IFERROR(INDEX('Batch Dates'!$G:$G,MATCH(I4,'Batch Dates'!$B:$B,0)),""))} -> 45723 | G4: legacy | H4: initial release | I4: BG1024 | J4: N/A — no P batch assigned | K4: Blue Gelato | L4: Ident A + Ident B + Foreign matter | M4: — | N4: {=IFERROR(INDEX('CoQ Register'!$B:$B,MATCH("BG1024|I",'CoQ Register'!$S:$S,0)),"—")} -> CoQ-PP_26-003 | O4: iCoA-PP-2025-0002 | P4: BG1024|I | Q4: registered — issued with the legacy series on 15.05.2026
A5: =IF(C5="yes",COUNT(A$1:A4)+1,"") -> 4 | B5: =IF(A5<>"","iCoA-PP_26-"&TEXT(A5,"000"),IF(C5="n/a","not needed","— at issue —")) -> iCoA-PP_26-004 | C5: yes | D5: =IF(A5="","",IF(G5="legacy",DATE(2026,5,15),IF(ISNUMBER(F5),(F5+5)+CHOOSE(WEEKDAY(F5+5,2),0,0,0,0,0,2,1),""))) -> 46157 | E5: {=IFERROR(INDEX('Batch Dates'!$F:$F,MATCH(J5,'Batch Dates'!$C:$C,0)),IFERROR(INDEX('Batch Dates'!$F:$F,MATCH(I5,'Batch Dates'!$B:$B,0)),""))} -> 45727 | F5: {=IFERROR(INDEX('Batch Dates'!$G:$G,MATCH(J5,'Batch Dates'!$C:$C,0)),IFERROR(INDEX('Batch Dates'!$G:$G,MATCH(I5,'Batch Dates'!$B:$B,0)),""))} -> 45727 | G5: legacy | H5: initial release | I5: GG1024 | J5: N/A — no P batch assigned | K5: Gorilla Glue | L5: Ident A + Ident B + Foreign matter | M5: — | N5: {=IFERROR(INDEX('CoQ Register'!$B:$B,MATCH("GG1024|I",'CoQ Register'!$S:$S,0)),"—")} -> CoQ-PP_26-004 | O5: iCoA-PP-2025-0003 | P5: GG1024|I | Q5: registered — issued with the legacy series on 15.05.2026
A6: =IF(C6="yes",COUNT(A$1:A5)+1,"") -> 5 | B6: =IF(A6<>"","iCoA-PP_26-"&TEXT(A6,"000"),IF(C6="n/a","not needed","— at issue —")) -> iCoA-PP_26-005 | C6: yes | D6: =IF(A6="","",IF(G6="legacy",DATE(2026,5,15),IF(ISNUMBER(F6),(F6+5)+CHOOSE(WEEKDAY(F6+5,2),0,0,0,0,0,2,1),""))) -> 46157 | E6: {=IFERROR(INDEX('Batch Dates'!$F:$F,MATCH(J6,'Batch Dates'!$C:$C,0)),IFERROR(INDEX('Batch Dates'!$F:$F,MATCH(I6,'Batch Dates'!$B:$B,0)),""))} -> 45758 | F6: {=IFERROR(INDEX('Batch Dates'!$G:$G,MATCH(J6,'Batch Dates'!$C:$C,0)),IFERROR(INDEX('Batch Dates'!$G:$G,MATCH(I6,'Batch Dates'!$B:$B,0)),""))} -> 45758 | G6: legacy | H6: initial release | I6: HPA1024 | J6: N/A — no P batch assigned | K6: HighProAmnesia | L6: Ident A + Ident B + Foreign matter | M6: — | N6: {=IFERROR(INDEX('CoQ Register'!$B:$B,MATCH("HPA1024|I",'CoQ Register'!$S:$S,0)),"—")} -> CoQ-PP_26-005 | O6: iCoA-PP-2025-0004 | P6: HPA1024|I | Q6: registered — issued with the legacy series on 15.05.2026
A7: =IF(C7="yes",COUNT(A$1:A6)+1,"") -> 6 | B7: =IF(A7<>"","iCoA-PP_26-"&TEXT(A7,"000"),IF(C7="n/a","not needed","— at issue —")) -> iCoA-PP_26-006 | C7: yes | D7: =IF(A7="","",IF(G7="legacy",DATE(2026,5,15),IF(ISNUMBER(F7),(F7+5)+CHOOSE(WEEKDAY(F7+5,2),0,0,0,0,0,2,1),""))) -> 46157 | E7: {=IFERROR(INDEX('Batch Dates'!$F:$F,MATCH(J7,'Batch Dates'!$C:$C,0)),IFERROR(INDEX('Batch Dates'!$F:$F,MATCH(I7,'Batch Dates'!$B:$B,0)),""))} -> 45771 | F7: {=IFERROR(INDEX('Batch Dates'!$G:$G,MATCH(J7,'Batch Dates'!$C:$C,0)),IFERROR(INDEX('Batch Dates'!$G:$G,MATCH(I7,'Batch Dates'!$B:$B,0)),""))} -> 45772 | G7: legacy | H7: initial release | I7: OPM1024 | J7: N/A — no P batch assigned | K7: OrangePunchMimosa | L7: Ident A + Ident B + Foreign matter | M7: — | N7: {=IFERROR(INDEX('CoQ Register'!$B:$B,MATCH("OPM1024|I",'CoQ Register'!$S:$S,0)),"—")} -> CoQ-PP_26-006 | O7: iCoA-PP-2025-0005 | P7: OPM1024|I | Q7: registered — issued with the legacy series on 15.05.2026
A8: =IF(C8="yes",COUNT(A$1:A7)+1,"") -> 7 | B8: =IF(A8<>"","iCoA-PP_26-"&TEXT(A8,"000"),IF(C8="n/a","not needed","— at issue —")) -> iCoA-PP_26-007 | C8: yes | D8: =IF(A8="","",IF(G8="legacy",DATE(2026,5,15),IF(ISNUMBER(F8),(F8+5)+CHOOSE(WEEKDAY(F8+5,2),0,0,0,0,0,2,1),""))) -> 46157 | E8: {=IFERROR(INDEX('Batch Dates'!$F:$F,MATCH(J8,'Batch Dates'!$C:$C,0)),IFERROR(INDEX('Batch Dates'!$F:$F,MATCH(I8,'Batch Dates'!$B:$B,0)),""))} -> 45811 | F8: {=IFERROR(INDEX('Batch Dates'!$G:$G,MATCH(J8,'Batch Dates'!$C:$C,0)),IFERROR(INDEX('Batch Dates'!$G:$G,MATCH(I8,'Batch Dates'!$B:$B,0)),""))} -> 45819 | G8: legacy | H8: initial release | I8: GP0824_02 | J8: P050022 | K8: Grape Pie | L8: Ident A + Ident B + Foreign matter | M8: — | N8: {=IFERROR(INDEX('CoQ Register'!$B:$B,MATCH("P050022|I",'CoQ Register'!$S:$S,0)),"—")} -> CoQ-PP_26-007 | O8: iCoA-PP-2025-0006 | P8: P050022|I | Q8: registered — issued with the legacy series on 15.05.2026
A9: =IF(C9="yes",COUNT(A$1:A8)+1,"") -> 8 | B9: =IF(A9<>"","iCoA-PP_26-"&TEXT(A9,"000"),IF(C9="n/a","not needed","— at issue —")) -> iCoA-PP_26-008 | C9: yes | D9: =IF(A9="","",IF(G9="legacy",DATE(2026,5,15),IF(ISNUMBER(F9),(F9+5)+CHOOSE(WEEKDAY(F9+5,2),0,0,0,0,0,2,1),""))) -> 46157 | E9: {=IFERROR(INDEX('Batch Dates'!$F:$F,MATCH(J9,'Batch Dates'!$C:$C,0)),IFERROR(INDEX('Batch Dates'!$F:$F,MATCH(I9,'Batch Dates'!$B:$B,0)),""))} -> 45819 | F9: {=IFERROR(INDEX('Batch Dates'!$G:$G,MATCH(J9,'Batch Dates'!$C:$C,0)),IFERROR(INDEX('Batch Dates'!$G:$G,MATCH(I9,'Batch Dates'!$B:$B,0)),""))} -> 45824 | G9: legacy | H9: initial release | I9: GG1024_02 | J9: P050012 | K9: Gorilla Glue | L9: Ident A + Ident B + Foreign matter | M9: — | N9: {=IFERROR(INDEX('CoQ Register'!$B:$B,MATCH("P050012|I",'CoQ Register'!$S:$S,0)),"—")} -> CoQ-PP_26-008 | O9: — | P9: P050012|I | Q9: registered — issued with the legacy series on 15.05.2026
A10: =IF(C10="yes",COUNT(A$1:A9)+1,"") -> 9 | B10: =IF(A10<>"","iCoA-PP_26-"&TEXT(A10,"000"),IF(C10="n/a","not needed","— at issue —")) -> iCoA-PP_26-009 | C10: yes | D10: =IF(A10="","",IF(G10="legacy",DATE(2026,5,15),IF(ISNUMBER(F10),(F10+5)+CHOOSE(WEEKDAY(F10+5,2),0,0,0,0,0,2,1),""))) -> 46157 | E10: {=IFERROR(INDEX('Batch Dates'!$F:$F,MATCH(J10,'Batch Dates'!$C:$C,0)),IFERROR(INDEX('Batch Dates'!$F:$F,MATCH(I10,'Batch Dates'!$B:$B,0)),""))} -> 45824 | F10: {=IFERROR(INDEX('Batch Dates'!$G:$G,MATCH(J10,'Batch Dates'!$C:$C,0)),IFERROR(INDEX('Batch Dates'!$G:$G,MATCH(I10,'Batch Dates'!$B:$B,0)),""))} -> 45827 | G10: legacy | H10: initial release | I10: MB0824_04 | J10: P050032 | K10: Motor Breath | L10: Ident A + Ident B + Foreign matter | M10: — | N10: {=IFERROR(INDEX('CoQ Register'!$B:$B,MATCH("P050032|I",'CoQ Register'!$S:$S,0)),"—")} -> CoQ-PP_26-009 | O10: — | P10: P050032|I | Q10: registered — issued with the legacy series on 15.05.2026
A11: =IF(C11="yes",COUNT(A$1:A10)+1,"") -> 10 | B11: =IF(A11<>"","iCoA-PP_26-"&TEXT(A11,"000"),IF(C11="n/a","not needed","— at issue —")) -> iCoA-PP_26-010 | C11: yes | D11: =IF(A11="","",IF(G11="legacy",DATE(2026,5,15),IF(ISNUMBER(F11),(F11+5)+CHOOSE(WEEKDAY(F11+5,2),0,0,0,0,0,2,1),""))) -> 46157 | E11: {=IFERROR(INDEX('Batch Dates'!$F:$F,MATCH(J11,'Batch Dates'!$C:$C,0)),IFERROR(INDEX('Batch Dates'!$F:$F,MATCH(I11,'Batch Dates'!$B:$B,0)),""))} -> 45828 | F11: {=IFERROR(INDEX('Batch Dates'!$G:$G,MATCH(J11,'Batch Dates'!$C:$C,0)),IFERROR(INDEX('Batch Dates'!$G:$G,MATCH(I11,'Batch Dates'!$B:$B,0)),""))} -> 45828 | G11: legacy | H11: initial release | I11: OMP1024_01 | J11: P050042 | K11: Orange Punch Mimosa | L11: Ident A + Ident B + Foreign matter | M11: — | N11: {=IFERROR(INDEX('CoQ Register'!$B:$B,MATCH("P050042|I",'CoQ Register'!$S:$S,0)),"—")} -> CoQ-PP_26-010 | O11: iCoA-PP-2025-0007 | P11: P050042|I | Q11: registered — issued with the legacy series on 15.05.2026
A12: =IF(C12="yes",COUNT(A$1:A11)+1,"") -> 11 | B12: =IF(A12<>"","iCoA-PP_26-"&TEXT(A12,"000"),IF(C12="n/a","not needed","— at issue —")) -> iCoA-PP_26-011 | C12: yes | D12: =IF(A12="","",IF(G12="legacy",DATE(2026,5,15),IF(ISNUMBER(F12),(F12+5)+CHOOSE(WEEKDAY(F12+5,2),0,0,0,0,0,2,1),""))) -> 46157 | E12: {=IFERROR(INDEX('Batch Dates'!$F:$F,MATCH(J12,'Batch Dates'!$C:$C,0)),IFERROR(INDEX('Batch Dates'!$F:$F,MATCH(I12,'Batch Dates'!$B:$B,0)),""))} -> 45835 | F12: {=IFERROR(INDEX('Batch Dates'!$G:$G,MATCH(J12,'Batch Dates'!$C:$C,0)),IFERROR(INDEX('Batch Dates'!$G:$G,MATCH(I12,'Batch Dates'!$B:$B,0)),""))} -> 45842 | G12: legacy | H12: initial release | I12: HPA1024_01 | J12: P050052 | K12: High Pro Amnesia | L12: Ident A + Ident B + Foreign matter | M12: — | N12: {=IFERROR(INDEX('CoQ Register'!$B:$B,MATCH("P050052|I",'CoQ Register'!$S:$S,0)),"—")} -> CoQ-PP_26-011 | O12: iCoA-PP-2025-0008 | P12: P050052|I | Q12: registered — issued with the legacy series on 15.05.2026
A13: =IF(C13="yes",COUNT(A$1:A12)+1,"") -> 12 | B13: =IF(A13<>"","iCoA-PP_26-"&TEXT(A13,"000"),IF(C13="n/a","not needed","— at issue —")) -> iCoA-PP_26-012 | C13: yes | D13: =IF(A13="","",IF(G13="legacy",DATE(2026,5,15),IF(ISNUMBER(F13),(F13+5)+CHOOSE(WEEKDAY(F13+5,2),0,0,0,0,0,2,1),""))) -> 46157 | E13: {=IFERROR(INDEX('Batch Dates'!$F:$F,MATCH(J13,'Batch Dates'!$C:$C,0)),IFERROR(INDEX('Batch Dates'!$F:$F,MATCH(I13,'Batch Dates'!$B:$B,0)),""))} -> 45842 | F13: {=IFERROR(INDEX('Batch Dates'!$G:$G,MATCH(J13,'Batch Dates'!$C:$C,0)),IFERROR(INDEX('Batch Dates'!$G:$G,MATCH(I13,'Batch Dates'!$B:$B,0)),""))} -> 45848 | G13: legacy | H13: initial release | I13: OPM1024_02 | J13: P050062 | K13: Orange Punch Mimosa | L13: Ident A + Ident B + Foreign matter | M13: — | N13: {=IFERROR(INDEX('CoQ Register'!$B:$B,MATCH("P050062|I",'CoQ Register'!$S:$S,0)),"—")} -> CoQ-PP_26-012 | O13: iCoA-PP-2025-0009 | P13: P050062|I | Q13: registered — issued with the legacy series on 15.05.2026
A14: =IF(C14="yes",COUNT(A$1:A13)+1,"") -> 13 | B14: =IF(A14<>"","iCoA-PP_26-"&TEXT(A14,"000"),IF(C14="n/a","not needed","— at issue —")) -> iCoA-PP_26-013 | C14: yes | D14: =IF(A14="","",IF(G14="legacy",DATE(2026,5,15),IF(ISNUMBER(F14),(F14+5)+CHOOSE(WEEKDAY(F14+5,2),0,0,0,0,0,2,1),""))) -> 46157 | E14: {=IFERROR(INDEX('Batch Dates'!$F:$F,MATCH(J14,'Batch Dates'!$C:$C,0)),IFERROR(INDEX('Batch Dates'!$F:$F,MATCH(I14,'Batch Dates'!$B:$B,0)),""))} -> 45852 | F14: {=IFERROR(INDEX('Batch Dates'!$G:$G,MATCH(J14,'Batch Dates'!$C:$C,0)),IFERROR(INDEX('Batch Dates'!$G:$G,MATCH(I14,'Batch Dates'!$B:$B,0)),""))} -> 45855 | G14: legacy | H14: initial release | I14: GP0824_03 | J14: P050072 | K14: Grape Pie | L14: Ident A + Ident B + Foreign matter | M14: — | N14: {=IFERROR(INDEX('CoQ Register'!$B:$B,MATCH("P050072|I",'CoQ Register'!$S:$S,0)),"—")} -> CoQ-PP_26-013 | O14: iCoA-PP-2025-0010 | P14: P050072|I | Q14: registered — issued with the legacy series on 15.05.2026
A15: =IF(C15="yes",COUNT(A$1:A14)+1,"") -> 14 | B15: =IF(A15<>"","iCoA-PP_26-"&TEXT(A15,"000"),IF(C15="n/a","not needed","— at issue —")) -> iCoA-PP_26-014 | C15: yes | D15: =IF(A15="","",IF(G15="legacy",DATE(2026,5,15),IF(ISNUMBER(F15),(F15+5)+CHOOSE(WEEKDAY(F15+5,2),0,0,0,0,0,2,1),""))) -> 46157 | E15: {=IFERROR(INDEX('Batch Dates'!$F:$F,MATCH(J15,'Batch Dates'!$C:$C,0)),IFERROR(INDEX('Batch Dates'!$F:$F,MATCH(I15,'Batch Dates'!$B:$B,0)),""))} -> 45860 | F15: {=IFERROR(INDEX('Batch Dates'!$G:$G,MATCH(J15,'Batch Dates'!$C:$C,0)),IFERROR(INDEX('Batch Dates'!$G:$G,MATCH(I15,'Batch Dates'!$B:$B,0)),""))} -> 45868 | G15: legacy | H15: initial release | I15: OPM1024_03 | J15: P050082 | K15: Orange Punch Mimosa | L15: Ident A + Ident B + Foreign matter | M15: — | N15: {=IFERROR(INDEX('CoQ Register'!$B:$B,MATCH("P050082|I",'CoQ Register'!$S:$S,0)),"—")} -> CoQ-PP_26-014 | O15: iCoA-PP-2025-0011 | P15: P050082|I | Q15: registered — issued with the legacy series on 15.05.2026
A16: =IF(C16="yes",COUNT(A$1:A15)+1,"") -> 15 | B16: =IF(A16<>"","iCoA-PP_26-"&TEXT(A16,"000"),IF(C16="n/a","not needed","— at issue —")) -> iCoA-PP_26-015 | C16: yes | D16: =IF(A16="","",IF(G16="legacy",DATE(2026,5,15),IF(ISNUMBER(F16),(F16+5)+CHOOSE(WEEKDAY(F16+5,2),0,0,0,0,0,2,1),""))) -> 46157 | E16: {=IFERROR(INDEX('Batch Dates'!$F:$F,MATCH(J16,'Batch Dates'!$C:$C,0)),IFERROR(INDEX('Batch Dates'!$F:$F,MATCH(I16,'Batch Dates'!$B:$B,0)),""))} -> 45869 | F16: {=IFERROR(INDEX('Batch Dates'!$G:$G,MATCH(J16,'Batch Dates'!$C:$C,0)),IFERROR(INDEX('Batch Dates'!$G:$G,MATCH(I16,'Batch Dates'!$B:$B,0)),""))} -> 45874 | G16: legacy | H16: initial release | I16: GG1024_01 | J16: P050092 | K16: Gorilla Glue | L16: Ident A + Ident B + Foreign matter | M16: — | N16: {=IFERROR(INDEX('CoQ Register'!$B:$B,MATCH("P050092|I",'CoQ Register'!$S:$S,0)),"—")} -> CoQ-PP_26-015 | O16: iCoA-PP-2025-0012 | P16: P050092|I | Q16: registered — issued with the legacy series on 15.05.2026
A17: =IF(C17="yes",COUNT(A$1:A16)+1,"") -> 16 | B17: =IF(A17<>"","iCoA-PP_26-"&TEXT(A17,"000"),IF(C17="n/a","not needed","— at issue —")) -> iCoA-PP_26-016 | C17: yes | D17: =IF(A17="","",IF(G17="legacy",DATE(2026,5,15),IF(ISNUMBER(F17),(F17+5)+CHOOSE(WEEKDAY(F17+5,2),0,0,0,0,0,2,1),""))) -> 46157 | E17: {=IFERROR(INDEX('Batch Dates'!$F:$F,MATCH(J17,'Batch Dates'!$C:$C,0)),IFERROR(INDEX('Batch Dates'!$F:$F,MATCH(I17,'Batch Dates'!$B:$B,0)),""))} -> 45874 | F17: {=IFERROR(INDEX('Batch Dates'!$G:$G,MATCH(J17,'Batch Dates'!$C:$C,0)),IFERROR(INDEX('Batch Dates'!$G:$G,MATCH(I17,'Batch Dates'!$B:$B,0)),""))} -> 45876 | G17: legacy | H17: initial release | I17: GP0824_01 | J17: P050102 | K17: Grape Pie | L17: Ident A + Ident B + Foreign matter | M17: — | N17: {=IFERROR(INDEX('CoQ Register'!$B:$B,MATCH("P050102|I",'CoQ Register'!$S:$S,0)),"—")} -> CoQ-PP_26-016 | O17: — | P17: P050102|I | Q17: registered — issued with the legacy series on 15.05.2026
A18: =IF(C18="yes",COUNT(A$1:A17)+1,"") -> 17 | B18: =IF(A18<>"","iCoA-PP_26-"&TEXT(A18,"000"),IF(C18="n/a","not needed","— at issue —")) -> iCoA-PP_26-017 | C18: yes | D18: =IF(A18="","",IF(G18="legacy",DATE(2026,5,15),IF(ISNUMBER(F18),(F18+5)+CHOOSE(WEEKDAY(F18+5,2),0,0,0,0,0,2,1),""))) -> 46157 | E18: {=IFERROR(INDEX('Batch Dates'!$F:$F,MATCH(J18,'Batch Dates'!$C:$C,0)),IFERROR(INDEX('Batch Dates'!$F:$F,MATCH(I18,'Batch Dates'!$B:$B,0)),""))} -> 45894 | F18: {=IFERROR(INDEX('Batch Dates'!$G:$G,MATCH(J18,'Batch Dates'!$C:$C,0)),IFERROR(INDEX('Batch Dates'!$G:$G,MATCH(I18,'Batch Dates'!$B:$B,0)),""))} -> 45900 | G18: legacy | H18: initial release | I18: MB0824_05 | J18: P050112 | K18: Motor Breath | L18: Ident A + Ident B + Foreign matter | M18: — | N18: {=IFERROR(INDEX('CoQ Register'!$B:$B,MATCH("P050112|I",'CoQ Register'!$S:$S,0)),"—")} -> CoQ-PP_26-017 | O18: iCoA-PP-2025-0013 | P18: P050112|I | Q18: registered — issued with the legacy series on 15.05.2026
A19: =IF(C19="yes",COUNT(A$1:A18)+1,"") -> 18 | B19: =IF(A19<>"","iCoA-PP_26-"&TEXT(A19,"000"),IF(C19="n/a","not needed","— at issue —")) -> iCoA-PP_26-018 | C19: yes | D19: =IF(A19="","",IF(G19="legacy",DATE(2026,5,15),IF(ISNUMBER(F19),(F19+5)+CHOOSE(WEEKDAY(F19+5,2),0,0,0,0,0,2,1),""))) -> 46157 | E19: {=IFERROR(INDEX('Batch Dates'!$F:$F,MATCH(J19,'Batch Dates'!$C:$C,0)),IFERROR(INDEX('Batch Dates'!$F:$F,MATCH(I19,'Batch Dates'!$B:$B,0)),""))} -> 45901 | F19: {=IFERROR(INDEX('Batch Dates'!$G:$G,MATCH(J19,'Batch Dates'!$C:$C,0)),IFERROR(INDEX('Batch Dates'!$G:$G,MATCH(I19,'Batch Dates'!$B:$B,0)),""))} -> 45909 | G19: legacy | H19: initial release | I19: BSS1024_01/1 | J19: P050122 | K19: Blue Sunset Sherbet | L19: Ident A + Ident B + Foreign matter | M19: — | N19: {=IFERROR(INDEX('CoQ Register'!$B:$B,MATCH("P050122|I",'CoQ Register'!$S:$S,0)),"—")} -> CoQ-PP_26-018 | O19: — | P19: P050122|I | Q19: registered — issued with the legacy series on 15.05.2026
A20: =IF(C20="yes",COUNT(A$1:A19)+1,"") -> 19 | B20: =IF(A20<>"","iCoA-PP_26-"&TEXT(A20,"000"),IF(C20="n/a","not needed","— at issue —")) -> iCoA-PP_26-019 | C20: yes | D20: =IF(A20="","",IF(G20="legacy",DATE(2026,5,15),IF(ISNUMBER(F20),(F20+5)+CHOOSE(WEEKDAY(F20+5,2),0,0,0,0,0,2,1),""))) -> 46157 | E20: {=IFERROR(INDEX('Batch Dates'!$F:$F,MATCH(J20,'Batch Dates'!$C:$C,0)),IFERROR(INDEX('Batch Dates'!$F:$F,MATCH(I20,'Batch Dates'!$B:$B,0)),""))} -> 45909 | F20: {=IFERROR(INDEX('Batch Dates'!$G:$G,MATCH(J20,'Batch Dates'!$C:$C,0)),IFERROR(INDEX('Batch Dates'!$G:$G,MATCH(I20,'Batch Dates'!$B:$B,0)),""))} -> 45915 | G20: legacy | H20: initial release | I20: OPM052501 | J20: P050132 | K20: Orange Punch Mimosa | L20: Ident A + Ident B + Foreign matter | M20: — | N20: {=IFERROR(INDEX('CoQ Register'!$B:$B,MATCH("P050132|I",'CoQ Register'!$S:$S,0)),"—")} -> CoQ-PP_26-019 | O20: — | P20: P050132|I | Q20: registered — issued with the legacy series on 15.05.2026
A21: =IF(C21="yes",COUNT(A$1:A20)+1,"") -> 20 | B21: =IF(A21<>"","iCoA-PP_26-"&TEXT(A21,"000"),IF(C21="n/a","not needed","— at issue —")) -> iCoA-PP_26-020 | C21: yes | D21: =IF(A21="","",IF(G21="legacy",DATE(2026,5,15),IF(ISNUMBER(F21),(F21+5)+CHOOSE(WEEKDAY(F21+5,2),0,0,0,0,0,2,1),""))) -> 46157 | E21: {=IFERROR(INDEX('Batch Dates'!$F:$F,MATCH(J21,'Batch Dates'!$C:$C,0)),IFERROR(INDEX('Batch Dates'!$F:$F,MATCH(I21,'Batch Dates'!$B:$B,0)),""))} -> 45925 | F21: {=IFERROR(INDEX('Batch Dates'!$G:$G,MATCH(J21,'Batch Dates'!$C:$C,0)),IFERROR(INDEX('Batch Dates'!$G:$G,MATCH(I21,'Batch Dates'!$B:$B,0)),""))} -> 45925 | G21: legacy | H21: initial release | I21: GP052501 | J21: P050152 | K21: Grape Pie | L21: Ident A + Ident B + Foreign matter | M21: — | N21: {=IFERROR(INDEX('CoQ Register'!$B:$B,MATCH("P050152|I",'CoQ Register'!$S:$S,0)),"—")} -> CoQ-PP_26-020 | O21: iCoA-PP-2025-0014 | P21: P050152|I | Q21: registered — issued with the legacy series on 15.05.2026
A22: =IF(C22="yes",COUNT(A$1:A21)+1,"") -> 21 | B22: =IF(A22<>"","iCoA-PP_26-"&TEXT(A22,"000"),IF(C22="n/a","not needed","— at issue —")) -> iCoA-PP_26-021 | C22: yes | D22: =IF(A22="","",IF(G22="legacy",DATE(2026,5,15),IF(ISNUMBER(F22),(F22+5)+CHOOSE(WEEKDAY(F22+5,2),0,0,0,0,0,2,1),""))) -> 46157 | E22: {=IFERROR(INDEX('Batch Dates'!$F:$F,MATCH(J22,'Batch Dates'!$C:$C,0)),IFERROR(INDEX('Batch Dates'!$F:$F,MATCH(I22,'Batch Dates'!$B:$B,0)),""))} -> 45930 | F22: {=IFERROR(INDEX('Batch Dates'!$G:$G,MATCH(J22,'Batch Dates'!$C:$C,0)),IFERROR(INDEX('Batch Dates'!$G:$G,MATCH(I22,'Batch Dates'!$B:$B,0)),""))} -> 45930 | G22: legacy | H22: initial release | I22: BSS1024_01/2 | J22: P050142 | K22: Blue Sunset Sherbet | L22: Ident A + Ident B + Foreign matter | M22: — | N22: {=IFERROR(INDEX('CoQ Register'!$B:$B,MATCH("P050142|I",'CoQ Register'!$S:$S,0)),"—")} -> CoQ-PP_26-021 | O22: — | P22: P050142|I | Q22: registered — issued with the legacy series on 15.05.2026
A23: =IF(C23="yes",COUNT(A$1:A22)+1,"") -> 22 | B23: =IF(A23<>"","iCoA-PP_26-"&TEXT(A23,"000"),IF(C23="n/a","not needed","— at issue —")) -> iCoA-PP_26-022 | C23: yes | D23: =IF(A23="","",IF(G23="legacy",DATE(2026,5,15),IF(ISNUMBER(F23),(F23+5)+CHOOSE(WEEKDAY(F23+5,2),0,0,0,0,0,2,1),""))) -> 46157 | E23: {=IFERROR(INDEX('Batch Dates'!$F:$F,MATCH(J23,'Batch Dates'!$C:$C,0)),IFERROR(INDEX('Batch Dates'!$F:$F,MATCH(I23,'Batch Dates'!$B:$B,0)),""))} -> 45930 | F23: {=IFERROR(INDEX('Batch Dates'!$G:$G,MATCH(J23,'Batch Dates'!$C:$C,0)),IFERROR(INDEX('Batch Dates'!$G:$G,MATCH(I23,'Batch Dates'!$B:$B,0)),""))} -> 45931 | G23: legacy | H23: initial release | I23: CJ052501/01 | J23: P050162 | K23: Cup Junky | L23: Ident A + Ident B + Foreign matter | M23: — | N23: {=IFERROR(INDEX('CoQ Register'!$B:$B,MATCH("P050162|I",'CoQ Register'!$S:$S,0)),"—")} -> CoQ-PP_26-022 | O23: iCoA-PP-2025-0015 | P23: P050162|I | Q23: registered — issued with the legacy series on 15.05.2026
A24: =IF(C24="yes",COUNT(A$1:A23)+1,"") -> 23 | B24: =IF(A24<>"","iCoA-PP_26-"&TEXT(A24,"000"),IF(C24="n/a","not needed","— at issue —")) -> iCoA-PP_26-023 | C24: yes | D24: =IF(A24="","",IF(G24="legacy",DATE(2026,5,15),IF(ISNUMBER(F24),(F24+5)+CHOOSE(WEEKDAY(F24+5,2),0,0,0,0,0,2,1),""))) -> 46157 | E24: {=IFERROR(INDEX('Batch Dates'!$F:$F,MATCH(J24,'Batch Dates'!$C:$C,0)),IFERROR(INDEX('Batch Dates'!$F:$F,MATCH(I24,'Batch Dates'!$B:$B,0)),""))} -> 45931 | F24: {=IFERROR(INDEX('Batch Dates'!$G:$G,MATCH(J24,'Batch Dates'!$C:$C,0)),IFERROR(INDEX('Batch Dates'!$G:$G,MATCH(I24,'Batch Dates'!$B:$B,0)),""))} -> 45932 | G24: legacy | H24: initial release | I24: CJ052501/02 | J24: P050172 | K24: Cap Junky | L24: Ident A + Ident B + Foreign matter | M24: — | N24: {=IFERROR(INDEX('CoQ Register'!$B:$B,MATCH("P050172|I",'CoQ Register'!$S:$S,0)),"—")} -> CoQ-PP_26-023 | O24: — | P24: P050172|I | Q24: registered — issued with the legacy series on 15.05.2026
A25: =IF(C25="yes",COUNT(A$1:A24)+1,"") -> 24 | B25: =IF(A25<>"","iCoA-PP_26-"&TEXT(A25,"000"),IF(C25="n/a","not needed","— at issue —")) -> iCoA-PP_26-024 | C25: yes | D25: =IF(A25="","",IF(G25="legacy",DATE(2026,5,15),IF(ISNUMBER(F25),(F25+5)+CHOOSE(WEEKDAY(F25+5,2),0,0,0,0,0,2,1),""))) -> 46157 | E25: {=IFERROR(INDEX('Batch Dates'!$F:$F,MATCH(J25,'Batch Dates'!$C:$C,0)),IFERROR(INDEX('Batch Dates'!$F:$F,MATCH(I25,'Batch Dates'!$B:$B,0)),""))} -> 45933 | F25: {=IFERROR(INDEX('Batch Dates'!$G:$G,MATCH(J25,'Batch Dates'!$C:$C,0)),IFERROR(INDEX('Batch Dates'!$G:$G,MATCH(I25,'Batch Dates'!$B:$B,0)),""))} -> 45939 | G25: legacy | H25: initial release | I25: HPA052501 | J25: P050182 | K25: High Pro Amnesia | L25: Ident A + Ident B + Foreign matter | M25: — | N25: {=IFERROR(INDEX('CoQ Register'!$B:$B,MATCH("P050182|I",'CoQ Register'!$S:$S,0)),"—")} -> CoQ-PP_26-024 | O25: iCoA-PP-2025-0016 | P25: P050182|I | Q25: registered — issued with the legacy series on 15.05.2026
A26: =IF(C26="yes",COUNT(A$1:A25)+1,"") -> 25 | B26: =IF(A26<>"","iCoA-PP_26-"&TEXT(A26,"000"),IF(C26="n/a","not needed","— at issue —")) -> iCoA-PP_26-025 | C26: yes | D26: =IF(A26="","",IF(G26="legacy",DATE(2026,5,15),IF(ISNUMBER(F26),(F26+5)+CHOOSE(WEEKDAY(F26+5,2),0,0,0,0,0,2,1),""))) -> 46157 | E26: {=IFERROR(INDEX('Batch Dates'!$F:$F,MATCH(J26,'Batch Dates'!$C:$C,0)),IFERROR(INDEX('Batch Dates'!$F:$F,MATCH(I26,'Batch Dates'!$B:$B,0)),""))} -> 45940 | F26: {=IFERROR(INDEX('Batch Dates'!$G:$G,MATCH(J26,'Batch Dates'!$C:$C,0)),IFERROR(INDEX('Batch Dates'!$G:$G,MATCH(I26,'Batch Dates'!$B:$B,0)),""))} -> 45951 | G26: legacy | H26: initial release | I26: BSS052501 | J26: P050192 | K26: Sleepy Joe | L26: Ident A + Ident B + Foreign matter | M26: — | N26: {=IFERROR(INDEX('CoQ Register'!$B:$B,MATCH("P050192|I",'CoQ Register'!$S:$S,0)),"—")} -> CoQ-PP_26-025 | O26: iCoA-PP-2025-0017 | P26: P050192|I | Q26: registered — issued with the legacy series on 15.05.2026
A27: =IF(C27="yes",COUNT(A$1:A26)+1,"") -> 26 | B27: =IF(A27<>"","iCoA-PP_26-"&TEXT(A27,"000"),IF(C27="n/a","not needed","— at issue —")) -> iCoA-PP_26-026 | C27: yes | D27: =IF(A27="","",IF(G27="legacy",DATE(2026,5,15),IF(ISNUMBER(F27),(F27+5)+CHOOSE(WEEKDAY(F27+5,2),0,0,0,0,0,2,1),""))) -> 46157 | E27: {=IFERROR(INDEX('Batch Dates'!$F:$F,MATCH(J27,'Batch Dates'!$C:$C,0)),IFERROR(INDEX('Batch Dates'!$F:$F,MATCH(I27,'Batch Dates'!$B:$B,0)),""))} -> 45960 | F27: {=IFERROR(INDEX('Batch Dates'!$G:$G,MATCH(J27,'Batch Dates'!$C:$C,0)),IFERROR(INDEX('Batch Dates'!$G:$G,MATCH(I27,'Batch Dates'!$B:$B,0)),""))} -> 45968 | G27: legacy | H27: initial release | I27: GP062501 | J27: P050202 | K27: Grape Pie | L27: Ident A + Ident B + Foreign matter | M27: — | N27: {=IFERROR(INDEX('CoQ Register'!$B:$B,MATCH("P050202|I",'CoQ Register'!$S:$S,0)),"—")} -> CoQ-PP_26-026 | O27: — | P27: P050202|I | Q27: registered — issued with the legacy series on 15.05.2026
A28: =IF(C28="yes",COUNT(A$1:A27)+1,"") -> 27 | B28: =IF(A28<>"","iCoA-PP_26-"&TEXT(A28,"000"),IF(C28="n/a","not needed","— at issue —")) -> iCoA-PP_26-027 | C28: yes | D28: =IF(A28="","",IF(G28="legacy",DATE(2026,5,15),IF(ISNUMBER(F28),(F28+5)+CHOOSE(WEEKDAY(F28+5,2),0,0,0,0,0,2,1),""))) -> 46157 | E28: {=IFERROR(INDEX('Batch Dates'!$F:$F,MATCH(J28,'Batch Dates'!$C:$C,0)),IFERROR(INDEX('Batch Dates'!$F:$F,MATCH(I28,'Batch Dates'!$B:$B,0)),""))} -> 45979 | F28: {=IFERROR(INDEX('Batch Dates'!$G:$G,MATCH(J28,'Batch Dates'!$C:$C,0)),IFERROR(INDEX('Batch Dates'!$G:$G,MATCH(I28,'Batch Dates'!$B:$B,0)),""))} -> 45985 | G28: legacy | H28: initial release | I28: CJ062501/2 | J28: P050212 | K28: Cap Junkie | L28: Ident A + Ident B + Foreign matter | M28: — | N28: {=IFERROR(INDEX('CoQ Register'!$B:$B,MATCH("P050212|I",'CoQ Register'!$S:$S,0)),"—")} -> CoQ-PP_26-027 | O28: — | P28: P050212|I | Q28: registered — issued with the legacy series on 15.05.2026
A29: =IF(C29="yes",COUNT(A$1:A28)+1,"") -> 28 | B29: =IF(A29<>"","iCoA-PP_26-"&TEXT(A29,"000"),IF(C29="n/a","not needed","— at issue —")) -> iCoA-PP_26-028 | C29: yes | D29: =IF(A29="","",IF(G29="legacy",DATE(2026,5,15),IF(ISNUMBER(F29),(F29+5)+CHOOSE(WEEKDAY(F29+5,2),0,0,0,0,0,2,1),""))) -> 46157 | E29: {=IFERROR(INDEX('Batch Dates'!$F:$F,MATCH(J29,'Batch Dates'!$C:$C,0)),IFERROR(INDEX('Batch Dates'!$F:$F,MATCH(I29,'Batch Dates'!$B:$B,0)),""))} -> 45985 | F29: {=IFERROR(INDEX('Batch Dates'!$G:$G,MATCH(J29,'Batch Dates'!$C:$C,0)),IFERROR(INDEX('Batch Dates'!$G:$G,MATCH(I29,'Batch Dates'!$B:$B,0)),""))} -> 45986 | G29: legacy | H29: initial release | I29: CJ062501/1 | J29: P050222 | K29: Cap Junkie | L29: Ident A + Ident B + Foreign matter | M29: — | N29: {=IFERROR(INDEX('CoQ Register'!$B:$B,MATCH("P050222|I",'CoQ Register'!$S:$S,0)),"—")} -> CoQ-PP_26-028 | O29: iCoA-PP-2025-0018 | P29: P050222|I | Q29: registered — issued with the legacy series on 15.05.2026
A30: =IF(C30="yes",COUNT(A$1:A29)+1,"") -> 29 | B30: =IF(A30<>"","iCoA-PP_26-"&TEXT(A30,"000"),IF(C30="n/a","not needed","— at issue —")) -> iCoA-PP_26-029 | C30: yes | D30: =IF(A30="","",IF(G30="legacy",DATE(2026,5,15),IF(ISNUMBER(F30),(F30+5)+CHOOSE(WEEKDAY(F30+5,2),0,0,0,0,0,2,1),""))) -> 46157 | E30: {=IFERROR(INDEX('Batch Dates'!$F:$F,MATCH(J30,'Batch Dates'!$C:$C,0)),IFERROR(INDEX('Batch Dates'!$F:$F,MATCH(I30,'Batch Dates'!$B:$B,0)),""))} -> 45988 | F30: {=IFERROR(INDEX('Batch Dates'!$G:$G,MATCH(J30,'Batch Dates'!$C:$C,0)),IFERROR(INDEX('Batch Dates'!$G:$G,MATCH(I30,'Batch Dates'!$B:$B,0)),""))} -> 45989 | G30: legacy | H30: initial release | I30: CJ072501 | J30: P050252 | K30: Cap Junky | L30: Ident A + Ident B + Foreign matter | M30: — | N30: {=IFERROR(INDEX('CoQ Register'!$B:$B,MATCH("P050252|I",'CoQ Register'!$S:$S,0)),"—")} -> CoQ-PP_26-029 | O30: — | P30: P050252|I | Q30: registered — issued with the legacy series on 15.05.2026
A31: =IF(C31="yes",COUNT(A$1:A30)+1,"") -> 30 | B31: =IF(A31<>"","iCoA-PP_26-"&TEXT(A31,"000"),IF(C31="n/a","not needed","— at issue —")) -> iCoA-PP_26-030 | C31: yes | D31: =IF(A31="","",IF(G31="legacy",DATE(2026,5,15),IF(ISNUMBER(F31),(F31+5)+CHOOSE(WEEKDAY(F31+5,2),0,0,0,0,0,2,1),""))) -> 46157 | E31: {=IFERROR(INDEX('Batch Dates'!$F:$F,MATCH(J31,'Batch Dates'!$C:$C,0)),IFERROR(INDEX('Batch Dates'!$F:$F,MATCH(I31,'Batch Dates'!$B:$B,0)),""))} -> 45992 | F31: {=IFERROR(INDEX('Batch Dates'!$G:$G,MATCH(J31,'Batch Dates'!$C:$C,0)),IFERROR(INDEX('Batch Dates'!$G:$G,MATCH(I31,'Batch Dates'!$B:$B,0)),""))} -> 45992 | G31: legacy | H31: initial release | I31: WC072501 | J31: P050262 | K31: Wedding Crusher | L31: Ident A + Ident B + Foreign matter | M31: — | N31: {=IFERROR(INDEX('CoQ Register'!$B:$B,MATCH("P050262|I",'CoQ Register'!$S:$S,0)),"—")} -> CoQ-PP_26-030 | O31: — | P31: P050262|I | Q31: registered — issued with the legacy series on 15.05.2026
A32: =IF(C32="yes",COUNT(A$1:A31)+1,"") -> 31 | B32: =IF(A32<>"","iCoA-PP_26-"&TEXT(A32,"000"),IF(C32="n/a","not needed","— at issue —")) -> iCoA-PP_26-031 | C32: yes | D32: =IF(A32="","",IF(G32="legacy",DATE(2026,5,15),IF(ISNUMBER(F32),(F32+5)+CHOOSE(WEEKDAY(F32+5,2),0,0,0,0,0,2,1),""))) -> 46157 | E32: {=IFERROR(INDEX('Batch Dates'!$F:$F,MATCH(J32,'Batch Dates'!$C:$C,0)),IFERROR(INDEX('Batch Dates'!$F:$F,MATCH(I32,'Batch Dates'!$B:$B,0)),""))} -> 45993 | F32: {=IFERROR(INDEX('Batch Dates'!$G:$G,MATCH(J32,'Batch Dates'!$C:$C,0)),IFERROR(INDEX('Batch Dates'!$G:$G,MATCH(I32,'Batch Dates'!$B:$B,0)),""))} -> 45994 | G32: legacy | H32: initial release | I32: PM072501 | J32: P050272 | K32: Permanent Marker | L32: Ident A + Ident B + Foreign matter | M32: — | N32: {=IFERROR(INDEX('CoQ Register'!$B:$B,MATCH("P050272|I",'CoQ Register'!$S:$S,0)),"—")} -> CoQ-PP_26-031 | O32: — | P32: P050272|I | Q32: registered — issued with the legacy series on 15.05.2026
A33: =IF(C33="yes",COUNT(A$1:A32)+1,"") -> 32 | B33: =IF(A33<>"","iCoA-PP_26-"&TEXT(A33,"000"),IF(C33="n/a","not needed","— at issue —")) -> iCoA-PP_26-032 | C33: yes | D33: =IF(A33="","",IF(G33="legacy",DATE(2026,5,15),IF(ISNUMBER(F33),(F33+5)+CHOOSE(WEEKDAY(F33+5,2),0,0,0,0,0,2,1),""))) -> 46157 | E33: {=IFERROR(INDEX('Batch Dates'!$F:$F,MATCH(J33,'Batch Dates'!$C:$C,0)),IFERROR(INDEX('Batch Dates'!$F:$F,MATCH(I33,'Batch Dates'!$B:$B,0)),""))} -> 45994 | F33: {=IFERROR(INDEX('Batch Dates'!$G:$G,MATCH(J33,'Batch Dates'!$C:$C,0)),IFERROR(INDEX('Batch Dates'!$G:$G,MATCH(I33,'Batch Dates'!$B:$B,0)),""))} -> 45995 | G33: legacy | H33: initial release | I33: CLE072501 | J33: P050282 | K33: Clemosa a bud | L33: Ident A + Ident B + Foreign matter | M33: — | N33: {=IFERROR(INDEX('CoQ Register'!$B:$B,MATCH("P050282|I",'CoQ Register'!$S:$S,0)),"—")} -> CoQ-PP_26-032 | O33: iCoA-PP-2025-0019 | P33: P050282|I | Q33: registered — issued with the legacy series on 15.05.2026
A34: =IF(C34="yes",COUNT(A$1:A33)+1,"") -> 33 | B34: =IF(A34<>"","iCoA-PP_26-"&TEXT(A34,"000"),IF(C34="n/a","not needed","— at issue —")) -> iCoA-PP_26-033 | C34: yes | D34: =IF(A34="","",IF(G34="legacy",DATE(2026,5,15),IF(ISNUMBER(F34),(F34+5)+CHOOSE(WEEKDAY(F34+5,2),0,0,0,0,0,2,1),""))) -> 46157 | E34: {=IFERROR(INDEX('Batch Dates'!$F:$F,MATCH(J34,'Batch Dates'!$C:$C,0)),IFERROR(INDEX('Batch Dates'!$F:$F,MATCH(I34,'Batch Dates'!$B:$B,0)),""))} -> 46006 | F34: {=IFERROR(INDEX('Batch Dates'!$G:$G,MATCH(J34,'Batch Dates'!$C:$C,0)),IFERROR(INDEX('Batch Dates'!$G:$G,MATCH(I34,'Batch Dates'!$B:$B,0)),""))} -> 46012 | G34: legacy | H34: initial release | I34: GP072501/1 | J34: P050292 | K34: Grape Pie | L34: Ident A + Ident B + Foreign matter | M34: — | N34: {=IFERROR(INDEX('CoQ Register'!$B:$B,MATCH("P050292|I",'CoQ Register'!$S:$S,0)),"—")} -> CoQ-PP_26-033 | O34: — | P34: P050292|I | Q34: registered — issued with the legacy series on 15.05.2026
A35: =IF(C35="yes",COUNT(A$1:A34)+1,"") -> 34 | B35: =IF(A35<>"","iCoA-PP_26-"&TEXT(A35,"000"),IF(C35="n/a","not needed","— at issue —")) -> iCoA-PP_26-034 | C35: yes | D35: =IF(A35="","",IF(G35="legacy",DATE(2026,5,15),IF(ISNUMBER(F35),(F35+5)+CHOOSE(WEEKDAY(F35+5,2),0,0,0,0,0,2,1),""))) -> 46157 | E35: {=IFERROR(INDEX('Batch Dates'!$F:$F,MATCH(J35,'Batch Dates'!$C:$C,0)),IFERROR(INDEX('Batch Dates'!$F:$F,MATCH(I35,'Batch Dates'!$B:$B,0)),""))} -> 46013 | F35: {=IFERROR(INDEX('Batch Dates'!$G:$G,MATCH(J35,'Batch Dates'!$C:$C,0)),IFERROR(INDEX('Batch Dates'!$G:$G,MATCH(I35,'Batch Dates'!$B:$B,0)),""))} -> 46013 | G35: legacy | H35: initial release | I35: GP072501/2 | J35: P050302 | K35: Grape Pie | L35: Ident A + Ident B + Foreign matter | M35: — | N35: {=IFERROR(INDEX('CoQ Register'!$B:$B,MATCH("P050302|I",'CoQ Register'!$S:$S,0)),"—")} -> CoQ-PP_26-034 | O35: iCoA-PP-2025-0020 | P35: P050302|I | Q35: registered — issued with the legacy series on 15.05.2026
A36: =IF(C36="yes",COUNT(A$1:A35)+1,"") -> 35 | B36: =IF(A36<>"","iCoA-PP_26-"&TEXT(A36,"000"),IF(C36="n/a","not needed","— at issue —")) -> iCoA-PP_26-035 | C36: yes | D36: =IF(A36="","",IF(G36="legacy",DATE(2026,5,15),IF(ISNUMBER(F36),(F36+5)+CHOOSE(WEEKDAY(F36+5,2),0,0,0,0,0,2,1),""))) -> 46157 | E36: {=IFERROR(INDEX('Batch Dates'!$F:$F,MATCH(J36,'Batch Dates'!$C:$C,0)),IFERROR(INDEX('Batch Dates'!$F:$F,MATCH(I36,'Batch Dates'!$B:$B,0)),""))} -> 46014 | F36: {=IFERROR(INDEX('Batch Dates'!$G:$G,MATCH(J36,'Batch Dates'!$C:$C,0)),IFERROR(INDEX('Batch Dates'!$G:$G,MATCH(I36,'Batch Dates'!$B:$B,0)),""))} -> 46017 | G36: legacy | H36: initial release | I36: GP082501/1 | J36: P050312 | K36: Grape Pie | L36: Ident A + Ident B + Foreign matter | M36: — | N36: {=IFERROR(INDEX('CoQ Register'!$B:$B,MATCH("P050312|I",'CoQ Register'!$S:$S,0)),"—")} -> CoQ-PP_26-035 | O36: iCoA-PP-2025-0021 | P36: P050312|I | Q36: registered — issued with the legacy series on 15.05.2026
A37: =IF(C37="yes",COUNT(A$1:A36)+1,"") -> 36 | B37: =IF(A37<>"","iCoA-PP_26-"&TEXT(A37,"000"),IF(C37="n/a","not needed","— at issue —")) -> iCoA-PP_26-036 | C37: yes | D37: =IF(A37="","",IF(G37="legacy",DATE(2026,5,15),IF(ISNUMBER(F37),(F37+5)+CHOOSE(WEEKDAY(F37+5,2),0,0,0,0,0,2,1),""))) -> 46157 | E37: {=IFERROR(INDEX('Batch Dates'!$F:$F,MATCH(J37,'Batch Dates'!$C:$C,0)),IFERROR(INDEX('Batch Dates'!$F:$F,MATCH(I37,'Batch Dates'!$B:$B,0)),""))} -> 46017 | F37: {=IFERROR(INDEX('Batch Dates'!$G:$G,MATCH(J37,'Batch Dates'!$C:$C,0)),IFERROR(INDEX('Batch Dates'!$G:$G,MATCH(I37,'Batch Dates'!$B:$B,0)),""))} -> 46017 | G37: legacy | H37: initial release | I37: GP082501/2 | J37: P050322 | K37: Grape Pie | L37: Ident A + Ident B + Foreign matter | M37: — | N37: {=IFERROR(INDEX('CoQ Register'!$B:$B,MATCH("P050322|I",'CoQ Register'!$S:$S,0)),"—")} -> CoQ-PP_26-036 | O37: iCoA-PP-2025-0022 | P37: P050322|I | Q37: registered — issued with the legacy series on 15.05.2026
A38: =IF(C38="yes",COUNT(A$1:A37)+1,"") -> 37 | B38: =IF(A38<>"","iCoA-PP_26-"&TEXT(A38,"000"),IF(C38="n/a","not needed","— at issue —")) -> iCoA-PP_26-037 | C38: yes | D38: =IF(A38="","",IF(G38="legacy",DATE(2026,5,15),IF(ISNUMBER(F38),(F38+5)+CHOOSE(WEEKDAY(F38+5,2),0,0,0,0,0,2,1),""))) -> 46157 | E38: {=IFERROR(INDEX('Batch Dates'!$F:$F,MATCH(J38,'Batch Dates'!$C:$C,0)),IFERROR(INDEX('Batch Dates'!$F:$F,MATCH(I38,'Batch Dates'!$B:$B,0)),""))} -> 46035 | F38: {=IFERROR(INDEX('Batch Dates'!$G:$G,MATCH(J38,'Batch Dates'!$C:$C,0)),IFERROR(INDEX('Batch Dates'!$G:$G,MATCH(I38,'Batch Dates'!$B:$B,0)),""))} -> 46036 | G38: legacy | H38: initial release | I38: WC082501 | J38: P060012 | K38: Wedding Crasher | L38: Ident A + Ident B + Foreign matter | M38: — | N38: {=IFERROR(INDEX('CoQ Register'!$B:$B,MATCH("P060012|I",'CoQ Register'!$S:$S,0)),"—")} -> CoQ-PP_26-037 | O38: iCoA-PP-2026-0001 | P38: P060012|I | Q38: registered — issued with the legacy series on 15.05.2026
A39: =IF(C39="yes",COUNT(A$1:A38)+1,"") -> 38 | B39: =IF(A39<>"","iCoA-PP_26-"&TEXT(A39,"000"),IF(C39="n/a","not needed","— at issue —")) -> iCoA-PP_26-038 | C39: yes | D39: =IF(A39="","",IF(G39="legacy",DATE(2026,5,15),IF(ISNUMBER(F39),(F39+5)+CHOOSE(WEEKDAY(F39+5,2),0,0,0,0,0,2,1),""))) -> 46157 | E39: {=IFERROR(INDEX('Batch Dates'!$F:$F,MATCH(J39,'Batch Dates'!$C:$C,0)),IFERROR(INDEX('Batch Dates'!$F:$F,MATCH(I39,'Batch Dates'!$B:$B,0)),""))} -> 46038 | F39: {=IFERROR(INDEX('Batch Dates'!$G:$G,MATCH(J39,'Batch Dates'!$C:$C,0)),IFERROR(INDEX('Batch Dates'!$G:$G,MATCH(I39,'Batch Dates'!$B:$B,0)),""))} -> 46038 | G39: legacy | H39: initial release | I39: CJ082501/1 | J39: P060022 | K39: Cap Junky | L39: Ident A + Ident B + Foreign matter | M39: — | N39: {=IFERROR(INDEX('CoQ Register'!$B:$B,MATCH("P060022|I",'CoQ Register'!$S:$S,0)),"—")} -> CoQ-PP_26-038 | O39: iCoA-PP-2026-0002 | P39: P060022|I | Q39: registered — issued with the legacy series on 15.05.2026
A40: =IF(C40="yes",COUNT(A$1:A39)+1,"") -> 39 | B40: =IF(A40<>"","iCoA-PP_26-"&TEXT(A40,"000"),IF(C40="n/a","not needed","— at issue —")) -> iCoA-PP_26-039 | C40: yes | D40: =IF(A40="","",IF(G40="legacy",DATE(2026,5,15),IF(ISNUMBER(F40),(F40+5)+CHOOSE(WEEKDAY(F40+5,2),0,0,0,0,0,2,1),""))) -> 46157 | E40: {=IFERROR(INDEX('Batch Dates'!$F:$F,MATCH(J40,'Batch Dates'!$C:$C,0)),IFERROR(INDEX('Batch Dates'!$F:$F,MATCH(I40,'Batch Dates'!$B:$B,0)),""))} -> 46051 | F40: {=IFERROR(INDEX('Batch Dates'!$G:$G,MATCH(J40,'Batch Dates'!$C:$C,0)),IFERROR(INDEX('Batch Dates'!$G:$G,MATCH(I40,'Batch Dates'!$B:$B,0)),""))} -> 46051 | G40: legacy | H40: initial release | I40: CJ082501/2 | J40: P060032 | K40: Cap Junky | L40: Ident A + Ident B + Foreign matter | M40: — | N40: {=IFERROR(INDEX('CoQ Register'!$B:$B,MATCH("P060032|I",'CoQ Register'!$S:$S,0)),"—")} -> CoQ-PP_26-039 | O40: iCoA-PP-2026-0003 | P40: P060032|I | Q40: registered — issued with the legacy series on 15.05.2026
A41: =IF(C41="yes",COUNT(A$1:A40)+1,"") -> 40 | B41: =IF(A41<>"","iCoA-PP_26-"&TEXT(A41,"000"),IF(C41="n/a","not needed","— at issue —")) -> iCoA-PP_26-040 | C41: yes | D41: =IF(A41="","",IF(G41="legacy",DATE(2026,5,15),IF(ISNUMBER(F41),(F41+5)+CHOOSE(WEEKDAY(F41+5,2),0,0,0,0,0,2,1),""))) -> 46157 | E41: {=IFERROR(INDEX('Batch Dates'!$F:$F,MATCH(J41,'Batch Dates'!$C:$C,0)),IFERROR(INDEX('Batch Dates'!$F:$F,MATCH(I41,'Batch Dates'!$B:$B,0)),""))} -> 46051 | F41: {=IFERROR(INDEX('Batch Dates'!$G:$G,MATCH(J41,'Batch Dates'!$C:$C,0)),IFERROR(INDEX('Batch Dates'!$G:$G,MATCH(I41,'Batch Dates'!$B:$B,0)),""))} -> 46051 | G41: legacy | H41: initial release | I41: OPM092501 | J41: P060042 | K41: Orange Punch Mimosa | L41: Ident A + Ident B + Foreign matter | M41: — | N41: {=IFERROR(INDEX('CoQ Register'!$B:$B,MATCH("P060042|I",'CoQ Register'!$S:$S,0)),"—")} -> CoQ-PP_26-040 | O41: iCoA-PP-2026-0004 | P41: P060042|I | Q41: registered — issued with the legacy series on 15.05.2026
A42: =IF(C42="yes",COUNT(A$1:A41)+1,"") -> 41 | B42: =IF(A42<>"","iCoA-PP_26-"&TEXT(A42,"000"),IF(C42="n/a","not needed","— at issue —")) -> iCoA-PP_26-041 | C42: yes | D42: =IF(A42="","",IF(G42="legacy",DATE(2026,5,15),IF(ISNUMBER(F42),(F42+5)+CHOOSE(WEEKDAY(F42+5,2),0,0,0,0,0,2,1),""))) -> 46157 | E42: {=IFERROR(INDEX('Batch Dates'!$F:$F,MATCH(J42,'Batch Dates'!$C:$C,0)),IFERROR(INDEX('Batch Dates'!$F:$F,MATCH(I42,'Batch Dates'!$B:$B,0)),""))} -> 46052 | F42: {=IFERROR(INDEX('Batch Dates'!$G:$G,MATCH(J42,'Batch Dates'!$C:$C,0)),IFERROR(INDEX('Batch Dates'!$G:$G,MATCH(I42,'Batch Dates'!$B:$B,0)),""))} -> 46052 | G42: legacy | H42: initial release | I42: AB092501 | J42: P060052 | K42: Apple and Banana | L42: Ident A + Ident B + Foreign matter | M42: — | N42: {=IFERROR(INDEX('CoQ Register'!$B:$B,MATCH("P060052|I",'CoQ Register'!$S:$S,0)),"—")} -> CoQ-PP_26-041 | O42: — | P42: P060052|I | Q42: registered — issued with the legacy series on 15.05.2026
A43: =IF(C43="yes",COUNT(A$1:A42)+1,"") -> 42 | B43: =IF(A43<>"","iCoA-PP_26-"&TEXT(A43,"000"),IF(C43="n/a","not needed","— at issue —")) -> iCoA-PP_26-042 | C43: yes | D43: =IF(A43="","",IF(G43="legacy",DATE(2026,5,15),IF(ISNUMBER(F43),(F43+5)+CHOOSE(WEEKDAY(F43+5,2),0,0,0,0,0,2,1),""))) -> 46157 | E43: {=IFERROR(INDEX('Batch Dates'!$F:$F,MATCH(J43,'Batch Dates'!$C:$C,0)),IFERROR(INDEX('Batch Dates'!$F:$F,MATCH(I43,'Batch Dates'!$B:$B,0)),""))} -> 46052 | F43: {=IFERROR(INDEX('Batch Dates'!$G:$G,MATCH(J43,'Batch Dates'!$C:$C,0)),IFERROR(INDEX('Batch Dates'!$G:$G,MATCH(I43,'Batch Dates'!$B:$B,0)),""))} -> 46052 | G43: legacy | H43: initial release | I43: PM092501 | J43: P060062 | K43: Permanent Market | L43: Ident A + Ident B + Foreign matter | M43: — | N43: {=IFERROR(INDEX('CoQ Register'!$B:$B,MATCH("P060062|I",'CoQ Register'!$S:$S,0)),"—")} -> CoQ-PP_26-042 | O43: iCoA-PP-2026-0005 | P43: P060062|I | Q43: registered — issued with the legacy series on 15.05.2026
A44: =IF(C44="yes",COUNT(A$1:A43)+1,"") -> 43 | B44: =IF(A44<>"","iCoA-PP_26-"&TEXT(A44,"000"),IF(C44="n/a","not needed","— at issue —")) -> iCoA-PP_26-043 | C44: yes | D44: =IF(A44="","",IF(G44="legacy",DATE(2026,5,15),IF(ISNUMBER(F44),(F44+5)+CHOOSE(WEEKDAY(F44+5,2),0,0,0,0,0,2,1),""))) -> 46157 | E44: {=IFERROR(INDEX('Batch Dates'!$F:$F,MATCH(J44,'Batch Dates'!$C:$C,0)),IFERROR(INDEX('Batch Dates'!$F:$F,MATCH(I44,'Batch Dates'!$B:$B,0)),""))} -> 46055 | F44: {=IFERROR(INDEX('Batch Dates'!$G:$G,MATCH(J44,'Batch Dates'!$C:$C,0)),IFERROR(INDEX('Batch Dates'!$G:$G,MATCH(I44,'Batch Dates'!$B:$B,0)),""))} -> 46055 | G44: legacy | H44: initial release | I44: CJ092501 | J44: P060072 | K44: Cap Junky | L44: Ident A + Ident B + Foreign matter | M44: — | N44: {=IFERROR(INDEX('CoQ Register'!$B:$B,MATCH("P060072|I",'CoQ Register'!$S:$S,0)),"—")} -> CoQ-PP_26-043 | O44: iCoA-PP-2026-0006 | P44: P060072|I | Q44: registered — issued with the legacy series on 15.05.2026
A45: =IF(C45="yes",COUNT(A$1:A44)+1,"") -> 44 | B45: =IF(A45<>"","iCoA-PP_26-"&TEXT(A45,"000"),IF(C45="n/a","not needed","— at issue —")) -> iCoA-PP_26-044 | C45: yes | D45: =IF(A45="","",IF(G45="legacy",DATE(2026,5,15),IF(ISNUMBER(F45),(F45+5)+CHOOSE(WEEKDAY(F45+5,2),0,0,0,0,0,2,1),""))) -> 46157 | E45: {=IFERROR(INDEX('Batch Dates'!$F:$F,MATCH(J45,'Batch Dates'!$C:$C,0)),IFERROR(INDEX('Batch Dates'!$F:$F,MATCH(I45,'Batch Dates'!$B:$B,0)),""))} -> 46055 | F45: {=IFERROR(INDEX('Batch Dates'!$G:$G,MATCH(J45,'Batch Dates'!$C:$C,0)),IFERROR(INDEX('Batch Dates'!$G:$G,MATCH(I45,'Batch Dates'!$B:$B,0)),""))} -> 46055 | G45: legacy | H45: initial release | I45: SJ0925021 | J45: P060082 | L45: Ident A + Ident B + Foreign matter | M45: — | N45: {=IFERROR(INDEX('CoQ Register'!$B:$B,MATCH("P060082|I",'CoQ Register'!$S:$S,0)),"—")} -> CoQ-PP_26-044 | O45: iCoA-PP-2026-0007 | P45: P060082|I | Q45: registered — issued with the legacy series on 15.05.2026
A46: =IF(C46="yes",COUNT(A$1:A45)+1,"") -> 45 | B46: =IF(A46<>"","iCoA-PP_26-"&TEXT(A46,"000"),IF(C46="n/a","not needed","— at issue —")) -> iCoA-PP_26-045 | C46: yes | D46: =IF(A46="","",IF(G46="legacy",DATE(2026,5,15),IF(ISNUMBER(F46),(F46+5)+CHOOSE(WEEKDAY(F46+5,2),0,0,0,0,0,2,1),""))) -> 46157 | E46: {=IFERROR(INDEX('Batch Dates'!$F:$F,MATCH(J46,'Batch Dates'!$C:$C,0)),IFERROR(INDEX('Batch Dates'!$F:$F,MATCH(I46,'Batch Dates'!$B:$B,0)),""))} -> 46056 | F46: {=IFERROR(INDEX('Batch Dates'!$G:$G,MATCH(J46,'Batch Dates'!$C:$C,0)),IFERROR(INDEX('Batch Dates'!$G:$G,MATCH(I46,'Batch Dates'!$B:$B,0)),""))} -> 46062 | G46: legacy | H46: initial release | I46: GP092501 | J46: P060092 | K46: Grape Pie | L46: Ident A + Ident B + Foreign matter | M46: — | N46: {=IFERROR(INDEX('CoQ Register'!$B:$B,MATCH("P060092|I",'CoQ Register'!$S:$S,0)),"—")} -> CoQ-PP_26-045 | O46: iCoA-PP-2026-0008 | P46: P060092|I | Q46: registered — issued with the legacy series on 15.05.2026
A47: =IF(C47="yes",COUNT(A$1:A46)+1,"") -> 46 | B47: =IF(A47<>"","iCoA-PP_26-"&TEXT(A47,"000"),IF(C47="n/a","not needed","— at issue —")) -> iCoA-PP_26-046 | C47: yes | D47: =IF(A47="","",IF(G47="legacy",DATE(2026,5,15),IF(ISNUMBER(F47),(F47+5)+CHOOSE(WEEKDAY(F47+5,2),0,0,0,0,0,2,1),""))) -> 46157 | E47: {=IFERROR(INDEX('Batch Dates'!$F:$F,MATCH(J47,'Batch Dates'!$C:$C,0)),IFERROR(INDEX('Batch Dates'!$F:$F,MATCH(I47,'Batch Dates'!$B:$B,0)),""))} -> 46069 | F47: {=IFERROR(INDEX('Batch Dates'!$G:$G,MATCH(J47,'Batch Dates'!$C:$C,0)),IFERROR(INDEX('Batch Dates'!$G:$G,MATCH(I47,'Batch Dates'!$B:$B,0)),""))} -> 46069 | G47: legacy | H47: initial release | I47: WED102501 | J47: P060102 | K47: Wedding Cake | L47: Ident A + Ident B + Foreign matter | M47: — | N47: {=IFERROR(INDEX('CoQ Register'!$B:$B,MATCH("P060102|I",'CoQ Register'!$S:$S,0)),"—")} -> CoQ-PP_26-046 | O47: — | P47: P060102|I | Q47: registered — issued with the legacy series on 15.05.2026
A48: =IF(C48="yes",COUNT(A$1:A47)+1,"") -> 47 | B48: =IF(A48<>"","iCoA-PP_26-"&TEXT(A48,"000"),IF(C48="n/a","not needed","— at issue —")) -> iCoA-PP_26-047 | C48: yes | D48: =IF(A48="","",IF(G48="legacy",DATE(2026,5,15),IF(ISNUMBER(F48),(F48+5)+CHOOSE(WEEKDAY(F48+5,2),0,0,0,0,0,2,1),""))) -> 46157 | E48: {=IFERROR(INDEX('Batch Dates'!$F:$F,MATCH(J48,'Batch Dates'!$C:$C,0)),IFERROR(INDEX('Batch Dates'!$F:$F,MATCH(I48,'Batch Dates'!$B:$B,0)),""))} -> 46076 | F48: {=IFERROR(INDEX('Batch Dates'!$G:$G,MATCH(J48,'Batch Dates'!$C:$C,0)),IFERROR(INDEX('Batch Dates'!$G:$G,MATCH(I48,'Batch Dates'!$B:$B,0)),""))} -> 46076 | G48: legacy | H48: initial release | I48: GRC102501 | J48: P060142 | K48: Graps & Creme | L48: Ident A + Ident B + Foreign matter | M48: — | N48: {=IFERROR(INDEX('CoQ Register'!$B:$B,MATCH("P060142|I",'CoQ Register'!$S:$S,0)),"—")} -> CoQ-PP_26-047 | O48: — | P48: P060142|I | Q48: registered — issued with the legacy series on 15.05.2026
A49: =IF(C49="yes",COUNT(A$1:A48)+1,"") -> 48 | B49: =IF(A49<>"","iCoA-PP_26-"&TEXT(A49,"000"),IF(C49="n/a","not needed","— at issue —")) -> iCoA-PP_26-048 | C49: yes | D49: =IF(A49="","",IF(G49="legacy",DATE(2026,5,15),IF(ISNUMBER(F49),(F49+5)+CHOOSE(WEEKDAY(F49+5,2),0,0,0,0,0,2,1),""))) -> 46157 | E49: {=IFERROR(INDEX('Batch Dates'!$F:$F,MATCH(J49,'Batch Dates'!$C:$C,0)),IFERROR(INDEX('Batch Dates'!$F:$F,MATCH(I49,'Batch Dates'!$B:$B,0)),""))} -> 46086 | F49: {=IFERROR(INDEX('Batch Dates'!$G:$G,MATCH(J49,'Batch Dates'!$C:$C,0)),IFERROR(INDEX('Batch Dates'!$G:$G,MATCH(I49,'Batch Dates'!$B:$B,0)),""))} -> 46086 | G49: legacy | H49: initial release | I49: J31102501 | J49: P060152 | K49: Jokerz 31 | L49: Ident A + Ident B + Foreign matter | M49: — | N49: {=IFERROR(INDEX('CoQ Register'!$B:$B,MATCH("P060152|I",'CoQ Register'!$S:$S,0)),"—")} -> CoQ-PP_26-048 | O49: iCoA-PP-2026-0012 | P49: P060152|I | Q49: registered — issued with the legacy series on 15.05.2026
A50: =IF(C50="yes",COUNT(A$1:A49)+1,"") -> 49 | B50: =IF(A50<>"","iCoA-PP_26-"&TEXT(A50,"000"),IF(C50="n/a","not needed","— at issue —")) -> iCoA-PP_26-049 | C50: yes | D50: =IF(A50="","",IF(G50="legacy",DATE(2026,5,15),IF(ISNUMBER(F50),(F50+5)+CHOOSE(WEEKDAY(F50+5,2),0,0,0,0,0,2,1),""))) -> 46157 | E50: {=IFERROR(INDEX('Batch Dates'!$F:$F,MATCH(J50,'Batch Dates'!$C:$C,0)),IFERROR(INDEX('Batch Dates'!$F:$F,MATCH(I50,'Batch Dates'!$B:$B,0)),""))} -> 46090 | F50: {=IFERROR(INDEX('Batch Dates'!$G:$G,MATCH(J50,'Batch Dates'!$C:$C,0)),IFERROR(INDEX('Batch Dates'!$G:$G,MATCH(I50,'Batch Dates'!$B:$B,0)),""))} -> 46090 | G50: legacy | H50: initial release | I50: SJ102501 | J50: P060162 | K50: Sleepy Joe | L50: Ident A + Ident B + Foreign matter | M50: — | N50: {=IFERROR(INDEX('CoQ Register'!$B:$B,MATCH("P060162|I",'CoQ Register'!$S:$S,0)),"—")} -> CoQ-PP_26-049 | O50: — | P50: P060162|I | Q50: registered — issued with the legacy series on 15.05.2026
A51: =IF(C51="yes",COUNT(A$1:A50)+1,"") -> 50 | B51: =IF(A51<>"","iCoA-PP_26-"&TEXT(A51,"000"),IF(C51="n/a","not needed","— at issue —")) -> iCoA-PP_26-050 | C51: yes | D51: =IF(A51="","",IF(G51="legacy",DATE(2026,5,15),IF(ISNUMBER(F51),(F51+5)+CHOOSE(WEEKDAY(F51+5,2),0,0,0,0,0,2,1),""))) -> 46157 | E51: {=IFERROR(INDEX('Batch Dates'!$F:$F,MATCH(J51,'Batch Dates'!$C:$C,0)),IFERROR(INDEX('Batch Dates'!$F:$F,MATCH(I51,'Batch Dates'!$B:$B,0)),""))} -> 46093 | F51: {=IFERROR(INDEX('Batch Dates'!$G:$G,MATCH(J51,'Batch Dates'!$C:$C,0)),IFERROR(INDEX('Batch Dates'!$G:$G,MATCH(I51,'Batch Dates'!$B:$B,0)),""))} -> 46093 | G51: legacy | H51: initial release | I51: KC102501 | J51: P060172 | K51: Kush Crasher | L51: Ident A + Ident B + Foreign matter | M51: — | N51: {=IFERROR(INDEX('CoQ Register'!$B:$B,MATCH("P060172|I",'CoQ Register'!$S:$S,0)),"—")} -> CoQ-PP_26-050 | O51: iCoA-PP-2026-0013 | P51: P060172|I | Q51: registered — issued with the legacy series on 15.05.2026
A52: =IF(C52="yes",COUNT(A$1:A51)+1,"") -> 51 | B52: =IF(A52<>"","iCoA-PP_26-"&TEXT(A52,"000"),IF(C52="n/a","not needed","— at issue —")) -> iCoA-PP_26-051 | C52: yes | D52: =IF(A52="","",IF(G52="legacy",DATE(2026,5,15),IF(ISNUMBER(F52),(F52+5)+CHOOSE(WEEKDAY(F52+5,2),0,0,0,0,0,2,1),""))) -> 46157 | E52: {=IFERROR(INDEX('Batch Dates'!$F:$F,MATCH(J52,'Batch Dates'!$C:$C,0)),IFERROR(INDEX('Batch Dates'!$F:$F,MATCH(I52,'Batch Dates'!$B:$B,0)),""))} -> 46095 | F52: {=IFERROR(INDEX('Batch Dates'!$G:$G,MATCH(J52,'Batch Dates'!$C:$C,0)),IFERROR(INDEX('Batch Dates'!$G:$G,MATCH(I52,'Batch Dates'!$B:$B,0)),""))} -> 46095 | G52: legacy | H52: initial release | I52: GRC102501 | J52: P060182 | K52: Graps & Creme | L52: Ident A + Ident B + Foreign matter | M52: — | N52: {=IFERROR(INDEX('CoQ Register'!$B:$B,MATCH("P060182|I",'CoQ Register'!$S:$S,0)),"—")} -> CoQ-PP_26-051 | O52: iCoA-PP-2026-0014 | P52: P060182|I | Q52: registered — issued with the legacy series on 15.05.2026
A53: =IF(C53="yes",COUNT(A$1:A52)+1,"") -> 52 | B53: =IF(A53<>"","iCoA-PP_26-"&TEXT(A53,"000"),IF(C53="n/a","not needed","— at issue —")) -> iCoA-PP_26-052 | C53: yes | D53: =IF(A53="","",IF(G53="legacy",DATE(2026,5,15),IF(ISNUMBER(F53),(F53+5)+CHOOSE(WEEKDAY(F53+5,2),0,0,0,0,0,2,1),""))) -> 46157 | E53: {=IFERROR(INDEX('Batch Dates'!$F:$F,MATCH(J53,'Batch Dates'!$C:$C,0)),IFERROR(INDEX('Batch Dates'!$F:$F,MATCH(I53,'Batch Dates'!$B:$B,0)),""))} -> 46112 | F53: {=IFERROR(INDEX('Batch Dates'!$G:$G,MATCH(J53,'Batch Dates'!$C:$C,0)),IFERROR(INDEX('Batch Dates'!$G:$G,MATCH(I53,'Batch Dates'!$B:$B,0)),""))} -> 46112 | G53: legacy | H53: initial release | I53: SJ112501 | J53: P060192 | K53: Sleepy Joy | L53: Ident A + Ident B + Foreign matter | M53: — | N53: {=IFERROR(INDEX('CoQ Register'!$B:$B,MATCH("P060192|I",'CoQ Register'!$S:$S,0)),"—")} -> CoQ-PP_26-052 | O53: — | P53: P060192|I | Q53: registered — issued with the legacy series on 15.05.2026
A54: =IF(C54="yes",COUNT(A$1:A53)+1,"") -> 53 | B54: =IF(A54<>"","iCoA-PP_26-"&TEXT(A54,"000"),IF(C54="n/a","not needed","— at issue —")) -> iCoA-PP_26-053 | C54: yes | D54: =IF(A54="","",IF(G54="legacy",DATE(2026,5,15),IF(ISNUMBER(F54),(F54+5)+CHOOSE(WEEKDAY(F54+5,2),0,0,0,0,0,2,1),""))) -> 46157 | E54: {=IFERROR(INDEX('Batch Dates'!$F:$F,MATCH(J54,'Batch Dates'!$C:$C,0)),IFERROR(INDEX('Batch Dates'!$F:$F,MATCH(I54,'Batch Dates'!$B:$B,0)),""))} -> 46129 | F54: {=IFERROR(INDEX('Batch Dates'!$G:$G,MATCH(J54,'Batch Dates'!$C:$C,0)),IFERROR(INDEX('Batch Dates'!$G:$G,MATCH(I54,'Batch Dates'!$B:$B,0)),""))} -> 46129 | G54: legacy | H54: initial release | I54: J31112501 | J54: P060202 | K54: Jokerz 31 | L54: Ident A + Ident B + Foreign matter | M54: — | N54: {=IFERROR(INDEX('CoQ Register'!$B:$B,MATCH("P060202|I",'CoQ Register'!$S:$S,0)),"—")} -> CoQ-PP_26-053 | O54: — | P54: P060202|I | Q54: registered — issued with the legacy series on 15.05.2026
A55: =IF(C55="yes",COUNT(A$1:A54)+1,"") -> 54 | B55: =IF(A55<>"","iCoA-PP_26-"&TEXT(A55,"000"),IF(C55="n/a","not needed","— at issue —")) -> iCoA-PP_26-054 | C55: yes | D55: =IF(A55="","",IF(G55="legacy",DATE(2026,5,15),IF(ISNUMBER(F55),(F55+5)+CHOOSE(WEEKDAY(F55+5,2),0,0,0,0,0,2,1),""))) -> 46157 | E55: {=IFERROR(INDEX('Batch Dates'!$F:$F,MATCH(J55,'Batch Dates'!$C:$C,0)),IFERROR(INDEX('Batch Dates'!$F:$F,MATCH(I55,'Batch Dates'!$B:$B,0)),""))} -> 46133 | F55: {=IFERROR(INDEX('Batch Dates'!$G:$G,MATCH(J55,'Batch Dates'!$C:$C,0)),IFERROR(INDEX('Batch Dates'!$G:$G,MATCH(I55,'Batch Dates'!$B:$B,0)),""))} -> 46133 | G55: legacy | H55: initial release | I55: JD112501 | J55: P060212 | K55: Jelly Donutz | L55: Ident A + Ident B + Foreign matter | M55: — | N55: {=IFERROR(INDEX('CoQ Register'!$B:$B,MATCH("P060212|I",'CoQ Register'!$S:$S,0)),"—")} -> CoQ-PP_26-054 | O55: iCoA-PP-2026-0015 | P55: P060212|I | Q55: registered — issued with the legacy series on 15.05.2026
A56: =IF(C56="yes",COUNT(A$1:A55)+1,"") -> 55 | B56: =IF(A56<>"","iCoA-PP_26-"&TEXT(A56,"000"),IF(C56="n/a","not needed","— at issue —")) -> iCoA-PP_26-055 | C56: yes | D56: =IF(A56="","",IF(G56="legacy",DATE(2026,5,15),IF(ISNUMBER(F56),(F56+5)+CHOOSE(WEEKDAY(F56+5,2),0,0,0,0,0,2,1),""))) -> 46157 | E56: {=IFERROR(INDEX('Batch Dates'!$F:$F,MATCH(J56,'Batch Dates'!$C:$C,0)),IFERROR(INDEX('Batch Dates'!$F:$F,MATCH(I56,'Batch Dates'!$B:$B,0)),""))} -> 46136 | F56: {=IFERROR(INDEX('Batch Dates'!$G:$G,MATCH(J56,'Batch Dates'!$C:$C,0)),IFERROR(INDEX('Batch Dates'!$G:$G,MATCH(I56,'Batch Dates'!$B:$B,0)),""))} -> 46136 | G56: legacy | H56: initial release | I56: OPM112501 | J56: P060222 | K56: Orange Punch Mimosa | L56: Ident A + Ident B + Foreign matter | M56: — | N56: {=IFERROR(INDEX('CoQ Register'!$B:$B,MATCH("P060222|I",'CoQ Register'!$S:$S,0)),"—")} -> CoQ-PP_26-055 | O56: — | P56: P060222|I | Q56: registered — issued with the legacy series on 15.05.2026
A57: =IF(C57="yes",COUNT(A$1:A56)+1,"") -> 56 | B57: =IF(A57<>"","iCoA-PP_26-"&TEXT(A57,"000"),IF(C57="n/a","not needed","— at issue —")) -> iCoA-PP_26-056 | C57: yes | D57: =IF(A57="","",IF(G57="legacy",DATE(2026,5,15),IF(ISNUMBER(F57),(F57+5)+CHOOSE(WEEKDAY(F57+5,2),0,0,0,0,0,2,1),""))) -> 46157 | E57: {=IFERROR(INDEX('Batch Dates'!$F:$F,MATCH(J57,'Batch Dates'!$C:$C,0)),IFERROR(INDEX('Batch Dates'!$F:$F,MATCH(I57,'Batch Dates'!$B:$B,0)),""))} -> 46139 | F57: {=IFERROR(INDEX('Batch Dates'!$G:$G,MATCH(J57,'Batch Dates'!$C:$C,0)),IFERROR(INDEX('Batch Dates'!$G:$G,MATCH(I57,'Batch Dates'!$B:$B,0)),""))} -> 46139 | G57: legacy | H57: initial release | I57: PM112501 | J57: P060232 | K57: Permanent Market | L57: Ident A + Ident B + Foreign matter | M57: — | N57: {=IFERROR(INDEX('CoQ Register'!$B:$B,MATCH("P060232|I",'CoQ Register'!$S:$S,0)),"—")} -> CoQ-PP_26-056 | O57: iCoA-PP-2026-0016 | P57: P060232|I | Q57: registered — issued with the legacy series on 15.05.2026
A58: =IF(C58="yes",COUNT(A$1:A57)+1,"") -> 57 | B58: =IF(A58<>"","iCoA-PP_26-"&TEXT(A58,"000"),IF(C58="n/a","not needed","— at issue —")) -> iCoA-PP_26-057 | C58: yes | D58: =IF(A58="","",IF(G58="legacy",DATE(2026,5,15),IF(ISNUMBER(F58),(F58+5)+CHOOSE(WEEKDAY(F58+5,2),0,0,0,0,0,2,1),""))) -> 46157 | E58: {=IFERROR(INDEX('Batch Dates'!$F:$F,MATCH(J58,'Batch Dates'!$C:$C,0)),IFERROR(INDEX('Batch Dates'!$F:$F,MATCH(I58,'Batch Dates'!$B:$B,0)),""))} -> 46140 | F58: {=IFERROR(INDEX('Batch Dates'!$G:$G,MATCH(J58,'Batch Dates'!$C:$C,0)),IFERROR(INDEX('Batch Dates'!$G:$G,MATCH(I58,'Batch Dates'!$B:$B,0)),""))} -> 46140 | G58: legacy | H58: initial release | I58: OPM122501 | J58: P060242 | K58: Orange Punch Mimosa | L58: Ident A + Ident B + Foreign matter | M58: — | N58: {=IFERROR(INDEX('CoQ Register'!$B:$B,MATCH("P060242|I",'CoQ Register'!$S:$S,0)),"—")} -> CoQ-PP_26-057 | O58: iCoA-PP-2026-0017 | P58: P060242|I | Q58: registered — issued with the legacy series on 15.05.2026
A59: =IF(C59="yes",COUNT(A$1:A58)+1,"") -> 58 | B59: =IF(A59<>"","iCoA-PP_26-"&TEXT(A59,"000"),IF(C59="n/a","not needed","— at issue —")) -> iCoA-PP_26-058 | C59: yes | D59: =IF(A59="","",IF(G59="legacy",DATE(2026,5,15),IF(ISNUMBER(F59),(F59+5)+CHOOSE(WEEKDAY(F59+5,2),0,0,0,0,0,2,1),""))) -> 46157 | E59: {=IFERROR(INDEX('Batch Dates'!$F:$F,MATCH(J59,'Batch Dates'!$C:$C,0)),IFERROR(INDEX('Batch Dates'!$F:$F,MATCH(I59,'Batch Dates'!$B:$B,0)),""))} -> 46147 | F59: {=IFERROR(INDEX('Batch Dates'!$G:$G,MATCH(J59,'Batch Dates'!$C:$C,0)),IFERROR(INDEX('Batch Dates'!$G:$G,MATCH(I59,'Batch Dates'!$B:$B,0)),""))} -> 46147 | G59: legacy | H59: initial release | I59: GG112501 | J59: P060252 | K59: Gorilla Glue | L59: Ident A + Ident B + Foreign matter | M59: — | N59: {=IFERROR(INDEX('CoQ Register'!$B:$B,MATCH("P060252|I",'CoQ Register'!$S:$S,0)),"—")} -> CoQ-PP_26-058 | O59: — | P59: P060252|I | Q59: registered — issued with the legacy series on 15.05.2026
A60: =IF(C60="yes",COUNT(A$1:A59)+1,"") -> 59 | B60: =IF(A60<>"","iCoA-PP_26-"&TEXT(A60,"000"),IF(C60="n/a","not needed","— at issue —")) -> iCoA-PP_26-059 | C60: yes | D60: =IF(A60="","",IF(G60="legacy",DATE(2026,5,15),IF(ISNUMBER(F60),(F60+5)+CHOOSE(WEEKDAY(F60+5,2),0,0,0,0,0,2,1),""))) -> 46161 | E60: {=IFERROR(INDEX('Batch Dates'!$F:$F,MATCH(J60,'Batch Dates'!$C:$C,0)),IFERROR(INDEX('Batch Dates'!$F:$F,MATCH(I60,'Batch Dates'!$B:$B,0)),""))} -> 46156 | F60: {=IFERROR(INDEX('Batch Dates'!$G:$G,MATCH(J60,'Batch Dates'!$C:$C,0)),IFERROR(INDEX('Batch Dates'!$G:$G,MATCH(I60,'Batch Dates'!$B:$B,0)),""))} -> 46156 | G60: post-SOP | H60: initial release | I60: J31122501 | J60: P060262 | K60: Jokerz 31 | L60: Ident A + Ident B + Foreign matter | M60: — | N60: {=IFERROR(INDEX('CoQ Register'!$B:$B,MATCH("P060262|I",'CoQ Register'!$S:$S,0)),"—")} -> CoQ-PP_26-059 | O60: — | P60: P060262|I | Q60: registered — first working day 5 days after packaging
A61: =IF(C61="yes",COUNT(A$1:A60)+1,"") -> 60 | B61: =IF(A61<>"","iCoA-PP_26-"&TEXT(A61,"000"),IF(C61="n/a","not needed","— at issue —")) -> iCoA-PP_26-060 | C61: yes | D61: =IF(A61="","",IF(G61="legacy",DATE(2026,5,15),IF(ISNUMBER(F61),(F61+5)+CHOOSE(WEEKDAY(F61+5,2),0,0,0,0,0,2,1),""))) -> 46167 | E61: {=IFERROR(INDEX('Batch Dates'!$F:$F,MATCH(J61,'Batch Dates'!$C:$C,0)),IFERROR(INDEX('Batch Dates'!$F:$F,MATCH(I61,'Batch Dates'!$B:$B,0)),""))} -> 46160 | F61: {=IFERROR(INDEX('Batch Dates'!$G:$G,MATCH(J61,'Batch Dates'!$C:$C,0)),IFERROR(INDEX('Batch Dates'!$G:$G,MATCH(I61,'Batch Dates'!$B:$B,0)),""))} -> 46160 | G61: post-SOP | H61: initial release | I61: CC112501 | J61: P060272 | K61: Cash Cow | L61: Ident A + Ident B + Foreign matter | M61: — | N61: {=IFERROR(INDEX('CoQ Register'!$B:$B,MATCH("P060272|I",'CoQ Register'!$S:$S,0)),"—")} -> CoQ-PP_26-060 | O61: — | P61: P060272|I | Q61: registered — first working day 5 days after packaging
A62: =IF(C62="yes",COUNT(A$1:A61)+1,"") -> 61 | B62: =IF(A62<>"","iCoA-PP_26-"&TEXT(A62,"000"),IF(C62="n/a","not needed","— at issue —")) -> iCoA-PP_26-061 | C62: yes | D62: =IF(A62="","",IF(G62="legacy",DATE(2026,5,15),IF(ISNUMBER(F62),(F62+5)+CHOOSE(WEEKDAY(F62+5,2),0,0,0,0,0,2,1),""))) -> 46167 | E62: {=IFERROR(INDEX('Batch Dates'!$F:$F,MATCH(J62,'Batch Dates'!$C:$C,0)),IFERROR(INDEX('Batch Dates'!$F:$F,MATCH(I62,'Batch Dates'!$B:$B,0)),""))} -> 46160 | F62: {=IFERROR(INDEX('Batch Dates'!$G:$G,MATCH(J62,'Batch Dates'!$C:$C,0)),IFERROR(INDEX('Batch Dates'!$G:$G,MATCH(I62,'Batch Dates'!$B:$B,0)),""))} -> 46160 | G62: post-SOP | H62: initial release | I62: SCR112501 | J62: P060282 | K62: Scrambler | L62: Ident A + Ident B + Foreign matter | M62: — | N62: {=IFERROR(INDEX('CoQ Register'!$B:$B,MATCH("P060282|I",'CoQ Register'!$S:$S,0)),"—")} -> CoQ-PP_26-061 | O62: iCoA-PP-2026-0018 | P62: P060282|I | Q62: registered — first working day 5 days after packaging
A63: =IF(C63="yes",COUNT(A$1:A62)+1,"") -> 62 | B63: =IF(A63<>"","iCoA-PP_26-"&TEXT(A63,"000"),IF(C63="n/a","not needed","— at issue —")) -> iCoA-PP_26-062 | C63: yes | D63: =IF(A63="","",IF(G63="legacy",DATE(2026,5,15),IF(ISNUMBER(F63),(F63+5)+CHOOSE(WEEKDAY(F63+5,2),0,0,0,0,0,2,1),""))) -> 46167 | E63: {=IFERROR(INDEX('Batch Dates'!$F:$F,MATCH(J63,'Batch Dates'!$C:$C,0)),IFERROR(INDEX('Batch Dates'!$F:$F,MATCH(I63,'Batch Dates'!$B:$B,0)),""))} -> 46161 | F63: {=IFERROR(INDEX('Batch Dates'!$G:$G,MATCH(J63,'Batch Dates'!$C:$C,0)),IFERROR(INDEX('Batch Dates'!$G:$G,MATCH(I63,'Batch Dates'!$B:$B,0)),""))} -> 46161 | G63: post-SOP | H63: initial release | I63: FB112501 | J63: P060292 | K63: Fat Bastard | L63: Ident A + Ident B + Foreign matter | M63: — | N63: {=IFERROR(INDEX('CoQ Register'!$B:$B,MATCH("P060292|I",'CoQ Register'!$S:$S,0)),"—")} -> CoQ-PP_26-062 | O63: — | P63: P060292|I | Q63: registered — first working day 5 days after packaging
A64: =IF(C64="yes",COUNT(A$1:A63)+1,"") -> 63 | B64: =IF(A64<>"","iCoA-PP_26-"&TEXT(A64,"000"),IF(C64="n/a","not needed","— at issue —")) -> iCoA-PP_26-063 | C64: yes | D64: =IF(A64="","",IF(G64="legacy",DATE(2026,5,15),IF(ISNUMBER(F64),(F64+5)+CHOOSE(WEEKDAY(F64+5,2),0,0,0,0,0,2,1),""))) -> 46167 | E64: {=IFERROR(INDEX('Batch Dates'!$F:$F,MATCH(J64,'Batch Dates'!$C:$C,0)),IFERROR(INDEX('Batch Dates'!$F:$F,MATCH(I64,'Batch Dates'!$B:$B,0)),""))} -> 46162 | F64: {=IFERROR(INDEX('Batch Dates'!$G:$G,MATCH(J64,'Batch Dates'!$C:$C,0)),IFERROR(INDEX('Batch Dates'!$G:$G,MATCH(I64,'Batch Dates'!$B:$B,0)),""))} -> 46162 | G64: post-SOP | H64: initial release | I64: GG012601＊ | J64: P060302 | K64: Gorilla Glue | L64: Ident A + Ident B + Foreign matter | M64: — | N64: {=IFERROR(INDEX('CoQ Register'!$B:$B,MATCH("P060302|I",'CoQ Register'!$S:$S,0)),"—")} -> CoQ-PP_26-063 | O64: — | P64: P060302|I | Q64: registered — first working day 5 days after packaging
A65: =IF(C65="yes",COUNT(A$1:A64)+1,"") -> 64 | B65: =IF(A65<>"","iCoA-PP_26-"&TEXT(A65,"000"),IF(C65="n/a","not needed","— at issue —")) -> iCoA-PP_26-064 | C65: yes | D65: =IF(A65="","",IF(G65="legacy",DATE(2026,5,15),IF(ISNUMBER(F65),(F65+5)+CHOOSE(WEEKDAY(F65+5,2),0,0,0,0,0,2,1),""))) -> 46168 | E65: {=IFERROR(INDEX('Batch Dates'!$F:$F,MATCH(J65,'Batch Dates'!$C:$C,0)),IFERROR(INDEX('Batch Dates'!$F:$F,MATCH(I65,'Batch Dates'!$B:$B,0)),""))} -> 46163 | F65: {=IFERROR(INDEX('Batch Dates'!$G:$G,MATCH(J65,'Batch Dates'!$C:$C,0)),IFERROR(INDEX('Batch Dates'!$G:$G,MATCH(I65,'Batch Dates'!$B:$B,0)),""))} -> 46163 | G65: post-SOP | H65: initial release | I65: JD012601＊ | J65: P060312 | K65: Jelly Donutz | L65: Ident A + Ident B + Foreign matter | M65: — | N65: {=IFERROR(INDEX('CoQ Register'!$B:$B,MATCH("P060312|I",'CoQ Register'!$S:$S,0)),"—")} -> CoQ-PP_26-064 | O65: — | P65: P060312|I | Q65: registered — first working day 5 days after packaging
A66: =IF(C66="yes",COUNT(A$1:A65)+1,"") -> 65 | B66: =IF(A66<>"","iCoA-PP_26-"&TEXT(A66,"000"),IF(C66="n/a","not needed","— at issue —")) -> iCoA-PP_26-065 | C66: yes | D66: =IF(A66="","",IF(G66="legacy",DATE(2026,5,15),IF(ISNUMBER(F66),(F66+5)+CHOOSE(WEEKDAY(F66+5,2),0,0,0,0,0,2,1),""))) -> 46169 | E66: {=IFERROR(INDEX('Batch Dates'!$F:$F,MATCH(J66,'Batch Dates'!$C:$C,0)),IFERROR(INDEX('Batch Dates'!$F:$F,MATCH(I66,'Batch Dates'!$B:$B,0)),""))} -> 46164 | F66: {=IFERROR(INDEX('Batch Dates'!$G:$G,MATCH(J66,'Batch Dates'!$C:$C,0)),IFERROR(INDEX('Batch Dates'!$G:$G,MATCH(I66,'Batch Dates'!$B:$B,0)),""))} -> 46164 | G66: post-SOP | H66: initial release | I66: CC012601/1 | J66: P060332 | L66: Ident A + Ident B + Foreign matter | M66: — | N66: {=IFERROR(INDEX('CoQ Register'!$B:$B,MATCH("P060332|I",'CoQ Register'!$S:$S,0)),"—")} -> CoQ-PP_26-065 | O66: — | P66: P060332|I | Q66: registered — first working day 5 days after packaging
A67: =IF(C67="yes",COUNT(A$1:A66)+1,"") -> 66 | B67: =IF(A67<>"","iCoA-PP_26-"&TEXT(A67,"000"),IF(C67="n/a","not needed","— at issue —")) -> iCoA-PP_26-066 | C67: yes | D67: =IF(A67="","",IF(G67="legacy",DATE(2026,5,15),IF(ISNUMBER(F67),(F67+5)+CHOOSE(WEEKDAY(F67+5,2),0,0,0,0,0,2,1),""))) -> 46169 | E67: {=IFERROR(INDEX('Batch Dates'!$F:$F,MATCH(J67,'Batch Dates'!$C:$C,0)),IFERROR(INDEX('Batch Dates'!$F:$F,MATCH(I67,'Batch Dates'!$B:$B,0)),""))} -> 46164 | F67: {=IFERROR(INDEX('Batch Dates'!$G:$G,MATCH(J67,'Batch Dates'!$C:$C,0)),IFERROR(INDEX('Batch Dates'!$G:$G,MATCH(I67,'Batch Dates'!$B:$B,0)),""))} -> 46164 | G67: post-SOP | H67: initial release | I67: FB012601_1 | J67: P060322 | K67: Fat Bastard | L67: Ident A + Ident B + Foreign matter | M67: — | N67: {=IFERROR(INDEX('CoQ Register'!$B:$B,MATCH("P060322|I",'CoQ Register'!$S:$S,0)),"—")} -> CoQ-PP_26-066 | O67: iCoA-PP-2026-0019 | P67: P060322|I | Q67: registered — first working day 5 days after packaging
A68: =IF(C68="yes",COUNT(A$1:A67)+1,"") -> 67 | B68: =IF(A68<>"","iCoA-PP_26-"&TEXT(A68,"000"),IF(C68="n/a","not needed","— at issue —")) -> iCoA-PP_26-067 | C68: yes | D68: =IF(A68="","",IF(G68="legacy",DATE(2026,5,15),IF(ISNUMBER(F68),(F68+5)+CHOOSE(WEEKDAY(F68+5,2),0,0,0,0,0,2,1),""))) -> 46170 | E68: {=IFERROR(INDEX('Batch Dates'!$F:$F,MATCH(J68,'Batch Dates'!$C:$C,0)),IFERROR(INDEX('Batch Dates'!$F:$F,MATCH(I68,'Batch Dates'!$B:$B,0)),""))} -> 46165 | F68: {=IFERROR(INDEX('Batch Dates'!$G:$G,MATCH(J68,'Batch Dates'!$C:$C,0)),IFERROR(INDEX('Batch Dates'!$G:$G,MATCH(I68,'Batch Dates'!$B:$B,0)),""))} -> 46165 | G68: post-SOP | H68: initial release | I68: FB012602* | J68: P060352 | K68: Fat Bastard | L68: Ident A + Ident B + Foreign matter | M68: — | N68: {=IFERROR(INDEX('CoQ Register'!$B:$B,MATCH("P060352|I",'CoQ Register'!$S:$S,0)),"—")} -> CoQ-PP_26-067 | O68: iCoA-PP-2026-0021 | P68: P060352|I | Q68: registered — first working day 5 days after packaging
A69: =IF(C69="yes",COUNT(A$1:A68)+1,"") -> 68 | B69: =IF(A69<>"","iCoA-PP_26-"&TEXT(A69,"000"),IF(C69="n/a","not needed","— at issue —")) -> iCoA-PP_26-068 | C69: yes | D69: =IF(A69="","",IF(G69="legacy",DATE(2026,5,15),IF(ISNUMBER(F69),(F69+5)+CHOOSE(WEEKDAY(F69+5,2),0,0,0,0,0,2,1),""))) -> 46174 | E69: {=IFERROR(INDEX('Batch Dates'!$F:$F,MATCH(J69,'Batch Dates'!$C:$C,0)),IFERROR(INDEX('Batch Dates'!$F:$F,MATCH(I69,'Batch Dates'!$B:$B,0)),""))} -> 46167 | F69: {=IFERROR(INDEX('Batch Dates'!$G:$G,MATCH(J69,'Batch Dates'!$C:$C,0)),IFERROR(INDEX('Batch Dates'!$G:$G,MATCH(I69,'Batch Dates'!$B:$B,0)),""))} -> 46167 | G69: post-SOP | H69: initial release | I69: SCR012601* | J69: P060342 | K69: Scrambler | L69: Ident A + Ident B + Foreign matter | M69: — | N69: {=IFERROR(INDEX('CoQ Register'!$B:$B,MATCH("P060342|I",'CoQ Register'!$S:$S,0)),"—")} -> CoQ-PP_26-068 | O69: — | P69: P060342|I | Q69: registered — first working day 5 days after packaging
A70: =IF(C70="yes",COUNT(A$1:A69)+1,"") -> 69 | B70: =IF(A70<>"","iCoA-PP_26-"&TEXT(A70,"000"),IF(C70="n/a","not needed","— at issue —")) -> iCoA-PP_26-069 | C70: yes | D70: =IF(A70="","",IF(G70="legacy",DATE(2026,5,15),IF(ISNUMBER(F70),(F70+5)+CHOOSE(WEEKDAY(F70+5,2),0,0,0,0,0,2,1),""))) -> 46174 | E70: {=IFERROR(INDEX('Batch Dates'!$F:$F,MATCH(J70,'Batch Dates'!$C:$C,0)),IFERROR(INDEX('Batch Dates'!$F:$F,MATCH(I70,'Batch Dates'!$B:$B,0)),""))} -> 46167 | F70: {=IFERROR(INDEX('Batch Dates'!$G:$G,MATCH(J70,'Batch Dates'!$C:$C,0)),IFERROR(INDEX('Batch Dates'!$G:$G,MATCH(I70,'Batch Dates'!$B:$B,0)),""))} -> 46167 | G70: post-SOP | H70: initial release | I70: SCR012603 | J70: P060382 | K70: Scrambler | L70: Ident A + Ident B + Foreign matter | M70: — | N70: {=IFERROR(INDEX('CoQ Register'!$B:$B,MATCH("P060382|I",'CoQ Register'!$S:$S,0)),"—")} -> CoQ-PP_26-069 | O70: iCoA-PP-2026-0026 | P70: P060382|I | Q70: registered — first working day 5 days after packaging
A71: =IF(C71="yes",COUNT(A$1:A70)+1,"") | B71: =IF(A71<>"","iCoA-PP_26-"&TEXT(A71,"000"),IF(C71="n/a","not needed","— at issue —")) -> not needed | C71: n/a | D71: =IF(A71="","",IF(G71="legacy",DATE(2026,5,15),IF(ISNUMBER(F71),(F71+5)+CHOOSE(WEEKDAY(F71+5,2),0,0,0,0,0,2,1),""))) | E71: {=IFERROR(INDEX('Batch Dates'!$F:$F,MATCH(J71,'Batch Dates'!$C:$C,0)),IFERROR(INDEX('Batch Dates'!$F:$F,MATCH(I71,'Batch Dates'!$B:$B,0)),""))} -> 46165 | F71: {=IFERROR(INDEX('Batch Dates'!$G:$G,MATCH(J71,'Batch Dates'!$C:$C,0)),IFERROR(INDEX('Batch Dates'!$G:$G,MATCH(I71,'Batch Dates'!$B:$B,0)),""))} -> 46165 | G71: post-SOP | H71: initial release | I71: FB012603V | J71: P060392 | K71: Fat Bastard | L71: — all three on the CNP certificate — | M71: A: ППК26110 / B: ППК26110 / FM: ППК26110 | N71: {=IFERROR(INDEX('CoQ Register'!$B:$B,MATCH("P060392|I",'CoQ Register'!$S:$S,0)),"—")} -> CoQ-PP_26-070 | O71: — | P71: P060392|I | Q71: not needed — CNP covers A, B and foreign matter
A72: =IF(C72="yes",COUNT(A$1:A71)+1,"") | B72: =IF(A72<>"","iCoA-PP_26-"&TEXT(A72,"000"),IF(C72="n/a","not needed","— at issue —")) -> not needed | C72: n/a | D72: =IF(A72="","",IF(G72="legacy",DATE(2026,5,15),IF(ISNUMBER(F72),(F72+5)+CHOOSE(WEEKDAY(F72+5,2),0,0,0,0,0,2,1),""))) | E72: {=IFERROR(INDEX('Batch Dates'!$F:$F,MATCH(J72,'Batch Dates'!$C:$C,0)),IFERROR(INDEX('Batch Dates'!$F:$F,MATCH(I72,'Batch Dates'!$B:$B,0)),""))} -> 46165 | F72: {=IFERROR(INDEX('Batch Dates'!$G:$G,MATCH(J72,'Batch Dates'!$C:$C,0)),IFERROR(INDEX('Batch Dates'!$G:$G,MATCH(I72,'Batch Dates'!$B:$B,0)),""))} -> 46165 | G72: post-SOP | H72: initial release | I72: JD012603 | J72: P060362 | L72: — all three on the CNP certificate — | M72: A: ППК26111 / B: ППК26111 / FM: ППК26111 | N72: {=IFERROR(INDEX('CoQ Register'!$B:$B,MATCH("P060362|I",'CoQ Register'!$S:$S,0)),"—")} -> CoQ-PP_26-071 | O72: iCoA-PP-2026-0020 | P72: P060362|I | Q72: not needed — CNP covers A, B and foreign matter
A73: =IF(C73="yes",COUNT(A$1:A72)+1,"") | B73: =IF(A73<>"","iCoA-PP_26-"&TEXT(A73,"000"),IF(C73="n/a","not needed","— at issue —")) -> not needed | C73: n/a | D73: =IF(A73="","",IF(G73="legacy",DATE(2026,5,15),IF(ISNUMBER(F73),(F73+5)+CHOOSE(WEEKDAY(F73+5,2),0,0,0,0,0,2,1),""))) | E73: {=IFERROR(INDEX('Batch Dates'!$F:$F,MATCH(J73,'Batch Dates'!$C:$C,0)),IFERROR(INDEX('Batch Dates'!$F:$F,MATCH(I73,'Batch Dates'!$B:$B,0)),""))} -> 46165 | F73: {=IFERROR(INDEX('Batch Dates'!$G:$G,MATCH(J73,'Batch Dates'!$C:$C,0)),IFERROR(INDEX('Batch Dates'!$G:$G,MATCH(I73,'Batch Dates'!$B:$B,0)),""))} -> 46165 | G73: post-SOP | H73: initial release | I73: JD012603 | J73: P060422 | L73: — all three on the CNP certificate — | M73: A: ППК26111 / B: ППК26111 / FM: ППК26111 | N73: {=IFERROR(INDEX('CoQ Register'!$B:$B,MATCH("P060422|I",'CoQ Register'!$S:$S,0)),"—")} -> CoQ-PP_26-072 | O73: iCoA-PP-2026-0022 | P73: P060422|I | Q73: not needed — CNP covers A, B and foreign matter
A74: =IF(C74="yes",COUNT(A$1:A73)+1,"") | B74: =IF(A74<>"","iCoA-PP_26-"&TEXT(A74,"000"),IF(C74="n/a","not needed","— at issue —")) -> not needed | C74: n/a | D74: =IF(A74="","",IF(G74="legacy",DATE(2026,5,15),IF(ISNUMBER(F74),(F74+5)+CHOOSE(WEEKDAY(F74+5,2),0,0,0,0,0,2,1),""))) | E74: {=IFERROR(INDEX('Batch Dates'!$F:$F,MATCH(J74,'Batch Dates'!$C:$C,0)),IFERROR(INDEX('Batch Dates'!$F:$F,MATCH(I74,'Batch Dates'!$B:$B,0)),""))} -> 46166 | F74: {=IFERROR(INDEX('Batch Dates'!$G:$G,MATCH(J74,'Batch Dates'!$C:$C,0)),IFERROR(INDEX('Batch Dates'!$G:$G,MATCH(I74,'Batch Dates'!$B:$B,0)),""))} -> 46166 | G74: post-SOP | H74: initial release | I74: GG012603 | J74: P060402 | K74: GorillaGlue | L74: — all three on the CNP certificate — | M74: A: ППК26114 / B: ППК26114 / FM: ППК26114 | N74: {=IFERROR(INDEX('CoQ Register'!$B:$B,MATCH("P060402|I",'CoQ Register'!$S:$S,0)),"—")} -> CoQ-PP_26-073 | O74: iCoA-PP-2026-0023 | P74: P060402|I | Q74: not needed — CNP covers A, B and foreign matter
A75: =IF(C75="yes",COUNT(A$1:A74)+1,"") | B75: =IF(A75<>"","iCoA-PP_26-"&TEXT(A75,"000"),IF(C75="n/a","not needed","— at issue —")) -> not needed | C75: n/a | D75: =IF(A75="","",IF(G75="legacy",DATE(2026,5,15),IF(ISNUMBER(F75),(F75+5)+CHOOSE(WEEKDAY(F75+5,2),0,0,0,0,0,2,1),""))) | E75: {=IFERROR(INDEX('Batch Dates'!$F:$F,MATCH(J75,'Batch Dates'!$C:$C,0)),IFERROR(INDEX('Batch Dates'!$F:$F,MATCH(I75,'Batch Dates'!$B:$B,0)),""))} -> 46166 | F75: {=IFERROR(INDEX('Batch Dates'!$G:$G,MATCH(J75,'Batch Dates'!$C:$C,0)),IFERROR(INDEX('Batch Dates'!$G:$G,MATCH(I75,'Batch Dates'!$B:$B,0)),""))} -> 46166 | G75: post-SOP | H75: initial release | I75: JD012603 | J75: P060412 | L75: — all three on the CNP certificate — | M75: A: ППК26111 / B: ППК26111 / FM: ППК26111 | N75: {=IFERROR(INDEX('CoQ Register'!$B:$B,MATCH("P060412|I",'CoQ Register'!$S:$S,0)),"—")} -> CoQ-PP_26-074 | O75: iCoA-PP-2026-0025 | P75: P060412|I | Q75: not needed — CNP covers A, B and foreign matter
A76: =IF(C76="yes",COUNT(A$1:A75)+1,"") | B76: =IF(A76<>"","iCoA-PP_26-"&TEXT(A76,"000"),IF(C76="n/a","not needed","— at issue —")) -> not needed | C76: n/a | D76: =IF(A76="","",IF(G76="legacy",DATE(2026,5,15),IF(ISNUMBER(F76),(F76+5)+CHOOSE(WEEKDAY(F76+5,2),0,0,0,0,0,2,1),""))) | E76: {=IFERROR(INDEX('Batch Dates'!$F:$F,MATCH(J76,'Batch Dates'!$C:$C,0)),IFERROR(INDEX('Batch Dates'!$F:$F,MATCH(I76,'Batch Dates'!$B:$B,0)),""))} -> 46188 | F76: {=IFERROR(INDEX('Batch Dates'!$G:$G,MATCH(J76,'Batch Dates'!$C:$C,0)),IFERROR(INDEX('Batch Dates'!$G:$G,MATCH(I76,'Batch Dates'!$B:$B,0)),""))} -> 46188 | G76: post-SOP | H76: initial release | I76: FB012603 | J76: P060432 | K76: Fat Bastard | L76: — all three on the CNP certificate — | M76: A: ППК26112 / B: ППК26112 / FM: ППК26112 | N76: {=IFERROR(INDEX('CoQ Register'!$B:$B,MATCH("P060432|I",'CoQ Register'!$S:$S,0)),"—")} -> CoQ-PP_26-075 | O76: — | P76: P060432|I | Q76: not needed — CNP covers A, B and foreign matter
A77: =IF(C77="yes",COUNT(A$1:A76)+1,"") | B77: =IF(A77<>"","iCoA-PP_26-"&TEXT(A77,"000"),IF(C77="n/a","not needed","— at issue —")) -> not needed | C77: n/a | D77: =IF(A77="","",IF(G77="legacy",DATE(2026,5,15),IF(ISNUMBER(F77),(F77+5)+CHOOSE(WEEKDAY(F77+5,2),0,0,0,0,0,2,1),""))) | E77: {=IFERROR(INDEX('Batch Dates'!$F:$F,MATCH(J77,'Batch Dates'!$C:$C,0)),IFERROR(INDEX('Batch Dates'!$F:$F,MATCH(I77,'Batch Dates'!$B:$B,0)),""))} -> 46191 | F77: {=IFERROR(INDEX('Batch Dates'!$G:$G,MATCH(J77,'Batch Dates'!$C:$C,0)),IFERROR(INDEX('Batch Dates'!$G:$G,MATCH(I77,'Batch Dates'!$B:$B,0)),""))} -> 46191 | G77: post-SOP | H77: initial release | I77: SCR022601 | J77: P060442 | K77: Scrambler | L77: — all three on the CNP certificate — | M77: A: ППК26116 / B: ППК26116 / FM: ППК26116 | N77: {=IFERROR(INDEX('CoQ Register'!$B:$B,MATCH("P060442|I",'CoQ Register'!$S:$S,0)),"—")} -> CoQ-PP_26-076 | O77: — | P77: P060442|I | Q77: not needed — CNP covers A, B and foreign matter
A78: =IF(C78="yes",COUNT(A$1:A77)+1,"") | B78: =IF(A78<>"","iCoA-PP_26-"&TEXT(A78,"000"),IF(C78="n/a","not needed","— at issue —")) -> not needed | C78: n/a | D78: =IF(A78="","",IF(G78="legacy",DATE(2026,5,15),IF(ISNUMBER(F78),(F78+5)+CHOOSE(WEEKDAY(F78+5,2),0,0,0,0,0,2,1),""))) | E78: {=IFERROR(INDEX('Batch Dates'!$F:$F,MATCH(J78,'Batch Dates'!$C:$C,0)),IFERROR(INDEX('Batch Dates'!$F:$F,MATCH(I78,'Batch Dates'!$B:$B,0)),""))} -> 46202 | F78: {=IFERROR(INDEX('Batch Dates'!$G:$G,MATCH(J78,'Batch Dates'!$C:$C,0)),IFERROR(INDEX('Batch Dates'!$G:$G,MATCH(I78,'Batch Dates'!$B:$B,0)),""))} -> 46202 | G78: post-SOP | H78: initial release | I78: FB032601 | J78: P060452 | K78: FatBastard | L78: — all three on the CNP certificate — | M78: A: ППК26127 / B: ППК26127 / FM: ППК26127 | N78: {=IFERROR(INDEX('CoQ Register'!$B:$B,MATCH("P060452|I",'CoQ Register'!$S:$S,0)),"—")} -> CoQ-PP_26-077 | O78: — | P78: P060452|I | Q78: not needed — CNP covers A, B and foreign matter
A79: =IF(C79="yes",COUNT(A$1:A78)+1,"") | B79: =IF(A79<>"","iCoA-PP_26-"&TEXT(A79,"000"),IF(C79="n/a","not needed","— at issue —")) -> not needed | C79: n/a | D79: =IF(A79="","",IF(G79="legacy",DATE(2026,5,15),IF(ISNUMBER(F79),(F79+5)+CHOOSE(WEEKDAY(F79+5,2),0,0,0,0,0,2,1),""))) | E79: {=IFERROR(INDEX('Batch Dates'!$F:$F,MATCH(J79,'Batch Dates'!$C:$C,0)),IFERROR(INDEX('Batch Dates'!$F:$F,MATCH(I79,'Batch Dates'!$B:$B,0)),""))} -> 46219 | F79: {=IFERROR(INDEX('Batch Dates'!$G:$G,MATCH(J79,'Batch Dates'!$C:$C,0)),IFERROR(INDEX('Batch Dates'!$G:$G,MATCH(I79,'Batch Dates'!$B:$B,0)),""))} -> 46219 | G79: post-SOP | H79: initial release | I79: GG032601 | J79: P060462 | K79: GorillaGlue | L79: — all three on the CNP certificate — | M79: A: ППК26128 / B: ППК26128 / FM: ППК26128 | N79: {=IFERROR(INDEX('CoQ Register'!$B:$B,MATCH("P060462|I",'CoQ Register'!$S:$S,0)),"—")} -> CoQ-PP_26-078 | O79: — | P79: P060462|I | Q79: not needed — CNP covers A, B and foreign matter
A80: =IF(C80="yes",COUNT(A$1:A79)+1,"") | B80: =IF(A80<>"","iCoA-PP_26-"&TEXT(A80,"000"),IF(C80="n/a","not needed","— at issue —")) -> not needed | C80: n/a | D80: =IF(A80="","",IF(G80="legacy",DATE(2026,5,15),IF(ISNUMBER(F80),(F80+5)+CHOOSE(WEEKDAY(F80+5,2),0,0,0,0,0,2,1),""))) | E80: {=IFERROR(INDEX('Batch Dates'!$F:$F,MATCH(J80,'Batch Dates'!$C:$C,0)),IFERROR(INDEX('Batch Dates'!$F:$F,MATCH(I80,'Batch Dates'!$B:$B,0)),""))} -> 46239 | F80: {=IFERROR(INDEX('Batch Dates'!$G:$G,MATCH(J80,'Batch Dates'!$C:$C,0)),IFERROR(INDEX('Batch Dates'!$G:$G,MATCH(I80,'Batch Dates'!$B:$B,0)),""))} -> 46239 | G80: post-SOP | H80: initial release | I80: JD022601 | J80: P060482 | K80: JellyDonutz | L80: — all three on the CNP certificate — | M80: A: ППК26115 / B: ППК26115 / FM: ППК26115 | N80: {=IFERROR(INDEX('CoQ Register'!$B:$B,MATCH("P060482|I",'CoQ Register'!$S:$S,0)),"—")} -> CoQ-PP_26-079 | O80: — | P80: P060482|I | Q80: not needed — CNP covers A, B and foreign matter
A81: =IF(C81="yes",COUNT(A$1:A80)+1,"") | B81: =IF(A81<>"","iCoA-PP_26-"&TEXT(A81,"000"),IF(C81="n/a","not needed","— at issue —")) -> not needed | C81: n/a | D81: =IF(A81="","",IF(G81="legacy",DATE(2026,5,15),IF(ISNUMBER(F81),(F81+5)+CHOOSE(WEEKDAY(F81+5,2),0,0,0,0,0,2,1),""))) | E81: {=IFERROR(INDEX('Batch Dates'!$F:$F,MATCH(J81,'Batch Dates'!$C:$C,0)),IFERROR(INDEX('Batch Dates'!$F:$F,MATCH(I81,'Batch Dates'!$B:$B,0)),""))} | F81: {=IFERROR(INDEX('Batch Dates'!$G:$G,MATCH(J81,'Batch Dates'!$C:$C,0)),IFERROR(INDEX('Batch Dates'!$G:$G,MATCH(I81,'Batch Dates'!$B:$B,0)),""))} | G81: — | H81: initial release | I81: — not recorded — | J81: P160012 | L81: — all three on the CNP certificate — | M81: A: ППК26117 / B: ППК26117 / FM: ППК26117 | N81: {=IFERROR(INDEX('CoQ Register'!$B:$B,MATCH("P160012|I",'CoQ Register'!$S:$S,0)),"—")} -> — at issue — | O81: — | P81: P160012|I | Q81: not needed — CNP covers A, B and foreign matter
A82: =IF(C82="yes",COUNT(A$1:A81)+1,"") | B82: =IF(A82<>"","iCoA-PP_26-"&TEXT(A82,"000"),IF(C82="n/a","not needed","— at issue —")) -> not needed | C82: n/a | D82: =IF(A82="","",IF(G82="legacy",DATE(2026,5,15),IF(ISNUMBER(F82),(F82+5)+CHOOSE(WEEKDAY(F82+5,2),0,0,0,0,0,2,1),""))) | E82: {=IFERROR(INDEX('Batch Dates'!$F:$F,MATCH(J82,'Batch Dates'!$C:$C,0)),IFERROR(INDEX('Batch Dates'!$F:$F,MATCH(I82,'Batch Dates'!$B:$B,0)),""))} | F82: {=IFERROR(INDEX('Batch Dates'!$G:$G,MATCH(J82,'Batch Dates'!$C:$C,0)),IFERROR(INDEX('Batch Dates'!$G:$G,MATCH(I82,'Batch Dates'!$B:$B,0)),""))} | G82: — | H82: initial release | I82: — not recorded — | J82: P160022 | L82: — all three on the CNP certificate — | M82: A: ППК26118 / B: ППК26118 / FM: ППК26118 | N82: {=IFERROR(INDEX('CoQ Register'!$B:$B,MATCH("P160022|I",'CoQ Register'!$S:$S,0)),"—")} -> — at issue — | O82: — | P82: P160022|I | Q82: not needed — CNP covers A, B and foreign matter
A83: =IF(C83="yes",COUNT(A$1:A82)+1,"") | B83: =IF(A83<>"","iCoA-PP_26-"&TEXT(A83,"000"),IF(C83="n/a","not needed","— at issue —")) -> not needed | C83: n/a | D83: =IF(A83="","",IF(G83="legacy",DATE(2026,5,15),IF(ISNUMBER(F83),(F83+5)+CHOOSE(WEEKDAY(F83+5,2),0,0,0,0,0,2,1),""))) | E83: {=IFERROR(INDEX('Batch Dates'!$F:$F,MATCH(J83,'Batch Dates'!$C:$C,0)),IFERROR(INDEX('Batch Dates'!$F:$F,MATCH(I83,'Batch Dates'!$B:$B,0)),""))} | F83: {=IFERROR(INDEX('Batch Dates'!$G:$G,MATCH(J83,'Batch Dates'!$C:$C,0)),IFERROR(INDEX('Batch Dates'!$G:$G,MATCH(I83,'Batch Dates'!$B:$B,0)),""))} | G83: — | H83: initial release | I83: — not recorded — | J83: P160032 | L83: — all three on the CNP certificate — | M83: A: ППК26119 / B: ППК26119 / FM: ППК26119 | N83: {=IFERROR(INDEX('CoQ Register'!$B:$B,MATCH("P160032|I",'CoQ Register'!$S:$S,0)),"—")} -> — at issue — | O83: — | P83: P160032|I | Q83: not needed — CNP covers A, B and foreign matter
A84: =IF(C84="yes",COUNT(A$1:A83)+1,"") | B84: =IF(A84<>"","iCoA-PP_26-"&TEXT(A84,"000"),IF(C84="n/a","not needed","— at issue —")) -> — at issue — | C84: no | D84: =IF(A84="","",IF(G84="legacy",DATE(2026,5,15),IF(ISNUMBER(F84),(F84+5)+CHOOSE(WEEKDAY(F84+5,2),0,0,0,0,0,2,1),""))) | E84: {=IFERROR(INDEX('Batch Dates'!$F:$F,MATCH(J84,'Batch Dates'!$C:$C,0)),IFERROR(INDEX('Batch Dates'!$F:$F,MATCH(I84,'Batch Dates'!$B:$B,0)),""))} | F84: {=IFERROR(INDEX('Batch Dates'!$G:$G,MATCH(J84,'Batch Dates'!$C:$C,0)),IFERROR(INDEX('Batch Dates'!$G:$G,MATCH(I84,'Batch Dates'!$B:$B,0)),""))} | G84: — | H84: initial release | I84: JD112501＊ | J84: N/A — no P batch assigned | K84: Jelly Donutz | L84: Ident A + Ident B + Foreign matter | M84: — | N84: {=IFERROR(INDEX('CoQ Register'!$B:$B,MATCH("JD112501|I",'CoQ Register'!$S:$S,0)),"—")} -> — at issue — | O84: iCoA-PP-2026-0015 | P84: JD112501|I | Q84: not yet issuable — no packaging date on the list
A85: =IF(C85="yes",COUNT(A$1:A84)+1,"") | B85: =IF(A85<>"","iCoA-PP_26-"&TEXT(A85,"000"),IF(C85="n/a","not needed","— at issue —")) -> — at issue — | C85: no | D85: =IF(A85="","",IF(G85="legacy",DATE(2026,5,15),IF(ISNUMBER(F85),(F85+5)+CHOOSE(WEEKDAY(F85+5,2),0,0,0,0,0,2,1),""))) | E85: at retest sampling | F85: {=IFERROR(INDEX('Batch Dates'!$G:$G,MATCH(J85,'Batch Dates'!$C:$C,0)),IFERROR(INDEX('Batch Dates'!$G:$G,MATCH(I85,'Batch Dates'!$B:$B,0)),""))} -> 45720 | G85: legacy | H85: retest — Tranche 1 (sampled July 2026) | I85: BSS1024 | J85: N/A — no P batch assigned | K85: Blue Sunset Sherbet | L85: Ident A + Ident B + Foreign matter | M85: — | N85: {=IFERROR(INDEX('CoQ Register'!$B:$B,MATCH("BSS1024|R",'CoQ Register'!$S:$S,0)),"—")} -> — at issue — | O85: — | P85: BSS1024|R | Q85: not yet issuable — retest assay on file; identification A, B and foreign matter to test at the retest sampling
A86: =IF(C86="yes",COUNT(A$1:A85)+1,"") | B86: =IF(A86<>"","iCoA-PP_26-"&TEXT(A86,"000"),IF(C86="n/a","not needed","— at issue —")) -> — at issue — | C86: no | D86: =IF(A86="","",IF(G86="legacy",DATE(2026,5,15),IF(ISNUMBER(F86),(F86+5)+CHOOSE(WEEKDAY(F86+5,2),0,0,0,0,0,2,1),""))) | E86: at retest sampling | F86: {=IFERROR(INDEX('Batch Dates'!$G:$G,MATCH(J86,'Batch Dates'!$C:$C,0)),IFERROR(INDEX('Batch Dates'!$G:$G,MATCH(I86,'Batch Dates'!$B:$B,0)),""))} -> 45723 | G86: legacy | H86: retest — Tranche 1 (sampled July 2026) | I86: BG1024 | J86: N/A — no P batch assigned | K86: Blue Gelato | L86: Ident A + Ident B + Foreign matter | M86: — | N86: {=IFERROR(INDEX('CoQ Register'!$B:$B,MATCH("BG1024|R",'CoQ Register'!$S:$S,0)),"—")} -> — at issue — | O86: — | P86: BG1024|R | Q86: not yet issuable — retest assay on file; identification A, B and foreign matter to test at the retest sampling
A87: =IF(C87="yes",COUNT(A$1:A86)+1,"") | B87: =IF(A87<>"","iCoA-PP_26-"&TEXT(A87,"000"),IF(C87="n/a","not needed","— at issue —")) -> — at issue — | C87: no | D87: =IF(A87="","",IF(G87="legacy",DATE(2026,5,15),IF(ISNUMBER(F87),(F87+5)+CHOOSE(WEEKDAY(F87+5,2),0,0,0,0,0,2,1),""))) | E87: at retest sampling | F87: {=IFERROR(INDEX('Batch Dates'!$G:$G,MATCH(J87,'Batch Dates'!$C:$C,0)),IFERROR(INDEX('Batch Dates'!$G:$G,MATCH(I87,'Batch Dates'!$B:$B,0)),""))} -> 45758 | G87: legacy | H87: retest — Tranche 1 (sampled July 2026) | I87: HPA1024 | J87: N/A — no P batch assigned | K87: HighProAmnesia | L87: Ident A + Ident B + Foreign matter | M87: — | N87: {=IFERROR(INDEX('CoQ Register'!$B:$B,MATCH("HPA1024|R",'CoQ Register'!$S:$S,0)),"—")} -> — at issue — | O87: — | P87: HPA1024|R | Q87: not yet issuable — retest assay on file; identification A, B and foreign matter to test at the retest sampling
A88: =IF(C88="yes",COUNT(A$1:A87)+1,"") | B88: =IF(A88<>"","iCoA-PP_26-"&TEXT(A88,"000"),IF(C88="n/a","not needed","— at issue —")) -> — at issue — | C88: no | D88: =IF(A88="","",IF(G88="legacy",DATE(2026,5,15),IF(ISNUMBER(F88),(F88+5)+CHOOSE(WEEKDAY(F88+5,2),0,0,0,0,0,2,1),""))) | E88: at retest sampling | F88: {=IFERROR(INDEX('Batch Dates'!$G:$G,MATCH(J88,'Batch Dates'!$C:$C,0)),IFERROR(INDEX('Batch Dates'!$G:$G,MATCH(I88,'Batch Dates'!$B:$B,0)),""))} -> 45772 | G88: legacy | H88: retest — Tranche 1 (sampled July 2026) | I88: OPM1024 | J88: N/A — no P batch assigned | K88: OrangePunchMimosa | L88: Ident A + Ident B + Foreign matter | M88: — | N88: {=IFERROR(INDEX('CoQ Register'!$B:$B,MATCH("OPM1024|R",'CoQ Register'!$S:$S,0)),"—")} -> — at issue — | O88: — | P88: OPM1024|R | Q88: not yet issuable — retest assay on file; identification A, B and foreign matter to test at the retest sampling
A89: =IF(C89="yes",COUNT(A$1:A88)+1,"") | B89: =IF(A89<>"","iCoA-PP_26-"&TEXT(A89,"000"),IF(C89="n/a","not needed","— at issue —")) -> — at issue — | C89: no | D89: =IF(A89="","",IF(G89="legacy",DATE(2026,5,15),IF(ISNUMBER(F89),(F89+5)+CHOOSE(WEEKDAY(F89+5,2),0,0,0,0,0,2,1),""))) | E89: at retest sampling | F89: {=IFERROR(INDEX('Batch Dates'!$G:$G,MATCH(J89,'Batch Dates'!$C:$C,0)),IFERROR(INDEX('Batch Dates'!$G:$G,MATCH(I89,'Batch Dates'!$B:$B,0)),""))} -> 45819 | G89: legacy | H89: retest — Tranche 1 (sampled July 2026) | I89: GP0824_02 | J89: P050022 | K89: Grape Pie | L89: Ident A + Ident B + Foreign matter | M89: — | N89: {=IFERROR(INDEX('CoQ Register'!$B:$B,MATCH("P050022|R",'CoQ Register'!$S:$S,0)),"—")} -> — at issue — | O89: — | P89: P050022|R | Q89: not yet issuable — retest assay on file; identification A, B and foreign matter to test at the retest sampling
A90: =IF(C90="yes",COUNT(A$1:A89)+1,"") | B90: =IF(A90<>"","iCoA-PP_26-"&TEXT(A90,"000"),IF(C90="n/a","not needed","— at issue —")) -> — at issue — | C90: no | D90: =IF(A90="","",IF(G90="legacy",DATE(2026,5,15),IF(ISNUMBER(F90),(F90+5)+CHOOSE(WEEKDAY(F90+5,2),0,0,0,0,0,2,1),""))) | E90: at retest sampling | F90: {=IFERROR(INDEX('Batch Dates'!$G:$G,MATCH(J90,'Batch Dates'!$C:$C,0)),IFERROR(INDEX('Batch Dates'!$G:$G,MATCH(I90,'Batch Dates'!$B:$B,0)),""))} -> 45842 | G90: legacy | H90: retest — Tranche 1 (sampled July 2026) | I90: HPA1024_01 | J90: P050052 | K90: High Pro Amnesia | L90: Ident A + Ident B + Foreign matter | M90: — | N90: {=IFERROR(INDEX('CoQ Register'!$B:$B,MATCH("P050052|R",'CoQ Register'!$S:$S,0)),"—")} -> — at issue — | O90: — | P90: P050052|R | Q90: not yet issuable — retest assay on file; identification A, B and foreign matter to test at the retest sampling
A91: =IF(C91="yes",COUNT(A$1:A90)+1,"") | B91: =IF(A91<>"","iCoA-PP_26-"&TEXT(A91,"000"),IF(C91="n/a","not needed","— at issue —")) -> — at issue — | C91: no | D91: =IF(A91="","",IF(G91="legacy",DATE(2026,5,15),IF(ISNUMBER(F91),(F91+5)+CHOOSE(WEEKDAY(F91+5,2),0,0,0,0,0,2,1),""))) | E91: at retest sampling | F91: {=IFERROR(INDEX('Batch Dates'!$G:$G,MATCH(J91,'Batch Dates'!$C:$C,0)),IFERROR(INDEX('Batch Dates'!$G:$G,MATCH(I91,'Batch Dates'!$B:$B,0)),""))} -> 45848 | G91: legacy | H91: retest — Tranche 1 (sampled July 2026) | I91: OPM1024_02 | J91: P050062 | K91: Orange Punch Mimosa | L91: Ident A + Ident B + Foreign matter | M91: — | N91: {=IFERROR(INDEX('CoQ Register'!$B:$B,MATCH("P050062|R",'CoQ Register'!$S:$S,0)),"—")} -> — at issue — | O91: — | P91: P050062|R | Q91: not yet issuable — retest assay on file; identification A, B and foreign matter to test at the retest sampling
A92: =IF(C92="yes",COUNT(A$1:A91)+1,"") | B92: =IF(A92<>"","iCoA-PP_26-"&TEXT(A92,"000"),IF(C92="n/a","not needed","— at issue —")) -> — at issue — | C92: no | D92: =IF(A92="","",IF(G92="legacy",DATE(2026,5,15),IF(ISNUMBER(F92),(F92+5)+CHOOSE(WEEKDAY(F92+5,2),0,0,0,0,0,2,1),""))) | E92: at retest sampling | F92: {=IFERROR(INDEX('Batch Dates'!$G:$G,MATCH(J92,'Batch Dates'!$C:$C,0)),IFERROR(INDEX('Batch Dates'!$G:$G,MATCH(I92,'Batch Dates'!$B:$B,0)),""))} -> 45874 | G92: legacy | H92: retest — Tranche 1 (sampled July 2026) | I92: GG1024_01 | J92: P050092 | K92: Gorilla Glue | L92: Ident A + Ident B + Foreign matter | M92: — | N92: {=IFERROR(INDEX('CoQ Register'!$B:$B,MATCH("P050092|R",'CoQ Register'!$S:$S,0)),"—")} -> — at issue — | O92: — | P92: P050092|R | Q92: not yet issuable — retest assay on file; identification A, B and foreign matter to test at the retest sampling
A93: =IF(C93="yes",COUNT(A$1:A92)+1,"") | B93: =IF(A93<>"","iCoA-PP_26-"&TEXT(A93,"000"),IF(C93="n/a","not needed","— at issue —")) -> — at issue — | C93: no | D93: =IF(A93="","",IF(G93="legacy",DATE(2026,5,15),IF(ISNUMBER(F93),(F93+5)+CHOOSE(WEEKDAY(F93+5,2),0,0,0,0,0,2,1),""))) | E93: at retest sampling | F93: {=IFERROR(INDEX('Batch Dates'!$G:$G,MATCH(J93,'Batch Dates'!$C:$C,0)),IFERROR(INDEX('Batch Dates'!$G:$G,MATCH(I93,'Batch Dates'!$B:$B,0)),""))} -> 45925 | G93: legacy | H93: retest — Tranche 1 (sampled July 2026) | I93: GP052501 | J93: P050152 | K93: Grape Pie | L93: Ident A + Ident B + Foreign matter | M93: — | N93: {=IFERROR(INDEX('CoQ Register'!$B:$B,MATCH("P050152|R",'CoQ Register'!$S:$S,0)),"—")} -> — at issue — | O93: — | P93: P050152|R | Q93: not yet issuable — retest assay on file; identification A, B and foreign matter to test at the retest sampling
A94: =IF(C94="yes",COUNT(A$1:A93)+1,"") | B94: =IF(A94<>"","iCoA-PP_26-"&TEXT(A94,"000"),IF(C94="n/a","not needed","— at issue —")) -> — at issue — | C94: no | D94: =IF(A94="","",IF(G94="legacy",DATE(2026,5,15),IF(ISNUMBER(F94),(F94+5)+CHOOSE(WEEKDAY(F94+5,2),0,0,0,0,0,2,1),""))) | E94: at retest sampling | F94: {=IFERROR(INDEX('Batch Dates'!$G:$G,MATCH(J94,'Batch Dates'!$C:$C,0)),IFERROR(INDEX('Batch Dates'!$G:$G,MATCH(I94,'Batch Dates'!$B:$B,0)),""))} -> 45931 | G94: legacy | H94: retest — Tranche 1 (sampled July 2026) | I94: CJ052501/01 | J94: P050162 | K94: Cup Junky | L94: Ident A + Ident B + Foreign matter | M94: — | N94: {=IFERROR(INDEX('CoQ Register'!$B:$B,MATCH("P050162|R",'CoQ Register'!$S:$S,0)),"—")} -> — at issue — | O94: — | P94: P050162|R | Q94: not yet issuable — retest assay on file; identification A, B and foreign matter to test at the retest sampling
A95: =IF(C95="yes",COUNT(A$1:A94)+1,"") | B95: =IF(A95<>"","iCoA-PP_26-"&TEXT(A95,"000"),IF(C95="n/a","not needed","— at issue —")) -> — at issue — | C95: no | D95: =IF(A95="","",IF(G95="legacy",DATE(2026,5,15),IF(ISNUMBER(F95),(F95+5)+CHOOSE(WEEKDAY(F95+5,2),0,0,0,0,0,2,1),""))) | E95: at retest sampling | F95: {=IFERROR(INDEX('Batch Dates'!$G:$G,MATCH(J95,'Batch Dates'!$C:$C,0)),IFERROR(INDEX('Batch Dates'!$G:$G,MATCH(I95,'Batch Dates'!$B:$B,0)),""))} -> 46017 | G95: legacy | H95: retest — Tranche 1 (sampled July 2026) | I95: GP082501/2 | J95: P050322 | K95: Grape Pie | L95: Ident A + Ident B + Foreign matter | M95: — | N95: {=IFERROR(INDEX('CoQ Register'!$B:$B,MATCH("P050322|R",'CoQ Register'!$S:$S,0)),"—")} -> — at issue — | O95: — | P95: P050322|R | Q95: not yet issuable — retest assay on file; identification A, B and foreign matter to test at the retest sampling
A96: =IF(C96="yes",COUNT(A$1:A95)+1,"") | B96: =IF(A96<>"","iCoA-PP_26-"&TEXT(A96,"000"),IF(C96="n/a","not needed","— at issue —")) -> — at issue — | C96: no | D96: =IF(A96="","",IF(G96="legacy",DATE(2026,5,15),IF(ISNUMBER(F96),(F96+5)+CHOOSE(WEEKDAY(F96+5,2),0,0,0,0,0,2,1),""))) | E96: at retest sampling | F96: {=IFERROR(INDEX('Batch Dates'!$G:$G,MATCH(J96,'Batch Dates'!$C:$C,0)),IFERROR(INDEX('Batch Dates'!$G:$G,MATCH(I96,'Batch Dates'!$B:$B,0)),""))} -> 45985 | G96: legacy | H96: retest — Tranche 1 (sampled July 2026) | I96: CJ062501/2 | J96: P050212 | K96: Cap Junkie | L96: Ident A + Ident B + Foreign matter | M96: — | N96: {=IFERROR(INDEX('CoQ Register'!$B:$B,MATCH("P050212|R",'CoQ Register'!$S:$S,0)),"—")} -> — at issue — | O96: — | P96: P050212|R | Q96: not yet issuable — retest assay on file; identification A, B and foreign matter to test at the retest sampling
A97: =IF(C97="yes",COUNT(A$1:A96)+1,"") | B97: =IF(A97<>"","iCoA-PP_26-"&TEXT(A97,"000"),IF(C97="n/a","not needed","— at issue —")) -> — at issue — | C97: no | D97: =IF(A97="","",IF(G97="legacy",DATE(2026,5,15),IF(ISNUMBER(F97),(F97+5)+CHOOSE(WEEKDAY(F97+5,2),0,0,0,0,0,2,1),""))) | E97: at retest sampling | F97: {=IFERROR(INDEX('Batch Dates'!$G:$G,MATCH(J97,'Batch Dates'!$C:$C,0)),IFERROR(INDEX('Batch Dates'!$G:$G,MATCH(I97,'Batch Dates'!$B:$B,0)),""))} -> 46051 | G97: legacy | H97: retest — Tranche 1 (sampled July 2026) | I97: CJ082501/2 | J97: P060032 | K97: Cap Junky | L97: Ident A + Ident B + Foreign matter | M97: — | N97: {=IFERROR(INDEX('CoQ Register'!$B:$B,MATCH("P060032|R",'CoQ Register'!$S:$S,0)),"—")} -> — at issue — | O97: — | P97: P060032|R | Q97: not yet issuable — retest assay on file; identification A, B and foreign matter to test at the retest sampling
A98: =IF(C98="yes",COUNT(A$1:A97)+1,"") | B98: =IF(A98<>"","iCoA-PP_26-"&TEXT(A98,"000"),IF(C98="n/a","not needed","— at issue —")) -> — at issue — | C98: no | D98: =IF(A98="","",IF(G98="legacy",DATE(2026,5,15),IF(ISNUMBER(F98),(F98+5)+CHOOSE(WEEKDAY(F98+5,2),0,0,0,0,0,2,1),""))) | E98: at retest sampling | F98: {=IFERROR(INDEX('Batch Dates'!$G:$G,MATCH(J98,'Batch Dates'!$C:$C,0)),IFERROR(INDEX('Batch Dates'!$G:$G,MATCH(I98,'Batch Dates'!$B:$B,0)),""))} -> 46052 | G98: legacy | H98: retest — Tranche 1 (sampled July 2026) | I98: PM092501 | J98: P060062 | K98: Permanent Market | L98: Ident A + Ident B + Foreign matter | M98: — | N98: {=IFERROR(INDEX('CoQ Register'!$B:$B,MATCH("P060062|R",'CoQ Register'!$S:$S,0)),"—")} -> — at issue — | O98: — | P98: P060062|R | Q98: not yet issuable — retest assay on file; identification A, B and foreign matter to test at the retest sampling
A99: =IF(C99="yes",COUNT(A$1:A98)+1,"") | B99: =IF(A99<>"","iCoA-PP_26-"&TEXT(A99,"000"),IF(C99="n/a","not needed","— at issue —")) -> — at issue — | C99: no | D99: =IF(A99="","",IF(G99="legacy",DATE(2026,5,15),IF(ISNUMBER(F99),(F99+5)+CHOOSE(WEEKDAY(F99+5,2),0,0,0,0,0,2,1),""))) | E99: at retest sampling | F99: {=IFERROR(INDEX('Batch Dates'!$G:$G,MATCH(J99,'Batch Dates'!$C:$C,0)),IFERROR(INDEX('Batch Dates'!$G:$G,MATCH(I99,'Batch Dates'!$B:$B,0)),""))} -> 46086 | G99: legacy | H99: retest — Tranche 1 (sampled July 2026) | I99: J31102501 | J99: P060152 | K99: Jokerz 31 | L99: Ident A + Ident B + Foreign matter | M99: — | N99: {=IFERROR(INDEX('CoQ Register'!$B:$B,MATCH("P060152|R",'CoQ Register'!$S:$S,0)),"—")} -> — at issue — | O99: — | P99: P060152|R | Q99: not yet issuable — retest assay on file; identification A, B and foreign matter to test at the retest sampling
A100: =IF(C100="yes",COUNT(A$1:A99)+1,"") | B100: =IF(A100<>"","iCoA-PP_26-"&TEXT(A100,"000"),IF(C100="n/a","not needed","— at issue —")) -> — at issue — | C100: no | D100: =IF(A100="","",IF(G100="legacy",DATE(2026,5,15),IF(ISNUMBER(F100),(F100+5)+CHOOSE(WEEKDAY(F100+5,2),0,0,0,0,0,2,1),""))) | E100: at retest sampling | F100: {=IFERROR(INDEX('Batch Dates'!$G:$G,MATCH(J100,'Batch Dates'!$C:$C,0)),IFERROR(INDEX('Batch Dates'!$G:$G,MATCH(I100,'Batch Dates'!$B:$B,0)),""))} -> 46133 | G100: legacy | H100: retest — Tranche 1 (sampled July 2026) | I100: JD112501 | J100: P060212 | K100: Jelly Donutz | L100: Ident A + Ident B + Foreign matter | M100: — | N100: {=IFERROR(INDEX('CoQ Register'!$B:$B,MATCH("P060212|R",'CoQ Register'!$S:$S,0)),"—")} -> — at issue — | O100: — | P100: P060212|R | Q100: not yet issuable — retest assay on file; identification A, B and foreign matter to test at the retest sampling
...

Sheet iCoA Issuance
A1: Seq | B1: Series | C1: iCoA | D1: CoQ | E1: Plan references (31.08.2026) | F1: Group | G1: Basis date | H1: Test date (packaging) | I1: iCoA issue (planned) | J1: CoQ issue (planned) | K1: CU Batch | L1: P Batch | M1: Strain | N1: Harvest | O1: Packaging | P1: Packaging complete | Q1: iCoA scope | R1: #1 Ident. A | S1: #2 Ident. B | T1: #7 Foreign matter | U1: Ident C — covered by (eCoA) | V1: Retest assay #4–#6 (eCoA) | W1: Retest mycotoxins #10 (eCoA) | X1: Carried forward | Y1: Status
A2: 1 | B2: initial release | C2: {=IFERROR(INDEX('iCoA Register'!$B:$B,MATCH("CJ1024|I",'iCoA Register'!$P:$P,0)),"— at issue —")} -> iCoA-PP_26-001 | D2: {=IFERROR(INDEX('CoQ Register'!$B:$B,MATCH("CJ1024|I",'CoQ Register'!$S:$S,0)),"—")} -> CoQ-PP_26-001 | E2: (assigned on issue) | F2: legacy | G2: 27.02.2025 | H2: 03.03.2025 | I2: {=IFERROR(INDEX('iCoA Register'!$D:$D,MATCH("CJ1024|I",'iCoA Register'!$P:$P,0)),"")} -> 46157 | J2: {=IFERROR(INDEX('CoQ Register'!$D:$D,MATCH("CJ1024|I",'CoQ Register'!$S:$S,0)),"")} -> 46169 | K2: CJ1024 | L2: N/A — no P batch assigned | M2: Cap Junky | N2: 20.01.2025 | O2: 03.03.2025 (the issuance plan's basis: 27.02.2025) | P2: 03.03.2025 | Q2: Ident A + Ident B + Foreign matter | R2: Conforms | S2: Conforms | T2: Conforms | U2: ППК25052, (26.02.2025) [CNP] | Y2: registered — issued with the legacy series on 15.05.2026
A3: 2 | B3: initial release | C3: {=IFERROR(INDEX('iCoA Register'!$B:$B,MATCH("BSS1024|I",'iCoA Register'!$P:$P,0)),"— at issue —")} -> iCoA-PP_26-002 | D3: {=IFERROR(INDEX('CoQ Register'!$B:$B,MATCH("BSS1024|I",'CoQ Register'!$S:$S,0)),"—")} -> CoQ-PP_26-002 | E3: iCoA-PP-2025-0001 / CoQ-PP-2025-0001 | F3: legacy | G3: 04.03.2025 | H3: 04.03.2025 | I3: {=IFERROR(INDEX('iCoA Register'!$D:$D,MATCH("BSS1024|I",'iCoA Register'!$P:$P,0)),"")} -> 46157 | J3: {=IFERROR(INDEX('CoQ Register'!$D:$D,MATCH("BSS1024|I",'CoQ Register'!$S:$S,0)),"")} -> 46169 | K3: BSS1024 | L3: N/A — no P batch assigned | M3: Blue Sunset Sherbet | N3: 22.01.2025 | O3: 04.03.2025 | P3: 04.03.2025 | Q3: Ident A + Ident B + Foreign matter | R3: Conforms | S3: Conforms | T3: Conforms | U3: ППК25051, (26.02.2025) [CNP] | Y3: registered — issued with the legacy series on 15.05.2026
A4: 3 | B4: initial release | C4: {=IFERROR(INDEX('iCoA Register'!$B:$B,MATCH("BG1024|I",'iCoA Register'!$P:$P,0)),"— at issue —")} -> iCoA-PP_26-003 | D4: {=IFERROR(INDEX('CoQ Register'!$B:$B,MATCH("BG1024|I",'CoQ Register'!$S:$S,0)),"—")} -> CoQ-PP_26-003 | E4: iCoA-PP-2025-0002 / CoQ-PP-2025-0002 | F4: legacy | G4: 07.03.2025 | H4: 07.03.2025 | I4: {=IFERROR(INDEX('iCoA Register'!$D:$D,MATCH("BG1024|I",'iCoA Register'!$P:$P,0)),"")} -> 46157 | J4: {=IFERROR(INDEX('CoQ Register'!$D:$D,MATCH("BG1024|I",'CoQ Register'!$S:$S,0)),"")} -> 46169 | K4: BG1024 | L4: N/A — no P batch assigned | M4: Blue Gelato | N4: 21.01.2025 | O4: 07.03.2025 | P4: 07.03.2025 | Q4: Ident A + Ident B + Foreign matter | R4: Conforms | S4: Conforms | T4: Conforms | U4: ППК25050, (26.02.2025) [CNP] | Y4: registered — issued with the legacy series on 15.05.2026
A5: 4 | B5: initial release | C5: {=IFERROR(INDEX('iCoA Register'!$B:$B,MATCH("GG1024|I",'iCoA Register'!$P:$P,0)),"— at issue —")} -> iCoA-PP_26-004 | D5: {=IFERROR(INDEX('CoQ Register'!$B:$B,MATCH("GG1024|I",'CoQ Register'!$S:$S,0)),"—")} -> CoQ-PP_26-004 | E5: iCoA-PP-2025-0003 / CoQ-PP-2025-0003 | F5: legacy | G5: 11.03.2025 | H5: 11.03.2025 | I5: {=IFERROR(INDEX('iCoA Register'!$D:$D,MATCH("GG1024|I",'iCoA Register'!$P:$P,0)),"")} -> 46157 | J5: {=IFERROR(INDEX('CoQ Register'!$D:$D,MATCH("GG1024|I",'CoQ Register'!$S:$S,0)),"")} -> 46169 | K5: GG1024 | L5: N/A — no P batch assigned | M5: Gorilla Glue | N5: 20.01.2025 | O5: 11.03.2025 | P5: 11.03.2025 | Q5: Ident A + Ident B + Foreign matter | R5: Conforms | S5: Conforms | T5: Confirms | U5: — no cannabinoid certificate from the initial testing — | Y5: registered — issued with the legacy series on 15.05.2026
A6: 5 | B6: initial release | C6: {=IFERROR(INDEX('iCoA Register'!$B:$B,MATCH("HPA1024|I",'iCoA Register'!$P:$P,0)),"— at issue —")} -> iCoA-PP_26-005 | D6: {=IFERROR(INDEX('CoQ Register'!$B:$B,MATCH("HPA1024|I",'CoQ Register'!$S:$S,0)),"—")} -> CoQ-PP_26-005 | E6: iCoA-PP-2025-0004 / CoQ-PP-2025-0004 | F6: legacy | G6: 11.04.2025 | H6: 11.04.2025 | I6: {=IFERROR(INDEX('iCoA Register'!$D:$D,MATCH("HPA1024|I",'iCoA Register'!$P:$P,0)),"")} -> 46157 | J6: {=IFERROR(INDEX('CoQ Register'!$D:$D,MATCH("HPA1024|I",'CoQ Register'!$S:$S,0)),"")} -> 46169 | K6: HPA1024 | L6: N/A — no P batch assigned | M6: HighProAmnesia | N6: 22.01.2025 | O6: 11.04.2025 | P6: 11.04.2025 | Q6: Ident A + Ident B + Foreign matter | R6: Conforms | S6: Conforms | T6: Conforms | U6: — no cannabinoid certificate from the initial testing — | Y6: registered — issued with the legacy series on 15.05.2026
A7: 6 | B7: initial release | C7: {=IFERROR(INDEX('iCoA Register'!$B:$B,MATCH("OPM1024|I",'iCoA Register'!$P:$P,0)),"— at issue —")} -> iCoA-PP_26-006 | D7: {=IFERROR(INDEX('CoQ Register'!$B:$B,MATCH("OPM1024|I",'CoQ Register'!$S:$S,0)),"—")} -> CoQ-PP_26-006 | E7: iCoA-PP-2025-0005 / CoQ-PP-2025-0005 | F7: legacy | G7: 24.04.2025 | H7: 24.04.2025 | I7: {=IFERROR(INDEX('iCoA Register'!$D:$D,MATCH("OPM1024|I",'iCoA Register'!$P:$P,0)),"")} -> 46157 | J7: {=IFERROR(INDEX('CoQ Register'!$D:$D,MATCH("OPM1024|I",'CoQ Register'!$S:$S,0)),"")} -> 46169 | K7: OPM1024 | L7: N/A — no P batch assigned | M7: OrangePunchMimosa | N7: 21.01.2025 | O7: 24.04.2025 – 25.04.2025 | P7: 25.04.2025 | Q7: Ident A + Ident B + Foreign matter | R7: Conforms | S7: Conforms | T7: Conforms | U7: — no cannabinoid certificate from the initial testing — | Y7: registered — issued with the legacy series on 15.05.2026
A8: 7 | B8: initial release | C8: {=IFERROR(INDEX('iCoA Register'!$B:$B,MATCH("P050022|I",'iCoA Register'!$P:$P,0)),"— at issue —")} -> iCoA-PP_26-007 | D8: {=IFERROR(INDEX('CoQ Register'!$B:$B,MATCH("P050022|I",'CoQ Register'!$S:$S,0)),"—")} -> CoQ-PP_26-007 | E8: iCoA-PP-2025-0006 / CoQ-PP-2025-0006 | F8: legacy | G8: 03.06.2025 | H8: 03.06.2025 | I8: {=IFERROR(INDEX('iCoA Register'!$D:$D,MATCH("P050022|I",'iCoA Register'!$P:$P,0)),"")} -> 46157 | J8: {=IFERROR(INDEX('CoQ Register'!$D:$D,MATCH("P050022|I",'CoQ Register'!$S:$S,0)),"")} -> 46169 | K8: GP0824_02 | L8: P050022 | M8: Grape Pie | N8: 22.04.2025 – 23.04.2025 | O8: 03.06.2025 – 11.06.2025 | P8: 11.06.2025 | Q8: Ident A + Ident B + Foreign matter | R8: Conforms | S8: Conforms | T8: Conforms | U8: ППК25139, (22.05.2025) [CNP] | Y8: registered — issued with the legacy series on 15.05.2026
A9: 8 | B9: initial release | C9: {=IFERROR(INDEX('iCoA Register'!$B:$B,MATCH("P050012|I",'iCoA Register'!$P:$P,0)),"— at issue —")} -> iCoA-PP_26-008 | D9: {=IFERROR(INDEX('CoQ Register'!$B:$B,MATCH("P050012|I",'CoQ Register'!$S:$S,0)),"—")} -> CoQ-PP_26-008 | E9: (assigned on issue) | F9: legacy | G9: 30.05.2025 | H9: 11.06.2025 | I9: {=IFERROR(INDEX('iCoA Register'!$D:$D,MATCH("P050012|I",'iCoA Register'!$P:$P,0)),"")} -> 46157 | J9: {=IFERROR(INDEX('CoQ Register'!$D:$D,MATCH("P050012|I",'CoQ Register'!$S:$S,0)),"")} -> 46169 | K9: GG1024_02 | L9: P050012 | M9: Gorilla Glue | N9: 14.04.2025 – 15.04.2025 | O9: 11.06.2025 – 16.06.2025 (the issuance plan's basis: 30.05.2025) | P9: 16.06.2025 | Q9: Ident A + Ident B + Foreign matter | R9: Conforms | S9: Conforms | T9: Conforms | U9: ППК25140, (22.05.2025) [CNP] | Y9: registered — issued with the legacy series on 15.05.2026
A10: 9 | B10: initial release | C10: {=IFERROR(INDEX('iCoA Register'!$B:$B,MATCH("P050032|I",'iCoA Register'!$P:$P,0)),"— at issue —")} -> iCoA-PP_26-009 | D10: {=IFERROR(INDEX('CoQ Register'!$B:$B,MATCH("P050032|I",'CoQ Register'!$S:$S,0)),"—")} -> CoQ-PP_26-009 | E10: (assigned on issue) | F10: legacy | G10: 07.05.2025 | H10: 16.06.2025 | I10: {=IFERROR(INDEX('iCoA Register'!$D:$D,MATCH("P050032|I",'iCoA Register'!$P:$P,0)),"")} -> 46157 | J10: {=IFERROR(INDEX('CoQ Register'!$D:$D,MATCH("P050032|I",'CoQ Register'!$S:$S,0)),"")} -> 46169 | K10: MB0824_04 | L10: P050032 | M10: Motor Breath | N10: 02.04.2025 – 03.04.2025 | O10: 16.06.2025 – 19.06.2025 (the issuance plan's basis: 07.05.2025) | P10: 19.06.2025 | Q10: Ident A + Ident B + Foreign matter | R10: Conforms | S10: Conforms | T10: Conforms | U10: ППК25118, (06.05.2025) [CNP] | Y10: registered — issued with the legacy series on 15.05.2026
A11: 10 | B11: initial release | C11: {=IFERROR(INDEX('iCoA Register'!$B:$B,MATCH("P050042|I",'iCoA Register'!$P:$P,0)),"— at issue —")} -> iCoA-PP_26-010 | D11: {=IFERROR(INDEX('CoQ Register'!$B:$B,MATCH("P050042|I",'CoQ Register'!$S:$S,0)),"—")} -> CoQ-PP_26-010 | E11: iCoA-PP-2025-0007 / CoQ-PP-2025-0007 | F11: legacy | G11: 20.06.2025 | H11: 20.06.2025 | I11: {=IFERROR(INDEX('iCoA Register'!$D:$D,MATCH("P050042|I",'iCoA Register'!$P:$P,0)),"")} -> 46157 | J11: {=IFERROR(INDEX('CoQ Register'!$D:$D,MATCH("P050042|I",'CoQ Register'!$S:$S,0)),"")} -> 46169 | K11: OMP1024_01 | L11: P050042 | M11: Orange Punch Mimosa | N11: 26.03.2025 – 27.03.2025 | O11: 20.06.2025 | P11: 20.06.2025 | Q11: Ident A + Ident B + Foreign matter | R11: Conforms | S11: Conforms | T11: Conforms | U11: ППК25117, (06.05.2025) [CNP] | Y11: registered — issued with the legacy series on 15.05.2026
A12: 11 | B12: initial release | C12: {=IFERROR(INDEX('iCoA Register'!$B:$B,MATCH("P050052|I",'iCoA Register'!$P:$P,0)),"— at issue —")} -> iCoA-PP_26-011 | D12: {=IFERROR(INDEX('CoQ Register'!$B:$B,MATCH("P050052|I",'CoQ Register'!$S:$S,0)),"—")} -> CoQ-PP_26-011 | E12: iCoA-PP-2025-0008 / CoQ-PP-2025-0008 | F12: legacy | G12: 27.06.2025 | H12: 27.06.2025 | I12: {=IFERROR(INDEX('iCoA Register'!$D:$D,MATCH("P050052|I",'iCoA Register'!$P:$P,0)),"")} -> 46157 | J12: {=IFERROR(INDEX('CoQ Register'!$D:$D,MATCH("P050052|I",'CoQ Register'!$S:$S,0)),"")} -> 46169 | K12: HPA1024_01 | L12: P050052 | M12: High Pro Amnesia | N12: 27.05.2025 – 28.05.2025 | O12: 27.06.2025 – 04.07.2025 | P12: 04.07.2025 | Q12: Ident A + Ident B + Foreign matter | R12: Conforms | S12: Conforms | T12: Conforms | U12: ППК25155, (24.06.2025) [CNP] | Y12: registered — issued with the legacy series on 15.05.2026
A13: 12 | B13: initial release | C13: {=IFERROR(INDEX('iCoA Register'!$B:$B,MATCH("P050062|I",'iCoA Register'!$P:$P,0)),"— at issue —")} -> iCoA-PP_26-012 | D13: {=IFERROR(INDEX('CoQ Register'!$B:$B,MATCH("P050062|I",'CoQ Register'!$S:$S,0)),"—")} -> CoQ-PP_26-012 | E13: iCoA-PP-2025-0009 / CoQ-PP-2025-0009 | F13: legacy | G13: 04.07.2025 | H13: 04.07.2025 | I13: {=IFERROR(INDEX('iCoA Register'!$D:$D,MATCH("P050062|I",'iCoA Register'!$P:$P,0)),"")} -> 46157 | J13: {=IFERROR(INDEX('CoQ Register'!$D:$D,MATCH("P050062|I",'CoQ Register'!$S:$S,0)),"")} -> 46169 | K13: OPM1024_02 | L13: P050062 | M13: Orange Punch Mimosa | N13: 29.05.2025 – 30.05.2025 | O13: 04.07.2025 – 10.07.2025 | P13: 10.07.2025 | Q13: Ident A + Ident B + Foreign matter | R13: Conforms | S13: Conforms | T13: Conforms | U13: ППК25154, (24.06.2025) [CNP] | Y13: registered — issued with the legacy series on 15.05.2026
A14: 13 | B14: initial release | C14: {=IFERROR(INDEX('iCoA Register'!$B:$B,MATCH("P050072|I",'iCoA Register'!$P:$P,0)),"— at issue —")} -> iCoA-PP_26-013 | D14: {=IFERROR(INDEX('CoQ Register'!$B:$B,MATCH("P050072|I",'CoQ Register'!$S:$S,0)),"—")} -> CoQ-PP_26-013 | E14: iCoA-PP-2025-0010 / CoQ-PP-2025-0010 | F14: legacy | G14: 14.07.2025 | H14: 14.07.2025 | I14: {=IFERROR(INDEX('iCoA Register'!$D:$D,MATCH("P050072|I",'iCoA Register'!$P:$P,0)),"")} -> 46157 | J14: {=IFERROR(INDEX('CoQ Register'!$D:$D,MATCH("P050072|I",'CoQ Register'!$S:$S,0)),"")} -> 46169 | K14: GP0824_03 | L14: P050072 | M14: Grape Pie | N14: 09.06.2025 – 10.06.2025 | O14: 14.07.2025 – 17.07.2025 | P14: 17.07.2025 | Q14: Ident A + Ident B + Foreign matter | R14: Conforms | S14: Conforms | T14: Conforms | U14: ППК25175, (10.07.2025) [CNP] | Y14: registered — issued with the legacy series on 15.05.2026
A15: 14 | B15: initial release | C15: {=IFERROR(INDEX('iCoA Register'!$B:$B,MATCH("P050082|I",'iCoA Register'!$P:$P,0)),"— at issue —")} -> iCoA-PP_26-014 | D15: {=IFERROR(INDEX('CoQ Register'!$B:$B,MATCH("P050082|I",'CoQ Register'!$S:$S,0)),"—")} -> CoQ-PP_26-014 | E15: iCoA-PP-2025-0011 / CoQ-PP-2025-0011 | F15: legacy | G15: 22.07.2025 | H15: 22.07.2025 | I15: {=IFERROR(INDEX('iCoA Register'!$D:$D,MATCH("P050082|I",'iCoA Register'!$P:$P,0)),"")} -> 46157 | J15: {=IFERROR(INDEX('CoQ Register'!$D:$D,MATCH("P050082|I",'CoQ Register'!$S:$S,0)),"")} -> 46169 | K15: OPM1024_03 | L15: P050082 | M15: Orange Punch Mimosa | N15: 01.07.2025 – 02.07.2025 | O15: 22.07.2025 – 30.07.2025 | P15: 30.07.2025 | Q15: Ident A + Ident B + Foreign matter | R15: Conforms | S15: Conforms | T15: Conforms | U15: ППК25210, (28.07.2025) [CNP] | Y15: registered — issued with the legacy series on 15.05.2026
A16: 15 | B16: initial release | C16: {=IFERROR(INDEX('iCoA Register'!$B:$B,MATCH("P050092|I",'iCoA Register'!$P:$P,0)),"— at issue —")} -> iCoA-PP_26-015 | D16: {=IFERROR(INDEX('CoQ Register'!$B:$B,MATCH("P050092|I",'CoQ Register'!$S:$S,0)),"—")} -> CoQ-PP_26-015 | E16: iCoA-PP-2025-0012 / CoQ-PP-2025-0012 | F16: legacy | G16: 31.07.2025 | H16: 31.07.2025 | I16: {=IFERROR(INDEX('iCoA Register'!$D:$D,MATCH("P050092|I",'iCoA Register'!$P:$P,0)),"")} -> 46157 | J16: {=IFERROR(INDEX('CoQ Register'!$D:$D,MATCH("P050092|I",'CoQ Register'!$S:$S,0)),"")} -> 46169 | K16: GG1024_01 | L16: P050092 | M16: Gorilla Glue | N16: 17.03.2025 – 18.03.2025 | O16: 31.07.2025 – 05.08.2025 | P16: 05.08.2025 | Q16: Ident A + Ident B + Foreign matter | R16: Conforms | S16: Conforms | T16: Conforms | U16: ППК25104, (17.04.2025) [CNP] | Y16: registered — issued with the legacy series on 15.05.2026
A17: 16 | B17: initial release | C17: {=IFERROR(INDEX('iCoA Register'!$B:$B,MATCH("P050102|I",'iCoA Register'!$P:$P,0)),"— at issue —")} -> iCoA-PP_26-016 | D17: {=IFERROR(INDEX('CoQ Register'!$B:$B,MATCH("P050102|I",'CoQ Register'!$S:$S,0)),"—")} -> CoQ-PP_26-016 | E17: (assigned on issue) | F17: legacy | G17: 17.04.2025 | H17: 05.08.2025 | I17: {=IFERROR(INDEX('iCoA Register'!$D:$D,MATCH("P050102|I",'iCoA Register'!$P:$P,0)),"")} -> 46157 | J17: {=IFERROR(INDEX('CoQ Register'!$D:$D,MATCH("P050102|I",'CoQ Register'!$S:$S,0)),"")} -> 46169 | K17: GP0824_01 | L17: P050102 | M17: Grape Pie | N17: 20.03.2025 – 21.03.2025 | O17: 05.08.2025 – 07.08.2025 (the issuance plan's basis: 17.04.2025) | P17: 07.08.2025 | Q17: Ident A + Ident B + Foreign matter | R17: Conforms | S17: Conforms | T17: Conforms | U17: ППК25105, (17.04.2025) [CNP] | Y17: registered — issued with the legacy series on 15.05.2026
A18: 17 | B18: initial release | C18: {=IFERROR(INDEX('iCoA Register'!$B:$B,MATCH("P050112|I",'iCoA Register'!$P:$P,0)),"— at issue —")} -> iCoA-PP_26-017 | D18: {=IFERROR(INDEX('CoQ Register'!$B:$B,MATCH("P050112|I",'CoQ Register'!$S:$S,0)),"—")} -> CoQ-PP_26-017 | E18: iCoA-PP-2025-0013 / CoQ-PP-2025-0013 | F18: legacy | G18: 25.08.2025 | H18: 25.08.2025 | I18: {=IFERROR(INDEX('iCoA Register'!$D:$D,MATCH("P050112|I",'iCoA Register'!$P:$P,0)),"")} -> 46157 | J18: {=IFERROR(INDEX('CoQ Register'!$D:$D,MATCH("P050112|I",'CoQ Register'!$S:$S,0)),"")} -> 46169 | K18: MB0824_05 | L18: P050112 | M18: Motor Breath | N18: 08.07.2025 – 09.07.2025 | O18: 25.08.2025 – 31.08.2025 | P18: 31.08.2025 | Q18: Ident A + Ident B + Foreign matter | R18: Conforms | S18: Conforms | T18: Conforms | U18: ППК25211, (28.07.2025) [CNP] | Y18: registered — issued with the legacy series on 15.05.2026
A19: 18 | B19: initial release | C19: {=IFERROR(INDEX('iCoA Register'!$B:$B,MATCH("P050122|I",'iCoA Register'!$P:$P,0)),"— at issue —")} -> iCoA-PP_26-018 | D19: {=IFERROR(INDEX('CoQ Register'!$B:$B,MATCH("P050122|I",'CoQ Register'!$S:$S,0)),"—")} -> CoQ-PP_26-018 | E19: — | F19: legacy | G19: 01.09.2025 | H19: 01.09.2025 | I19: {=IFERROR(INDEX('iCoA Register'!$D:$D,MATCH("P050122|I",'iCoA Register'!$P:$P,0)),"")} -> 46157 | J19: {=IFERROR(INDEX('CoQ Register'!$D:$D,MATCH("P050122|I",'CoQ Register'!$S:$S,0)),"")} -> 46169 | K19: BSS1024_01/1 | L19: P050122 | M19: Blue Sunset Sherbet | N19: 04.06.2025 – 05.06.2025 | O19: 01.09.2025 – 09.09.2025 | P19: 09.09.2025 | Q19: Ident A + Ident B + Foreign matter | R19: Conforms | S19: Conforms | T19: Conforms | U19: ППК25176, (10.07.2025) [CNP] | Y19: registered — issued with the legacy series on 15.05.2026
A20: 19 | B20: initial release | C20: {=IFERROR(INDEX('iCoA Register'!$B:$B,MATCH("P050132|I",'iCoA Register'!$P:$P,0)),"— at issue —")} -> iCoA-PP_26-019 | D20: {=IFERROR(INDEX('CoQ Register'!$B:$B,MATCH("P050132|I",'CoQ Register'!$S:$S,0)),"—")} -> CoQ-PP_26-019 | E20: (assigned on issue) | F20: legacy | G20: 05.09.2025 | H20: 09.09.2025 | I20: {=IFERROR(INDEX('iCoA Register'!$D:$D,MATCH("P050132|I",'iCoA Register'!$P:$P,0)),"")} -> 46157 | J20: {=IFERROR(INDEX('CoQ Register'!$D:$D,MATCH("P050132|I",'CoQ Register'!$S:$S,0)),"")} -> 46169 | K20: OPM052501 | L20: P050132 | M20: Orange Punch Mimosa | N20: 11.08.2025 – 13.08.2025 | O20: 09.09.2025 – 15.09.2025 (the issuance plan's basis: 05.09.2025) | P20: 15.09.2025 | Q20: Ident A + Ident B + Foreign matter | R20: Conforms | S20: Conforms | T20: Conforms | U20: ППК25257, (05.09.2025) [CNP] | Y20: registered — issued with the legacy series on 15.05.2026
A21: 20 | B21: initial release | C21: {=IFERROR(INDEX('iCoA Register'!$B:$B,MATCH("P050152|I",'iCoA Register'!$P:$P,0)),"— at issue —")} -> iCoA-PP_26-020 | D21: {=IFERROR(INDEX('CoQ Register'!$B:$B,MATCH("P050152|I",'CoQ Register'!$S:$S,0)),"—")} -> CoQ-PP_26-020 | E21: iCoA-PP-2025-0014 / CoQ-PP-2025-0014 | F21: legacy | G21: 25.09.2025 | H21: 25.09.2025 | I21: {=IFERROR(INDEX('iCoA Register'!$D:$D,MATCH("P050152|I",'iCoA Register'!$P:$P,0)),"")} -> 46157 | J21: {=IFERROR(INDEX('CoQ Register'!$D:$D,MATCH("P050152|I",'CoQ Register'!$S:$S,0)),"")} -> 46169 | K21: GP052501 | L21: P050152 | M21: Grape Pie | N21: — not given — | O21: 25.09.2025 | P21: 25.09.2025 | Q21: Ident A + Ident B + Foreign matter | R21: Conforms | S21: Conforms | T21: Conforms | U21: ППК25279, (19.09.2025) [CNP] | Y21: registered — issued with the legacy series on 15.05.2026
A22: 21 | B22: initial release | C22: {=IFERROR(INDEX('iCoA Register'!$B:$B,MATCH("P050142|I",'iCoA Register'!$P:$P,0)),"— at issue —")} -> iCoA-PP_26-021 | D22: {=IFERROR(INDEX('CoQ Register'!$B:$B,MATCH("P050142|I",'CoQ Register'!$S:$S,0)),"—")} -> CoQ-PP_26-021 | E22: — | F22: legacy | G22: 30.09.2025 | H22: 30.09.2025 | I22: {=IFERROR(INDEX('iCoA Register'!$D:$D,MATCH("P050142|I",'iCoA Register'!$P:$P,0)),"")} -> 46157 | J22: {=IFERROR(INDEX('CoQ Register'!$D:$D,MATCH("P050142|I",'CoQ Register'!$S:$S,0)),"")} -> 46169 | K22: BSS1024_01/2 | L22: P050142 | M22: Blue Sunset Sherbet | N22: — not given — | O22: 30.09.2025 | P22: 30.09.2025 | Q22: Ident A + Ident B + Foreign matter | R22: Conforms | S22: Conforms | T22: Conforms | U22: — no cannabinoid certificate from the initial testing — | Y22: registered — issued with the legacy series on 15.05.2026
A23: 22 | B23: initial release | C23: {=IFERROR(INDEX('iCoA Register'!$B:$B,MATCH("P050162|I",'iCoA Register'!$P:$P,0)),"— at issue —")} -> iCoA-PP_26-022 | D23: {=IFERROR(INDEX('CoQ Register'!$B:$B,MATCH("P050162|I",'CoQ Register'!$S:$S,0)),"—")} -> CoQ-PP_26-022 | E23: iCoA-PP-2025-0015 / CoQ-PP-2025-0015 | F23: legacy | G23: 30.09.2025 | H23: 30.09.2025 | I23: {=IFERROR(INDEX('iCoA Register'!$D:$D,MATCH("P050162|I",'iCoA Register'!$P:$P,0)),"")} -> 46157 | J23: {=IFERROR(INDEX('CoQ Register'!$D:$D,MATCH("P050162|I",'CoQ Register'!$S:$S,0)),"")} -> 46169 | K23: CJ052501/01 | L23: P050162 | M23: Cup Junky | N23: 20.08.2025 | O23: 30.09.2025 – 01.10.2025 | P23: 01.10.2025 | Q23: Ident A + Ident B + Foreign matter | R23: Conforms | S23: Conforms | T23: Conforms | U23: ППК25280, (17.09.2025) [CNP] | Y23: registered — issued with the legacy series on 15.05.2026
A24: 23 | B24: initial release | C24: {=IFERROR(INDEX('iCoA Register'!$B:$B,MATCH("P050172|I",'iCoA Register'!$P:$P,0)),"— at issue —")} -> iCoA-PP_26-023 | D24: {=IFERROR(INDEX('CoQ Register'!$B:$B,MATCH("P050172|I",'CoQ Register'!$S:$S,0)),"—")} -> CoQ-PP_26-023 | E24: (assigned on issue) | F24: legacy | G24: 17.09.2025 | H24: 01.10.2025 | I24: {=IFERROR(INDEX('iCoA Register'!$D:$D,MATCH("P050172|I",'iCoA Register'!$P:$P,0)),"")} -> 46157 | J24: {=IFERROR(INDEX('CoQ Register'!$D:$D,MATCH("P050172|I",'CoQ Register'!$S:$S,0)),"")} -> 46169 | K24: CJ052501/02 | L24: P050172 | M24: Cap Junky | N24: 20.08.2025 | O24: 01.10.2025 – 02.10.2025 (the issuance plan's basis: 17.09.2025) | P24: 02.10.2025 | Q24: Ident A + Ident B + Foreign matter | R24: Conforms | S24: Conforms | T24: Conforms | U24: ППК25281, (17.09.2025) [CNP] | Y24: registered — issued with the legacy series on 15.05.2026
A25: 24 | B25: initial release | C25: {=IFERROR(INDEX('iCoA Register'!$B:$B,MATCH("P050182|I",'iCoA Register'!$P:$P,0)),"— at issue —")} -> iCoA-PP_26-024 | D25: {=IFERROR(INDEX('CoQ Register'!$B:$B,MATCH("P050182|I",'CoQ Register'!$S:$S,0)),"—")} -> CoQ-PP_26-024 | E25: iCoA-PP-2025-0016 / CoQ-PP-2025-0016 | F25: legacy | G25: 03.10.2025 | H25: 03.10.2025 | I25: {=IFERROR(INDEX('iCoA Register'!$D:$D,MATCH("P050182|I",'iCoA Register'!$P:$P,0)),"")} -> 46157 | J25: {=IFERROR(INDEX('CoQ Register'!$D:$D,MATCH("P050182|I",'CoQ Register'!$S:$S,0)),"")} -> 46169 | K25: HPA052501 | L25: P050182 | M25: High Pro Amnesia | N25: 21.08.2025 – 23.08.2025 | O25: 03.10.2025 – 09.10.2025 | P25: 09.10.2025 | Q25: Ident A + Ident B + Foreign matter | R25: Conforms | S25: Conforms | T25: Conforms | U25: ППК25278, (19.09.2025) [CNP] | Y25: registered — issued with the legacy series on 15.05.2026
A26: 25 | B26: initial release | C26: {=IFERROR(INDEX('iCoA Register'!$B:$B,MATCH("P050192|I",'iCoA Register'!$P:$P,0)),"— at issue —")} -> iCoA-PP_26-025 | D26: {=IFERROR(INDEX('CoQ Register'!$B:$B,MATCH("P050192|I",'CoQ Register'!$S:$S,0)),"—")} -> CoQ-PP_26-025 | E26: iCoA-PP-2025-0017 / CoQ-PP-2025-0017 | F26: legacy | G26: 10.10.2025 | H26: 10.10.2025 | I26: {=IFERROR(INDEX('iCoA Register'!$D:$D,MATCH("P050192|I",'iCoA Register'!$P:$P,0)),"")} -> 46157 | J26: {=IFERROR(INDEX('CoQ Register'!$D:$D,MATCH("P050192|I",'CoQ Register'!$S:$S,0)),"")} -> 46169 | K26: BSS052501 | L26: P050192 | M26: Sleepy Joe | N26: 01.09.2025 – 03.09.2025 | O26: 10.10.2025 – 21.10.2025 | P26: 21.10.2025 | Q26: Ident A + Ident B + Foreign matter | R26: Conforms | S26: Conforms | T26: Conforms | U26: NGP-QCG-SOP-024 F3, (28.11.2025) [NGP] | Y26: registered — issued with the legacy series on 15.05.2026
A27: 26 | B27: initial release | C27: {=IFERROR(INDEX('iCoA Register'!$B:$B,MATCH("P050202|I",'iCoA Register'!$P:$P,0)),"— at issue —")} -> iCoA-PP_26-026 | D27: {=IFERROR(INDEX('CoQ Register'!$B:$B,MATCH("P050202|I",'CoQ Register'!$S:$S,0)),"—")} -> CoQ-PP_26-026 | E27: (assigned on issue) | F27: legacy | G27: 11.05.2026 | H27: 30.10.2025 | I27: {=IFERROR(INDEX('iCoA Register'!$D:$D,MATCH("P050202|I",'iCoA Register'!$P:$P,0)),"")} -> 46157 | J27: {=IFERROR(INDEX('CoQ Register'!$D:$D,MATCH("P050202|I",'CoQ Register'!$S:$S,0)),"")} -> 46169 | K27: GP062501 | L27: P050202 | M27: Grape Pie | N27: 15.09.2025 – 17.09.2025 | O27: 30.10.2025 – 07.11.2025 (the issuance plan's basis: 11.05.2026) | P27: 07.11.2025 | Q27: Ident A + Ident B + Foreign matter | R27: Conforms | S27: Conforms | T27: Conforms | U27: NGP-QCG-SOP-024 F3, (28.11.2025) [NGP] | Y27: registered — issued with the legacy series on 15.05.2026
A28: 27 | B28: initial release | C28: {=IFERROR(INDEX('iCoA Register'!$B:$B,MATCH("P050212|I",'iCoA Register'!$P:$P,0)),"— at issue —")} -> iCoA-PP_26-027 | D28: {=IFERROR(INDEX('CoQ Register'!$B:$B,MATCH("P050212|I",'CoQ Register'!$S:$S,0)),"—")} -> CoQ-PP_26-027 | E28: (assigned on issue) | F28: legacy | G28: 24.01.2026 | H28: 18.11.2025 | I28: {=IFERROR(INDEX('iCoA Register'!$D:$D,MATCH("P050212|I",'iCoA Register'!$P:$P,0)),"")} -> 46157 | J28: {=IFERROR(INDEX('CoQ Register'!$D:$D,MATCH("P050212|I",'CoQ Register'!$S:$S,0)),"")} -> 46169 | K28: CJ062501/2 | L28: P050212 | M28: Cap Junkie | N28: 23.09.2025 – 24.09.2025 | O28: 18.11.2025 – 24.11.2025 (the issuance plan's basis: 24.01.2026) | P28: 24.11.2025 | Q28: Ident A + Ident B + Foreign matter | R28: Conforms | S28: Conforms | T28: Conforms | U28: ППК25322, (23.10.2025) [CNP] | Y28: registered — issued with the legacy series on 15.05.2026
A29: 28 | B29: initial release | C29: {=IFERROR(INDEX('iCoA Register'!$B:$B,MATCH("P050222|I",'iCoA Register'!$P:$P,0)),"— at issue —")} -> iCoA-PP_26-028 | D29: {=IFERROR(INDEX('CoQ Register'!$B:$B,MATCH("P050222|I",'CoQ Register'!$S:$S,0)),"—")} -> CoQ-PP_26-028 | E29: iCoA-PP-2025-0018 / CoQ-PP-2025-0018 | F29: legacy | G29: 24.11.2025 | H29: 24.11.2025 | I29: {=IFERROR(INDEX('iCoA Register'!$D:$D,MATCH("P050222|I",'iCoA Register'!$P:$P,0)),"")} -> 46157 | J29: {=IFERROR(INDEX('CoQ Register'!$D:$D,MATCH("P050222|I",'CoQ Register'!$S:$S,0)),"")} -> 46169 | K29: CJ062501/1 | L29: P050222 | M29: Cap Junkie | N29: 23.09.2025 | O29: 24.11.2025 – 25.11.2025 | P29: 25.11.2025 | Q29: Ident A + Ident B + Foreign matter | R29: Conforms | S29: Conforms | T29: Conforms | U29: ППК25321, (23.10.2025) [CNP] | Y29: registered — issued with the legacy series on 15.05.2026
A30: 29 | B30: initial release | C30: {=IFERROR(INDEX('iCoA Register'!$B:$B,MATCH("P050252|I",'iCoA Register'!$P:$P,0)),"— at issue —")} -> iCoA-PP_26-029 | D30: {=IFERROR(INDEX('CoQ Register'!$B:$B,MATCH("P050252|I",'CoQ Register'!$S:$S,0)),"—")} -> CoQ-PP_26-029 | E30: (assigned on issue) | F30: legacy | G30: 02.12.2025 | H30: 27.11.2025 | I30: {=IFERROR(INDEX('iCoA Register'!$D:$D,MATCH("P050252|I",'iCoA Register'!$P:$P,0)),"")} -> 46157 | J30: {=IFERROR(INDEX('CoQ Register'!$D:$D,MATCH("P050252|I",'CoQ Register'!$S:$S,0)),"")} -> 46169 | K30: CJ072501 | L30: P050252 | M30: Cap Junky | N30: 27.10.2025 | O30: 27.11.2025 – 28.11.2025 (the issuance plan's basis: 02.12.2025) | P30: 28.11.2025 | Q30: Ident A + Ident B + Foreign matter | R30: Conforms | S30: Conforms | T30: Conforms | U30: ППК25367, (28.11.2025) [CNP] | Y30: registered — issued with the legacy series on 15.05.2026
A31: 30 | B31: initial release | C31: {=IFERROR(INDEX('iCoA Register'!$B:$B,MATCH("P050262|I",'iCoA Register'!$P:$P,0)),"— at issue —")} -> iCoA-PP_26-030 | D31: {=IFERROR(INDEX('CoQ Register'!$B:$B,MATCH("P050262|I",'CoQ Register'!$S:$S,0)),"—")} -> CoQ-PP_26-030 | E31: (assigned on issue) | F31: legacy | G31: 02.12.2025 | H31: 01.12.2025 | I31: {=IFERROR(INDEX('iCoA Register'!$D:$D,MATCH("P050262|I",'iCoA Register'!$P:$P,0)),"")} -> 46157 | J31: {=IFERROR(INDEX('CoQ Register'!$D:$D,MATCH("P050262|I",'CoQ Register'!$S:$S,0)),"")} -> 46169 | K31: WC072501 | L31: P050262 | M31: Wedding Crusher | N31: 27.10.2025 – 28.10.2025 | O31: 01.12.2025 (the issuance plan's basis: 02.12.2025) | P31: 01.12.2025 | Q31: Ident A + Ident B + Foreign matter | R31: Conforms | S31: Conforms | T31: Conforms | U31: ППК25369, (28.11.2025) [CNP] | Y31: registered — issued with the legacy series on 15.05.2026
A32: 31 | B32: initial release | C32: {=IFERROR(INDEX('iCoA Register'!$B:$B,MATCH("P050272|I",'iCoA Register'!$P:$P,0)),"— at issue —")} -> iCoA-PP_26-031 | D32: {=IFERROR(INDEX('CoQ Register'!$B:$B,MATCH("P050272|I",'CoQ Register'!$S:$S,0)),"—")} -> CoQ-PP_26-031 | E32: (assigned on issue) | F32: legacy | G32: 21.01.2026 | H32: 02.12.2025 | I32: {=IFERROR(INDEX('iCoA Register'!$D:$D,MATCH("P050272|I",'iCoA Register'!$P:$P,0)),"")} -> 46157 | J32: {=IFERROR(INDEX('CoQ Register'!$D:$D,MATCH("P050272|I",'CoQ Register'!$S:$S,0)),"")} -> 46169 | K32: PM072501 | L32: P050272 | M32: Permanent Marker | N32: 27.10.2025 | O32: 02.12.2025 – 03.12.2025 (the issuance plan's basis: 21.01.2026) | P32: 03.12.2025 | Q32: Ident A + Ident B + Foreign matter | R32: Conforms | S32: Conforms | T32: Conforms | U32: ППК25368, (28.11.2025) [CNP] | Y32: registered — issued with the legacy series on 15.05.2026
A33: 32 | B33: initial release | C33: {=IFERROR(INDEX('iCoA Register'!$B:$B,MATCH("P050282|I",'iCoA Register'!$P:$P,0)),"— at issue —")} -> iCoA-PP_26-032 | D33: {=IFERROR(INDEX('CoQ Register'!$B:$B,MATCH("P050282|I",'CoQ Register'!$S:$S,0)),"—")} -> CoQ-PP_26-032 | E33: iCoA-PP-2025-0019 / CoQ-PP-2025-0019 | F33: legacy | G33: 03.12.2025 | H33: 03.12.2025 | I33: {=IFERROR(INDEX('iCoA Register'!$D:$D,MATCH("P050282|I",'iCoA Register'!$P:$P,0)),"")} -> 46157 | J33: {=IFERROR(INDEX('CoQ Register'!$D:$D,MATCH("P050282|I",'CoQ Register'!$S:$S,0)),"")} -> 46169 | K33: CLE072501 | L33: P050282 | M33: Clemosa a bud | N33: 28.10.2025 | O33: 03.12.2025 – 04.12.2025 | P33: 04.12.2025 | Q33: Ident A + Ident B + Foreign matter | R33: Conforms | S33: Conforms | T33: Conforms | U33: ППК25370, (28.11.2025) [CNP] | Y33: registered — issued with the legacy series on 15.05.2026
A34: 33 | B34: initial release | C34: {=IFERROR(INDEX('iCoA Register'!$B:$B,MATCH("P050292|I",'iCoA Register'!$P:$P,0)),"— at issue —")} -> iCoA-PP_26-033 | D34: {=IFERROR(INDEX('CoQ Register'!$B:$B,MATCH("P050292|I",'CoQ Register'!$S:$S,0)),"—")} -> CoQ-PP_26-033 | E34: (assigned on issue) | F34: legacy | G34: 21.01.2026 | H34: 15.12.2025 | I34: {=IFERROR(INDEX('iCoA Register'!$D:$D,MATCH("P050292|I",'iCoA Register'!$P:$P,0)),"")} -> 46157 | J34: {=IFERROR(INDEX('CoQ Register'!$D:$D,MATCH("P050292|I",'CoQ Register'!$S:$S,0)),"")} -> 46169 | K34: GP072501/1 | L34: P050292 | M34: Grape Pie | N34: 11.11.2025 – 13.11.2025 | O34: 15.12.2025 – 21.12.2025 (the issuance plan's basis: 21.01.2026) | P34: 21.12.2025 | Q34: Ident A + Ident B + Foreign matter | R34: Conforms | S34: Conforms | T34: Conforms | U34: ППК25378, (12.12.2025) [CNP] | Y34: registered — issued with the legacy series on 15.05.2026
A35: 34 | B35: initial release | C35: {=IFERROR(INDEX('iCoA Register'!$B:$B,MATCH("P050302|I",'iCoA Register'!$P:$P,0)),"— at issue —")} -> iCoA-PP_26-034 | D35: {=IFERROR(INDEX('CoQ Register'!$B:$B,MATCH("P050302|I",'CoQ Register'!$S:$S,0)),"—")} -> CoQ-PP_26-034 | E35: iCoA-PP-2025-0020 / CoQ-PP-2025-0020 | F35: legacy | G35: 22.12.2025 | H35: 22.12.2025 | I35: {=IFERROR(INDEX('iCoA Register'!$D:$D,MATCH("P050302|I",'iCoA Register'!$P:$P,0)),"")} -> 46157 | J35: {=IFERROR(INDEX('CoQ Register'!$D:$D,MATCH("P050302|I",'CoQ Register'!$S:$S,0)),"")} -> 46169 | K35: GP072501/2 | L35: P050302 | M35: Grape Pie | N35: 13.11.2025 | O35: 22.12.2025 | P35: 22.12.2025 | Q35: Ident A + Ident B + Foreign matter | R35: Conforms | S35: Conforms | T35: Conforms | U35: ППК25379, (12.12.2025) [CNP] | Y35: registered — issued with the legacy series on 15.05.2026
A36: 35 | B36: initial release | C36: {=IFERROR(INDEX('iCoA Register'!$B:$B,MATCH("P050312|I",'iCoA Register'!$P:$P,0)),"— at issue —")} -> iCoA-PP_26-035 | D36: {=IFERROR(INDEX('CoQ Register'!$B:$B,MATCH("P050312|I",'CoQ Register'!$S:$S,0)),"—")} -> CoQ-PP_26-035 | E36: iCoA-PP-2025-0021 / CoQ-PP-2025-0021 | F36: legacy | G36: 23.12.2025 | H36: 23.12.2025 | I36: {=IFERROR(INDEX('iCoA Register'!$D:$D,MATCH("P050312|I",'iCoA Register'!$P:$P,0)),"")} -> 46157 | J36: {=IFERROR(INDEX('CoQ Register'!$D:$D,MATCH("P050312|I",'CoQ Register'!$S:$S,0)),"")} -> 46169 | K36: GP082501/1 | L36: P050312 | M36: Grape Pie | N36: 19.11.2025 – 20.11.2025 | O36: 23.12.2025 – 26.12.2025 | P36: 26.12.2025 | Q36: Ident A + Ident B + Foreign matter | R36: Conforms | S36: Conforms | T36: Conforms | U36: ППК25380, (12.12.2025) [CNP] | Y36: registered — issued with the legacy series on 15.05.2026
A37: 36 | B37: initial release | C37: {=IFERROR(INDEX('iCoA Register'!$B:$B,MATCH("P050322|I",'iCoA Register'!$P:$P,0)),"— at issue —")} -> iCoA-PP_26-036 | D37: {=IFERROR(INDEX('CoQ Register'!$B:$B,MATCH("P050322|I",'CoQ Register'!$S:$S,0)),"—")} -> CoQ-PP_26-036 | E37: iCoA-PP-2025-0022 / CoQ-PP-2025-0022 | F37: legacy | G37: 26.12.2025 | H37: 26.12.2025 | I37: {=IFERROR(INDEX('iCoA Register'!$D:$D,MATCH("P050322|I",'iCoA Register'!$P:$P,0)),"")} -> 46157 | J37: {=IFERROR(INDEX('CoQ Register'!$D:$D,MATCH("P050322|I",'CoQ Register'!$S:$S,0)),"")} -> 46169 | K37: GP082501/2 | L37: P050322 | M37: Grape Pie | N37: 20.11.2025 | O37: 26.12.2025 | P37: 26.12.2025 | Q37: Ident A + Ident B + Foreign matter | R37: Conforms | S37: Conforms | T37: Conforms | U37: ППК25381, (12.12.2025) [CNP] | Y37: registered — issued with the legacy series on 15.05.2026
A38: 37 | B38: initial release | C38: {=IFERROR(INDEX('iCoA Register'!$B:$B,MATCH("P060012|I",'iCoA Register'!$P:$P,0)),"— at issue —")} -> iCoA-PP_26-037 | D38: {=IFERROR(INDEX('CoQ Register'!$B:$B,MATCH("P060012|I",'CoQ Register'!$S:$S,0)),"—")} -> CoQ-PP_26-037 | E38: iCoA-PP-2026-0001 / CoQ-PP-2026-0001 | F38: legacy | G38: 13.01.2026 | H38: 13.01.2026 | I38: {=IFERROR(INDEX('iCoA Register'!$D:$D,MATCH("P060012|I",'iCoA Register'!$P:$P,0)),"")} -> 46157 | J38: {=IFERROR(INDEX('CoQ Register'!$D:$D,MATCH("P060012|I",'CoQ Register'!$S:$S,0)),"")} -> 46169 | K38: WC082501 | L38: P060012 | M38: Wedding Crasher | N38: 09.12.2025 | O38: 13.01.2026 – 14.01.2026 | P38: 14.01.2026 | Q38: Ident A + Ident B + Foreign matter | R38: Conforms | S38: Conforms | T38: Conforms | U38: ППК26001, (21.01.2026) [CNP] | Y38: registered — issued with the legacy series on 15.05.2026
A39: 38 | B39: initial release | C39: {=IFERROR(INDEX('iCoA Register'!$B:$B,MATCH("P060022|I",'iCoA Register'!$P:$P,0)),"— at issue —")} -> iCoA-PP_26-038 | D39: {=IFERROR(INDEX('CoQ Register'!$B:$B,MATCH("P060022|I",'CoQ Register'!$S:$S,0)),"—")} -> CoQ-PP_26-038 | E39: iCoA-PP-2026-0002 / CoQ-PP-2026-0002 | F39: legacy | G39: 16.01.2026 | H39: 16.01.2026 | I39: {=IFERROR(INDEX('iCoA Register'!$D:$D,MATCH("P060022|I",'iCoA Register'!$P:$P,0)),"")} -> 46157 | J39: {=IFERROR(INDEX('CoQ Register'!$D:$D,MATCH("P060022|I",'CoQ Register'!$S:$S,0)),"")} -> 46169 | K39: CJ082501/1 | L39: P060022 | M39: Cap Junky | N39: 09.12.2025 – 10.12.2025 | O39: 16.01.2026 | P39: 16.01.2026 | Q39: Ident A + Ident B + Foreign matter | R39: Conforms | S39: Conforms | T39: Conforms | U39: ППК26002, (21.01.2026) [CNP] | Y39: registered — issued with the legacy series on 15.05.2026
A40: 39 | B40: initial release | C40: {=IFERROR(INDEX('iCoA Register'!$B:$B,MATCH("P060032|I",'iCoA Register'!$P:$P,0)),"— at issue —")} -> iCoA-PP_26-039 | D40: {=IFERROR(INDEX('CoQ Register'!$B:$B,MATCH("P060032|I",'CoQ Register'!$S:$S,0)),"—")} -> CoQ-PP_26-039 | E40: iCoA-PP-2026-0003 / CoQ-PP-2026-0003 | F40: legacy | G40: 29.01.2026 | H40: 29.01.2026 | I40: {=IFERROR(INDEX('iCoA Register'!$D:$D,MATCH("P060032|I",'iCoA Register'!$P:$P,0)),"")} -> 46157 | J40: {=IFERROR(INDEX('CoQ Register'!$D:$D,MATCH("P060032|I",'CoQ Register'!$S:$S,0)),"")} -> 46169 | K40: CJ082501/2 | L40: P060032 | M40: Cap Junky | N40: 10.12.2025 | O40: 29.01.2026 | P40: 29.01.2026 | Q40: Ident A + Ident B + Foreign matter | R40: Conforms | S40: Conforms | T40: Conforms | U40: ППК26003, (21.01.2026) [CNP] | Y40: registered — issued with the legacy series on 15.05.2026
A41: 40 | B41: initial release | C41: {=IFERROR(INDEX('iCoA Register'!$B:$B,MATCH("P060042|I",'iCoA Register'!$P:$P,0)),"— at issue —")} -> iCoA-PP_26-040 | D41: {=IFERROR(INDEX('CoQ Register'!$B:$B,MATCH("P060042|I",'CoQ Register'!$S:$S,0)),"—")} -> CoQ-PP_26-040 | E41: iCoA-PP-2026-0004 / CoQ-PP-2026-0004 | F41: legacy | G41: 29.01.2026 | H41: 29.01.2026 | I41: {=IFERROR(INDEX('iCoA Register'!$D:$D,MATCH("P060042|I",'iCoA Register'!$P:$P,0)),"")} -> 46157 | J41: {=IFERROR(INDEX('CoQ Register'!$D:$D,MATCH("P060042|I",'CoQ Register'!$S:$S,0)),"")} -> 46169 | K41: OPM092501 | L41: P060042 | M41: Orange Punch Mimosa | N41: 12.12.2025 | O41: 29.01.2026 | P41: 29.01.2026 | Q41: Ident A + Ident B + Foreign matter | R41: Conforms | S41: Conforms | T41: Conforms | U41: ППК26008, (21.01.2026) [CNP] | Y41: registered — issued with the legacy series on 15.05.2026
A42: 41 | B42: initial release | C42: {=IFERROR(INDEX('iCoA Register'!$B:$B,MATCH("P060052|I",'iCoA Register'!$P:$P,0)),"— at issue —")} -> iCoA-PP_26-041 | D42: {=IFERROR(INDEX('CoQ Register'!$B:$B,MATCH("P060052|I",'CoQ Register'!$S:$S,0)),"—")} -> CoQ-PP_26-041 | E42: (assigned on issue) | F42: legacy | G42: 20.02.2026 | H42: 30.01.2026 | I42: {=IFERROR(INDEX('iCoA Register'!$D:$D,MATCH("P060052|I",'iCoA Register'!$P:$P,0)),"")} -> 46157 | J42: {=IFERROR(INDEX('CoQ Register'!$D:$D,MATCH("P060052|I",'CoQ Register'!$S:$S,0)),"")} -> 46169 | K42: AB092501 | L42: P060052 | M42: Apple and Banana | N42: 11.12.2025 | O42: 30.01.2026 (the issuance plan's basis: 20.02.2026) | P42: 30.01.2026 | Q42: Ident A + Ident B + Foreign matter | R42: Conforms | S42: Conforms | T42: Conforms | U42: ППК26005, (21.01.2026) [CNP] | Y42: registered — issued with the legacy series on 15.05.2026
A43: 42 | B43: initial release | C43: {=IFERROR(INDEX('iCoA Register'!$B:$B,MATCH("P060062|I",'iCoA Register'!$P:$P,0)),"— at issue —")} -> iCoA-PP_26-042 | D43: {=IFERROR(INDEX('CoQ Register'!$B:$B,MATCH("P060062|I",'CoQ Register'!$S:$S,0)),"—")} -> CoQ-PP_26-042 | E43: iCoA-PP-2026-0005 / CoQ-PP-2026-0005 | F43: legacy | G43: 30.01.2026 | H43: 30.01.2026 | I43: {=IFERROR(INDEX('iCoA Register'!$D:$D,MATCH("P060062|I",'iCoA Register'!$P:$P,0)),"")} -> 46157 | J43: {=IFERROR(INDEX('CoQ Register'!$D:$D,MATCH("P060062|I",'CoQ Register'!$S:$S,0)),"")} -> 46169 | K43: PM092501 | L43: P060062 | M43: Permanent Market | N43: 11.12.2025 | O43: 30.01.2026 | P43: 30.01.2026 | Q43: Ident A + Ident B + Foreign matter | R43: Conforms | S43: Conforms | T43: Conforms | U43: ППК26004, (21.01.2026) [CNP] | Y43: registered — issued with the legacy series on 15.05.2026
A44: 43 | B44: initial release | C44: {=IFERROR(INDEX('iCoA Register'!$B:$B,MATCH("P060072|I",'iCoA Register'!$P:$P,0)),"— at issue —")} -> iCoA-PP_26-043 | D44: {=IFERROR(INDEX('CoQ Register'!$B:$B,MATCH("P060072|I",'CoQ Register'!$S:$S,0)),"—")} -> CoQ-PP_26-043 | E44: iCoA-PP-2026-0006 / CoQ-PP-2026-0006 | F44: legacy | G44: 02.02.2026 | H44: 02.02.2026 | I44: {=IFERROR(INDEX('iCoA Register'!$D:$D,MATCH("P060072|I",'iCoA Register'!$P:$P,0)),"")} -> 46157 | J44: {=IFERROR(INDEX('CoQ Register'!$D:$D,MATCH("P060072|I",'CoQ Register'!$S:$S,0)),"")} -> 46169 | K44: CJ092501 | L44: P060072 | M44: Cap Junky | N44: 12.12.2025 | O44: 02.02.2026 | P44: 02.02.2026 | Q44: Ident A + Ident B + Foreign matter | R44: Conforms | S44: Conforms | T44: Conforms | U44: ППК26007, (21.01.2026) [CNP] | Y44: registered — issued with the legacy series on 15.05.2026
A45: 44 | B45: initial release | C45: {=IFERROR(INDEX('iCoA Register'!$B:$B,MATCH("P060082|I",'iCoA Register'!$P:$P,0)),"— at issue —")} -> iCoA-PP_26-044 | D45: {=IFERROR(INDEX('CoQ Register'!$B:$B,MATCH("P060082|I",'CoQ Register'!$S:$S,0)),"—")} -> CoQ-PP_26-044 | E45: iCoA-PP-2026-0007 / CoQ-PP-2026-0007 | F45: legacy | G45: 02.02.2026 | H45: 02.02.2026 | I45: {=IFERROR(INDEX('iCoA Register'!$D:$D,MATCH("P060082|I",'iCoA Register'!$P:$P,0)),"")} -> 46157 | J45: {=IFERROR(INDEX('CoQ Register'!$D:$D,MATCH("P060082|I",'CoQ Register'!$S:$S,0)),"")} -> 46169 | K45: SJ0925021 | L45: P060082 | N45: 11.12.2025 – 12.12.2025 | O45: 02.02.2026 | P45: 02.02.2026 | Q45: Ident A + Ident B + Foreign matter | R45: Conforms | S45: Conforms | T45: Conforms | U45: ППК26006, (21.01.2026) [CNP] | Y45: registered — issued with the legacy series on 15.05.2026
